Workbook
Name _Key1: #REF!
Name _Order1: 255
Name _Sort: #REF!
Name All_Outpatients_diagnosed: '[1]Summary people'!$S$20
Name Ambulanciers_per_bed: '[1]Staff&infrastructure assumption'!$C$14
Name ARTcoverage: #REF!
Name asymp_rate: [2]Summary!$H$3
Name Av_days_month: '[3]Setting 1 Costs'!$B$9
Name Beds_occupied: '[3]Setting 1 Costs'!$B$8
Name BedStay_Critical: '[1]Patient & case assumptions'!$C$17
Name BedStay_Severe: '[1]Patient & case assumptions'!$C$16
Name Buffer_stock: '[4]Model Assumption'!$E$127
Name Caretaker_to_outpatient: '[1]Patient & case assumptions'!$C$24
Name Caretakers_per_bed: '[1]Staff&infrastructure assumption'!$C$13
Name COST_METHOD: #REF!
Name CostYear: [5]Inflation!$B$1
Name CostYear: Inflation!$B$1
Name CostYrr: Inflation!$B$1
Name CovLev: #REF!
Name cpap: [2]Selection!$D$37
Name cpap_cost: '[2]Cost inputs'!$F$38
Name cpap_cov: [2]Selection!$G$37
Name CriticalCasePercentage: '[1]Patient & case assumptions'!$C$13
Name cur_1: [6]Start!$C$22
Name currency: [7]Assumptions!$O$9
Name CURRENCY: #REF!
Name Current_OutBreak_Week_Number: '[1]Total forecast by item'!$E$14
Name CurrResults: #REF!
Name CurrYear: [8]Projection!$E$6
Name CutOffMaxTests: '[1]Patient & case assumptions'!$C$29
Name d: [9]Sheet5!$A:$C
Name DataDate: [10]OfDates!$B$2
Name DataWuenic: [10]OfDates!$B$4
Name DataYear: [10]OfDates!$B$6
Name date: Title!$M$5
Name DDL_Private: [11]drop_down_lists!$G$60:$G$63
Name DDL_yes_no_NR_ND: [11]drop_down_lists!$F$33:$F$36
Name Depr_Category: [12]!depreciation[Category]
Name DHIS_HCavg: '[5]ART PPP'!$C$18
Name DHIS_HCavg: 'ART PPP'!$C$18
Name Discount_Rate: '[12]Model parameters'!$B$8
Name DoublingTime_Best: '[1]Epi curve calcs'!$Q$13
Name DoublingTime_Medium: '[1]Epi curve calcs'!$J$13
Name DoublingTime_Worst: '[1]Epi curve calcs'!$C$13
Name drug_costs: '[2]Cost inputs'!$B$117:$F$125
Name Epi_drop_rate: '[4]Model Assumption'!$E$133
Name Epi_Growth_rate: '[4]Model Assumption'!$E$132
Name Equipment_usage_table: '[1]Equipment per person per day'!$D$14:$I$105
Name ex_rate_2017: [13]Inflation!$F$21
Name exr: [13]SummaryInterventions!$A$27
Name exrate: [5]ZARtoUSD!$F$5
Name exrate: '[13]ZAR-USD'!$E$7
Name exrate: ZARtoUSD!$F$5
Name Fast_doubling_rate: '[1]Epi curve assumptions'!$C$16
Name Filename: [14]drop_down_lists!$H$3
Name HCW_per_lab: '[1]Staff&infrastructure assumption'!$C$28
Name HCWs_per_bed: '[1]Staff&infrastructure assumption'!$C$11
Name hfnc: [2]Selection!$D$34
Name hfnc_cost: '[2]Cost inputs'!$F$45
Name hfnc_cov: [2]Selection!$G$34

Sheet Title
M5: Version 10.1, 1 Apr 2025
L34: Lise Jamieson, Khumo Modiba, Gesine Meyer-Rath
M35: Queries: gesine@bu.edu
K41: Suggested citation:
K42: Jamieson L, Modiba K, Meyer-Rath G (2024) National HIV Unit Cost Model, South Africa. Health Economics and Epidemiology Research Office, University of the Witwatersrand, Johannesburg.

Sheet Summary of unit costs
A1: Intervention | C1: Population/notes | D1: Est population size (Thembisa 4.7+) | E1: Costing method | F1: Programme Area | G1: Unit Cost (2024 ZAR) | H1: Unit cost (2024 USD) | I1: Unit | J1: Validate % columns | K1: Consumables | L1: Drugs | M1: Equipment | N1: Lab Tests | O1: Overheads | P1: Staff | Q1: Consumables | R1: Drugs | S1: Equipment | T1: Lab Tests | U1: Overheads | V1: Staff
A2: ART Adults (1st line 1st year) | C2: ART adults starting ART on first line in given year | D2: 208375.3 | E2: Ingredients | F2: ART | G2: {=IF(E2="Literature",INDEX(LiteratureCost!$I$2:$I$10,MATCH('Summary of unit costs'!A2,LiteratureCost!$A$2:$A$10,0)),INDEX(InterventionCosts!$L$1:$L$2363,MATCH(A2,IF(InterventionCosts!$F$1:$F$2363="Cost per intervention",InterventionCosts!$A$1:$A$2363),0)))} -> 5352.6248 | H2: =G2/exrate -> 286.84009 | I2: {=IF(E2="Literature",INDEX(LiteratureCost!$G$2:$G$22,MATCH('Summary of unit costs'!A2,LiteratureCost!$A$2:$A$22,0)),INDEX(InterventionCosts!$L$1:$L$3432,MATCH(A2,IF(InterventionCosts!$F$1:$F$3432="Unit",InterventionCosts!$A$1:$A$3432),0)))} -> per person per year | J2: =G2/SUM(Q2:V2) -> 1 | K2: =Q2/$G2 -> 0 | L2: =R2/$G2 -> 0.24332172 | M2: =S2/$G2 -> 0 | N2: =T2/$G2 -> 0.21593891 | O2: =U2/$G2 -> 0.12432272 | P2: =V2/$G2 -> 0.41641666 | Q2: =SUMIFS(InterventionCosts!$K$2:$K$3432,InterventionCosts!$D$2:$D$3432,'Summary of unit costs'!Q$1,InterventionCosts!$A$2:$A$3432,'Summary of unit costs'!$A2) -> 0 | R2: =SUMIFS(InterventionCosts!$K$2:$K$3432,InterventionCosts!$D$2:$D$3432,'Summary of unit costs'!R$1,InterventionCosts!$A$2:$A$3432,'Summary of unit costs'!$A2) -> 1302.4098 | S2: =SUMIFS(InterventionCosts!$K$2:$K$3432,InterventionCosts!$D$2:$D$3432,'Summary of unit costs'!S$1,InterventionCosts!$A$2:$A$3432,'Summary of unit costs'!$A2) -> 0 | T2: =SUMIFS(InterventionCosts!$K$2:$K$3432,InterventionCosts!$D$2:$D$3432,'Summary of unit costs'!T$1,InterventionCosts!$A$2:$A$3432,'Summary of unit costs'!$A2) -> 1155.84 | U2: =SUMIFS(InterventionCosts!$K$2:$K$3432,InterventionCosts!$D$2:$D$3432,'Summary of unit costs'!U$1,InterventionCosts!$A$2:$A$3432,'Summary of unit costs'!$A2) -> 665.45285 | V2: =SUMIFS(InterventionCosts!$K$2:$K$3432,InterventionCosts!$D$2:$D$3432,'Summary of unit costs'!V$1,InterventionCosts!$A$2:$A$3432,'Summary of unit costs'!$A2) -> 2228.9221
A3: ART Adults (1st line followup) | C3: ART adults in years following starting ART | D3: =5761850-D2 -> 5553474.7 | E3: Ingredients | F3: ART | G3: {=IF(E3="Literature",INDEX(LiteratureCost!$I$2:$I$10,MATCH('Summary of unit costs'!A3,LiteratureCost!$A$2:$A$10,0)),INDEX(InterventionCosts!$L$1:$L$2363,MATCH(A3,IF(InterventionCosts!$F$1:$F$2363="Cost per intervention",InterventionCosts!$A$1:$A$2363),0)))} -> 3346.5773 | H3: =G3/exrate -> 179.33865 | I3: {=IF(E3="Literature",INDEX(LiteratureCost!$G$2:$G$22,MATCH('Summary of unit costs'!A3,LiteratureCost!$A$2:$A$22,0)),INDEX(InterventionCosts!$L$1:$L$3432,MATCH(A3,IF(InterventionCosts!$F$1:$F$3432="Unit",InterventionCosts!$A$1:$A$3432),0)))} -> per person per year | J3: =G3/SUM(Q3:V3) -> 1 | K3: =Q3/$G3 -> 0 | L3: =R3/$G3 -> 0.35555273 | M3: =S3/$G3 -> 0 | N3: =T3/$G3 -> 0.18562702 | O3: =U3/$G3 -> 0.10548849 | P3: =V3/$G3 -> 0.35333176 | Q3: =SUMIFS(InterventionCosts!$K$2:$K$3432,InterventionCosts!$D$2:$D$3432,'Summary of unit costs'!Q$1,InterventionCosts!$A$2:$A$3432,'Summary of unit costs'!$A3) -> 0 | R3: =SUMIFS(InterventionCosts!$K$2:$K$3432,InterventionCosts!$D$2:$D$3432,'Summary of unit costs'!R$1,InterventionCosts!$A$2:$A$3432,'Summary of unit costs'!$A3) -> 1189.8847 | S3: =SUMIFS(InterventionCosts!$K$2:$K$3432,InterventionCosts!$D$2:$D$3432,'Summary of unit costs'!S$1,InterventionCosts!$A$2:$A$3432,'Summary of unit costs'!$A3) -> 0 | T3: =SUMIFS(InterventionCosts!$K$2:$K$3432,InterventionCosts!$D$2:$D$3432,'Summary of unit costs'!T$1,InterventionCosts!$A$2:$A$3432,'Summary of unit costs'!$A3) -> 621.21516 | U3: =SUMIFS(InterventionCosts!$K$2:$K$3432,InterventionCosts!$D$2:$D$3432,'Summary of unit costs'!U$1,InterventionCosts!$A$2:$A$3432,'Summary of unit costs'!$A3) -> 353.02539 | V3: =SUMIFS(InterventionCosts!$K$2:$K$3432,InterventionCosts!$D$2:$D$3432,'Summary of unit costs'!V$1,InterventionCosts!$A$2:$A$3432,'Summary of unit costs'!$A3) -> 1182.452
A4: ART Adults (2nd line followup) | C4: ART adults on second line ART | D4: 577009 | E4: Ingredients | F4: ART | G4: {=IF(E4="Literature",INDEX(LiteratureCost!$I$2:$I$10,MATCH('Summary of unit costs'!A4,LiteratureCost!$A$2:$A$10,0)),INDEX(InterventionCosts!$L$1:$L$2363,MATCH(A4,IF(InterventionCosts!$F$1:$F$2363="Cost per intervention",InterventionCosts!$A$1:$A$2363),0)))} -> 5882.5211 | H4: =G4/exrate -> 315.23653 | I4: {=IF(E4="Literature",INDEX(LiteratureCost!$G$2:$G$22,MATCH('Summary of unit costs'!A4,LiteratureCost!$A$2:$A$22,0)),INDEX(InterventionCosts!$L$1:$L$3432,MATCH(A4,IF(InterventionCosts!$F$1:$F$3432="Unit",InterventionCosts!$A$1:$A$3432),0)))} -> per person per year | J4: =G4/SUM(Q4:V4) -> 1 | K4: =Q4/$G4 -> 0 | L4: =R4/$G4 -> 0.48395472 | M4: =S4/$G4 -> 0 | N4: =T4/$G4 -> 0.18976566 | O4: =U4/$G4 -> 0.07501575 | P4: =V4/$G4 -> 0.25126388 | Q4: =SUMIFS(InterventionCosts!$K$2:$K$3432,InterventionCosts!$D$2:$D$3432,'Summary of unit costs'!Q$1,InterventionCosts!$A$2:$A$3432,'Summary of unit costs'!$A4) -> 0 | R4: =SUMIFS(InterventionCosts!$K$2:$K$3432,InterventionCosts!$D$2:$D$3432,'Summary of unit costs'!R$1,InterventionCosts!$A$2:$A$3432,'Summary of unit costs'!$A4) -> 2846.8739 | S4: =SUMIFS(InterventionCosts!$K$2:$K$3432,InterventionCosts!$D$2:$D$3432,'Summary of unit costs'!S$1,InterventionCosts!$A$2:$A$3432,'Summary of unit costs'!$A4) -> 0 | T4: =SUMIFS(InterventionCosts!$K$2:$K$3432,InterventionCosts!$D$2:$D$3432,'Summary of unit costs'!T$1,InterventionCosts!$A$2:$A$3432,'Summary of unit costs'!$A4) -> 1116.3005 | U4: =SUMIFS(InterventionCosts!$K$2:$K$3432,InterventionCosts!$D$2:$D$3432,'Summary of unit costs'!U$1,InterventionCosts!$A$2:$A$3432,'Summary of unit costs'!$A4) -> 441.28173 | V4: =SUMIFS(InterventionCosts!$K$2:$K$3432,InterventionCosts!$D$2:$D$3432,'Summary of unit costs'!V$1,InterventionCosts!$A$2:$A$3432,'Summary of unit costs'!$A4) -> 1478.0651
A5: ART adult (average cost) | C5: Average cost estimate of above, weighted by est. population size | E5: Ingredients | F5: ART | G5: =SUMPRODUCT(G2:G4,$D$2:$D$4)/SUM($D$2:$D$4) -> 3643.3615 | H5: =G5/exrate -> 195.24293 | I5: per person per year | J5: =G5/SUM(Q5:V5) -> 1 | K5: =Q5/$G5 -> 0 | L5: =R5/$G5 -> 0.36900398 | M5: =S5/$G5 -> 0 | N5: =T5/$G5 -> 0.18769918 | O5: =U5/$G5 -> 0.10191946 | P5: =V5/$G5 -> 0.34137737 | Q5: =SUMPRODUCT(Q2:Q4,$D$2:$D$4)/SUM($D$2:$D$4) -> 0 | R5: =SUMPRODUCT(R2:R4,$D$2:$D$4)/SUM($D$2:$D$4) -> 1344.4149 | S5: =SUMPRODUCT(S2:S4,$D$2:$D$4)/SUM($D$2:$D$4) -> 0 | T5: =SUMPRODUCT(T2:T4,$D$2:$D$4)/SUM($D$2:$D$4) -> 683.85598 | U5: =SUMPRODUCT(U2:U4,$D$2:$D$4)/SUM($D$2:$D$4) -> 371.32945 | V5: =SUMPRODUCT(V2:V4,$D$2:$D$4)/SUM($D$2:$D$4) -> 1243.7612
A6: ART Paeds Neonates | C6: Paediatric ART, first month of birth (as per ART guidelines) | E6: Ingredients | F6: ART | G6: {=IF(E6="Literature",INDEX(LiteratureCost!$I$2:$I$10,MATCH('Summary of unit costs'!A6,LiteratureCost!$A$2:$A$10,0)),INDEX(InterventionCosts!$L$1:$L$2363,MATCH(A6,IF(InterventionCosts!$F$1:$F$2363="Cost per intervention",InterventionCosts!$A$1:$A$2363),0)))} -> 1770.7362 | H6: =G6/exrate -> 94.891411 | I6: {=IF(E6="Literature",INDEX(LiteratureCost!$G$2:$G$22,MATCH('Summary of unit costs'!A6,LiteratureCost!$A$2:$A$22,0)),INDEX(InterventionCosts!$L$1:$L$3432,MATCH(A6,IF(InterventionCosts!$F$1:$F$3432="Unit",InterventionCosts!$A$1:$A$3432),0)))} -> per person per year | J6: =G6/SUM(Q6:V6) -> 1 | K6: =Q6/$G6 -> 0 | L6: =R6/$G6 -> 0.021150751 | M6: =S6/$G6 -> 0 | N6: =T6/$G6 -> 0.32849371 | O6: =U6/$G6 -> 0.14952484 | P6: =V6/$G6 -> 0.5008307 | Q6: =SUMIFS(InterventionCosts!$K$2:$K$3432,InterventionCosts!$D$2:$D$3432,'Summary of unit costs'!Q$1,InterventionCosts!$A$2:$A$3432,'Summary of unit costs'!$A6) -> 0 | R6: =SUMIFS(InterventionCosts!$K$2:$K$3432,InterventionCosts!$D$2:$D$3432,'Summary of unit costs'!R$1,InterventionCosts!$A$2:$A$3432,'Summary of unit costs'!$A6) -> 37.4524 | S6: =SUMIFS(InterventionCosts!$K$2:$K$3432,InterventionCosts!$D$2:$D$3432,'Summary of unit costs'!S$1,InterventionCosts!$A$2:$A$3432,'Summary of unit costs'!$A6) -> 0 | T6: =SUMIFS(InterventionCosts!$K$2:$K$3432,InterventionCosts!$D$2:$D$3432,'Summary of unit costs'!T$1,InterventionCosts!$A$2:$A$3432,'Summary of unit costs'!$A6) -> 581.67569 | U6: =SUMIFS(InterventionCosts!$K$2:$K$3432,InterventionCosts!$D$2:$D$3432,'Summary of unit costs'!U$1,InterventionCosts!$A$2:$A$3432,'Summary of unit costs'!$A6) -> 264.76904 | V6: =SUMIFS(InterventionCosts!$K$2:$K$3432,InterventionCosts!$D$2:$D$3432,'Summary of unit costs'!V$1,InterventionCosts!$A$2:$A$3432,'Summary of unit costs'!$A6) -> 886.83903
A7: ART Paeds Kids <1 | C7: Paediatric ART in first year of life (after first month) | D7: 702 | E7: Ingredients | F7: ART | G7: {=IF(E7="Literature",INDEX(LiteratureCost!$I$2:$I$10,MATCH('Summary of unit costs'!A7,LiteratureCost!$A$2:$A$10,0)),INDEX(InterventionCosts!$L$1:$L$2363,MATCH(A7,IF(InterventionCosts!$F$1:$F$2363="Cost per intervention",InterventionCosts!$A$1:$A$2363),0)))} -> 5584.3168 | H7: =G7/exrate -> 299.25616 | I7: {=IF(E7="Literature",INDEX(LiteratureCost!$G$2:$G$22,MATCH('Summary of unit costs'!A7,LiteratureCost!$A$2:$A$22,0)),INDEX(InterventionCosts!$L$1:$L$3432,MATCH(A7,IF(InterventionCosts!$F$1:$F$3432="Unit",InterventionCosts!$A$1:$A$3432),0)))} -> per person per year | J7: =G7/SUM(Q7:V7) -> 1 | K7: =Q7/$G7 -> 0 | L7: =R7/$G7 -> 0.37753341 | M7: =S7/$G7 -> 0 | N7: =T7/$G7 -> 0.10416237 | O7: =U7/$G7 -> 0.1191646 | P7: =V7/$G7 -> 0.39913962 | Q7: =SUMIFS(InterventionCosts!$K$2:$K$3432,InterventionCosts!$D$2:$D$3432,'Summary of unit costs'!Q$1,InterventionCosts!$A$2:$A$3432,'Summary of unit costs'!$A7) -> 0 | R7: =SUMIFS(InterventionCosts!$K$2:$K$3432,InterventionCosts!$D$2:$D$3432,'Summary of unit costs'!R$1,InterventionCosts!$A$2:$A$3432,'Summary of unit costs'!$A7) -> 2108.2662 | S7: =SUMIFS(InterventionCosts!$K$2:$K$3432,InterventionCosts!$D$2:$D$3432,'Summary of unit costs'!S$1,InterventionCosts!$A$2:$A$3432,'Summary of unit costs'!$A7) -> 0 | T7: =SUMIFS(InterventionCosts!$K$2:$K$3432,InterventionCosts!$D$2:$D$3432,'Summary of unit costs'!T$1,InterventionCosts!$A$2:$A$3432,'Summary of unit costs'!$A7) -> 581.67569 | U7: =SUMIFS(InterventionCosts!$K$2:$K$3432,InterventionCosts!$D$2:$D$3432,'Summary of unit costs'!U$1,InterventionCosts!$A$2:$A$3432,'Summary of unit costs'!$A7) -> 665.45285 | V7: =SUMIFS(InterventionCosts!$K$2:$K$3432,InterventionCosts!$D$2:$D$3432,'Summary of unit costs'!V$1,InterventionCosts!$A$2:$A$3432,'Summary of unit costs'!$A7) -> 2228.9221
A8: ART Paeds Kids 1-2 (1st year) | C8: Peadiatric ART, starting ART at ages 1-2 yrs | D8: 397 | E8: Ingredients | F8: ART | G8: {=IF(E8="Literature",INDEX(LiteratureCost!$I$2:$I$10,MATCH('Summary of unit costs'!A8,LiteratureCost!$A$2:$A$10,0)),INDEX(InterventionCosts!$L$1:$L$2363,MATCH(A8,IF(InterventionCosts!$F$1:$F$2363="Cost per intervention",InterventionCosts!$A$1:$A$2363),0)))} -> 7995.96 | H8: =G8/exrate -> 428.49293 | I8: {=IF(E8="Literature",INDEX(LiteratureCost!$G$2:$G$22,MATCH('Summary of unit costs'!A8,LiteratureCost!$A$2:$A$22,0)),INDEX(InterventionCosts!$L$1:$L$3432,MATCH(A8,IF(InterventionCosts!$F$1:$F$3432="Unit",InterventionCosts!$A$1:$A$3432),0)))} -> per person per year | J8: =G8/SUM(Q8:V8) -> 1 | K8: =Q8/$G8 -> 0 | L8: =R8/$G8 -> 0.5033572 | M8: =S8/$G8 -> 0 | N8: =T8/$G8 -> 0.13466313 | O8: =U8/$G8 -> 0.083223635 | P8: =V8/$G8 -> 0.27875603 | Q8: =SUMIFS(InterventionCosts!$K$2:$K$3432,InterventionCosts!$D$2:$D$3432,'Summary of unit costs'!Q$1,InterventionCosts!$A$2:$A$3432,'Summary of unit costs'!$A8) -> 0 | R8: =SUMIFS(InterventionCosts!$K$2:$K$3432,InterventionCosts!$D$2:$D$3432,'Summary of unit costs'!R$1,InterventionCosts!$A$2:$A$3432,'Summary of unit costs'!$A8) -> 4024.824 | S8: =SUMIFS(InterventionCosts!$K$2:$K$3432,InterventionCosts!$D$2:$D$3432,'Summary of unit costs'!S$1,InterventionCosts!$A$2:$A$3432,'Summary of unit costs'!$A8) -> 0 | T8: =SUMIFS(InterventionCosts!$K$2:$K$3432,InterventionCosts!$D$2:$D$3432,'Summary of unit costs'!T$1,InterventionCosts!$A$2:$A$3432,'Summary of unit costs'!$A8) -> 1076.761 | U8: =SUMIFS(InterventionCosts!$K$2:$K$3432,InterventionCosts!$D$2:$D$3432,'Summary of unit costs'!U$1,InterventionCosts!$A$2:$A$3432,'Summary of unit costs'!$A8) -> 665.45285 | V8: =SUMIFS(InterventionCosts!$K$2:$K$3432,InterventionCosts!$D$2:$D$3432,'Summary of unit costs'!V$1,InterventionCosts!$A$2:$A$3432,'Summary of unit costs'!$A8) -> 2228.9221
A9: ART Paeds Kids 1-2 (followup) | C9: Peadiatric ART, in year after initiation at ages 1-2 yrs | D9: 2795 | E9: Ingredients | F9: ART | G9: {=IF(E9="Literature",INDEX(LiteratureCost!$I$2:$I$10,MATCH('Summary of unit costs'!A9,LiteratureCost!$A$2:$A$10,0)),INDEX(InterventionCosts!$L$1:$L$2363,MATCH(A9,IF(InterventionCosts!$F$1:$F$2363="Cost per intervention",InterventionCosts!$A$1:$A$2363),0)))} -> 6141.9771 | H9: =G9/exrate -> 329.14044 | I9: {=IF(E9="Literature",INDEX(LiteratureCost!$G$2:$G$22,MATCH('Summary of unit costs'!A9,LiteratureCost!$A$2:$A$22,0)),INDEX(InterventionCosts!$L$1:$L$3432,MATCH(A9,IF(InterventionCosts!$F$1:$F$3432="Unit",InterventionCosts!$A$1:$A$3432),0)))} -> per person per year | J9: =G9/SUM(Q9:V9) -> 1 | K9: =Q9/$G9 -> 0 | L9: =R9/$G9 -> 0.65529779 | M9: =S9/$G9 -> 0 | N9: =T9/$G9 -> 0.094704959 | O9: =U9/$G9 -> 0.057477483 | P9: =V9/$G9 -> 0.19251977 | Q9: =SUMIFS(InterventionCosts!$K$2:$K$3432,InterventionCosts!$D$2:$D$3432,'Summary of unit costs'!Q$1,InterventionCosts!$A$2:$A$3432,'Summary of unit costs'!$A9) -> 0 | R9: =SUMIFS(InterventionCosts!$K$2:$K$3432,InterventionCosts!$D$2:$D$3432,'Summary of unit costs'!R$1,InterventionCosts!$A$2:$A$3432,'Summary of unit costs'!$A9) -> 4024.824 | S9: =SUMIFS(InterventionCosts!$K$2:$K$3432,InterventionCosts!$D$2:$D$3432,'Summary of unit costs'!S$1,InterventionCosts!$A$2:$A$3432,'Summary of unit costs'!$A9) -> 0 | T9: =SUMIFS(InterventionCosts!$K$2:$K$3432,InterventionCosts!$D$2:$D$3432,'Summary of unit costs'!T$1,InterventionCosts!$A$2:$A$3432,'Summary of unit costs'!$A9) -> 581.67569 | U9: =SUMIFS(InterventionCosts!$K$2:$K$3432,InterventionCosts!$D$2:$D$3432,'Summary of unit costs'!U$1,InterventionCosts!$A$2:$A$3432,'Summary of unit costs'!$A9) -> 353.02539 | V9: =SUMIFS(InterventionCosts!$K$2:$K$3432,InterventionCosts!$D$2:$D$3432,'Summary of unit costs'!V$1,InterventionCosts!$A$2:$A$3432,'Summary of unit costs'!$A9) -> 1182.452
A10: ART Paeds Kids 3-5 (1st year) | C10: Peadiatric ART, starting ART at ages 3-5 yrs | D10: 710 | E10: Ingredients | F10: ART | G10: {=IF(E10="Literature",INDEX(LiteratureCost!$I$2:$I$10,MATCH('Summary of unit costs'!A10,LiteratureCost!$A$2:$A$10,0)),INDEX(InterventionCosts!$L$1:$L$2363,MATCH(A10,IF(InterventionCosts!$F$1:$F$2363="Cost per intervention",InterventionCosts!$A$1:$A$2363),0)))} -> 9186.2243 | H10: =G10/exrate -> 492.27762 | I10: {=IF(E10="Literature",INDEX(LiteratureCost!$G$2:$G$22,MATCH('Summary of unit costs'!A10,LiteratureCost!$A$2:$A$22,0)),INDEX(InterventionCosts!$L$1:$L$3432,MATCH(A10,IF(InterventionCosts!$F$1:$F$3432="Unit",InterventionCosts!$A$1:$A$3432),0)))} -> per person per year | J10: =G10/SUM(Q10:V10) -> 1 | K10: =Q10/$G10 -> 0 | L10: =R10/$G10 -> 0.56770749 | M10: =S10/$G10 -> 0 | N10: =T10/$G10 -> 0.11721475 | O10: =U10/$G10 -> 0.0724403 | P10: =V10/$G10 -> 0.24263746 | Q10: =SUMIFS(InterventionCosts!$K$2:$K$3432,InterventionCosts!$D$2:$D$3432,'Summary of unit costs'!Q$1,InterventionCosts!$A$2:$A$3432,'Summary of unit costs'!$A10) -> 0 | R10: =SUMIFS(InterventionCosts!$K$2:$K$3432,InterventionCosts!$D$2:$D$3432,'Summary of unit costs'!R$1,InterventionCosts!$A$2:$A$3432,'Summary of unit costs'!$A10) -> 5215.0884 | S10: =SUMIFS(InterventionCosts!$K$2:$K$3432,InterventionCosts!$D$2:$D$3432,'Summary of unit costs'!S$1,InterventionCosts!$A$2:$A$3432,'Summary of unit costs'!$A10) -> 0 | T10: =SUMIFS(InterventionCosts!$K$2:$K$3432,InterventionCosts!$D$2:$D$3432,'Summary of unit costs'!T$1,InterventionCosts!$A$2:$A$3432,'Summary of unit costs'!$A10) -> 1076.761 | U10: =SUMIFS(InterventionCosts!$K$2:$K$3432,InterventionCosts!$D$2:$D$3432,'Summary of unit costs'!U$1,InterventionCosts!$A$2:$A$3432,'Summary of unit costs'!$A10) -> 665.45285 | V10: =SUMIFS(InterventionCosts!$K$2:$K$3432,InterventionCosts!$D$2:$D$3432,'Summary of unit costs'!V$1,InterventionCosts!$A$2:$A$3432,'Summary of unit costs'!$A10) -> 2228.9221
A11: ART Paeds Kids 3-5 (followup) | C11: Peadiatric ART, in year after initiation at ages 3-5 yrs | D11: 5887 | E11: Ingredients | F11: ART | G11: {=IF(E11="Literature",INDEX(LiteratureCost!$I$2:$I$10,MATCH('Summary of unit costs'!A11,LiteratureCost!$A$2:$A$10,0)),INDEX(InterventionCosts!$L$1:$L$2363,MATCH(A11,IF(InterventionCosts!$F$1:$F$2363="Cost per intervention",InterventionCosts!$A$1:$A$2363),0)))} -> 7332.2415 | H11: =G11/exrate -> 392.92513 | I11: {=IF(E11="Literature",INDEX(LiteratureCost!$G$2:$G$22,MATCH('Summary of unit costs'!A11,LiteratureCost!$A$2:$A$22,0)),INDEX(InterventionCosts!$L$1:$L$3432,MATCH(A11,IF(InterventionCosts!$F$1:$F$3432="Unit",InterventionCosts!$A$1:$A$3432),0)))} -> per person per year | J11: =G11/SUM(Q11:V11) -> 1 | K11: =Q11/$G11 -> 0 | L11: =R11/$G11 -> 0.71125431 | M11: =S11/$G11 -> 0 | N11: =T11/$G11 -> 0.079331224 | O11: =U11/$G11 -> 0.048146994 | P11: =V11/$G11 -> 0.16126747 | Q11: =SUMIFS(InterventionCosts!$K$2:$K$3432,InterventionCosts!$D$2:$D$3432,'Summary of unit costs'!Q$1,InterventionCosts!$A$2:$A$3432,'Summary of unit costs'!$A11) -> 0 | R11: =SUMIFS(InterventionCosts!$K$2:$K$3432,InterventionCosts!$D$2:$D$3432,'Summary of unit costs'!R$1,InterventionCosts!$A$2:$A$3432,'Summary of unit costs'!$A11) -> 5215.0884 | S11: =SUMIFS(InterventionCosts!$K$2:$K$3432,InterventionCosts!$D$2:$D$3432,'Summary of unit costs'!S$1,InterventionCosts!$A$2:$A$3432,'Summary of unit costs'!$A11) -> 0 | T11: =SUMIFS(InterventionCosts!$K$2:$K$3432,InterventionCosts!$D$2:$D$3432,'Summary of unit costs'!T$1,InterventionCosts!$A$2:$A$3432,'Summary of unit costs'!$A11) -> 581.67569 | U11: =SUMIFS(InterventionCosts!$K$2:$K$3432,InterventionCosts!$D$2:$D$3432,'Summary of unit costs'!U$1,InterventionCosts!$A$2:$A$3432,'Summary of unit costs'!$A11) -> 353.02539 | V11: =SUMIFS(InterventionCosts!$K$2:$K$3432,InterventionCosts!$D$2:$D$3432,'Summary of unit costs'!V$1,InterventionCosts!$A$2:$A$3432,'Summary of unit costs'!$A11) -> 1182.452
A12: ART Paeds Kids 6-9 (1st year) | C12: Peadiatric ART, starting ART at ages 6-9 yrs | D12: 1121 | E12: Ingredients | F12: ART | G12: {=IF(E12="Literature",INDEX(LiteratureCost!$I$2:$I$10,MATCH('Summary of unit costs'!A12,LiteratureCost!$A$2:$A$10,0)),INDEX(InterventionCosts!$L$1:$L$2363,MATCH(A12,IF(InterventionCosts!$F$1:$F$2363="Cost per intervention",InterventionCosts!$A$1:$A$2363),0)))} -> 6812.4825 | H12: =G12/exrate -> 365.07194 | I12: {=IF(E12="Literature",INDEX(LiteratureCost!$G$2:$G$22,MATCH('Summary of unit costs'!A12,LiteratureCost!$A$2:$A$22,0)),INDEX(InterventionCosts!$L$1:$L$3432,MATCH(A12,IF(InterventionCosts!$F$1:$F$3432="Unit",InterventionCosts!$A$1:$A$3432),0)))} -> per person per year | J12: =G12/SUM(Q12:V12) -> 1 | K12: =Q12/$G12 -> 0 | L12: =R12/$G12 -> 0.41707946 | M12: =S12/$G12 -> 0 | N12: =T12/$G12 -> 0.15805707 | O12: =U12/$G12 -> 0.097681403 | P12: =V12/$G12 -> 0.32718206 | Q12: =SUMIFS(InterventionCosts!$K$2:$K$3432,InterventionCosts!$D$2:$D$3432,'Summary of unit costs'!Q$1,InterventionCosts!$A$2:$A$3432,'Summary of unit costs'!$A12) -> 0 | R12: =SUMIFS(InterventionCosts!$K$2:$K$3432,InterventionCosts!$D$2:$D$3432,'Summary of unit costs'!R$1,InterventionCosts!$A$2:$A$3432,'Summary of unit costs'!$A12) -> 2841.3466 | S12: =SUMIFS(InterventionCosts!$K$2:$K$3432,InterventionCosts!$D$2:$D$3432,'Summary of unit costs'!S$1,InterventionCosts!$A$2:$A$3432,'Summary of unit costs'!$A12) -> 0 | T12: =SUMIFS(InterventionCosts!$K$2:$K$3432,InterventionCosts!$D$2:$D$3432,'Summary of unit costs'!T$1,InterventionCosts!$A$2:$A$3432,'Summary of unit costs'!$A12) -> 1076.761 | U12: =SUMIFS(InterventionCosts!$K$2:$K$3432,InterventionCosts!$D$2:$D$3432,'Summary of unit costs'!U$1,InterventionCosts!$A$2:$A$3432,'Summary of unit costs'!$A12) -> 665.45285 | V12: =SUMIFS(InterventionCosts!$K$2:$K$3432,InterventionCosts!$D$2:$D$3432,'Summary of unit costs'!V$1,InterventionCosts!$A$2:$A$3432,'Summary of unit costs'!$A12) -> 2228.9221
A13: ART Paeds Kids 6-9 (followup) | C13: Peadiatric ART, in year after initiation at ages 6-9 yrs | D13: 14081 | E13: Ingredients | F13: ART | G13: {=IF(E13="Literature",INDEX(LiteratureCost!$I$2:$I$10,MATCH('Summary of unit costs'!A13,LiteratureCost!$A$2:$A$10,0)),INDEX(InterventionCosts!$L$1:$L$2363,MATCH(A13,IF(InterventionCosts!$F$1:$F$2363="Cost per intervention",InterventionCosts!$A$1:$A$2363),0)))} -> 4958.4997 | H13: =G13/exrate -> 265.71945 | I13: {=IF(E13="Literature",INDEX(LiteratureCost!$G$2:$G$22,MATCH('Summary of unit costs'!A13,LiteratureCost!$A$2:$A$22,0)),INDEX(InterventionCosts!$L$1:$L$3432,MATCH(A13,IF(InterventionCosts!$F$1:$F$3432="Unit",InterventionCosts!$A$1:$A$3432),0)))} -> per person per year | J13: =G13/SUM(Q13:V13) -> 1 | K13: =Q13/$G13 -> 0 | L13: =R13/$G13 -> 0.57302546 | M13: =S13/$G13 -> 0 | N13: =T13/$G13 -> 0.11730881 | O13: =U13/$G13 -> 0.071196008 | P13: =V13/$G13 -> 0.23846972 | Q13: =SUMIFS(InterventionCosts!$K$2:$K$3432,InterventionCosts!$D$2:$D$3432,'Summary of unit costs'!Q$1,InterventionCosts!$A$2:$A$3432,'Summary of unit costs'!$A13) -> 0 | R13: =SUMIFS(InterventionCosts!$K$2:$K$3432,InterventionCosts!$D$2:$D$3432,'Summary of unit costs'!R$1,InterventionCosts!$A$2:$A$3432,'Summary of unit costs'!$A13) -> 2841.3466 | S13: =SUMIFS(InterventionCosts!$K$2:$K$3432,InterventionCosts!$D$2:$D$3432,'Summary of unit costs'!S$1,InterventionCosts!$A$2:$A$3432,'Summary of unit costs'!$A13) -> 0 | T13: =SUMIFS(InterventionCosts!$K$2:$K$3432,InterventionCosts!$D$2:$D$3432,'Summary of unit costs'!T$1,InterventionCosts!$A$2:$A$3432,'Summary of unit costs'!$A13) -> 581.67569 | U13: =SUMIFS(InterventionCosts!$K$2:$K$3432,InterventionCosts!$D$2:$D$3432,'Summary of unit costs'!U$1,InterventionCosts!$A$2:$A$3432,'Summary of unit costs'!$A13) -> 353.02539 | V13: =SUMIFS(InterventionCosts!$K$2:$K$3432,InterventionCosts!$D$2:$D$3432,'Summary of unit costs'!V$1,InterventionCosts!$A$2:$A$3432,'Summary of unit costs'!$A13) -> 1182.452
A14: ART Paeds Kids 10-14 (1st year) | C14: Peadiatric ART, starting ART at ages 10-14 yrs | D14: 1196 | E14: Ingredients | F14: ART | G14: {=IF(E14="Literature",INDEX(LiteratureCost!$I$2:$I$10,MATCH('Summary of unit costs'!A14,LiteratureCost!$A$2:$A$10,0)),INDEX(InterventionCosts!$L$1:$L$2363,MATCH(A14,IF(InterventionCosts!$F$1:$F$2363="Cost per intervention",InterventionCosts!$A$1:$A$2363),0)))} -> 5584.7476 | H14: =G14/exrate -> 299.27924 | I14: {=IF(E14="Literature",INDEX(LiteratureCost!$G$2:$G$22,MATCH('Summary of unit costs'!A14,LiteratureCost!$A$2:$A$22,0)),INDEX(InterventionCosts!$L$1:$L$3432,MATCH(A14,IF(InterventionCosts!$F$1:$F$3432="Unit",InterventionCosts!$A$1:$A$3432),0)))} -> per person per year | J14: =G14/SUM(Q14:V14) -> 1 | K14: =Q14/$G14 -> 0 | L14: =R14/$G14 -> 0.28893188 | M14: =S14/$G14 -> 0 | N14: =T14/$G14 -> 0.19280388 | O14: =U14/$G14 -> 0.1191554 | P14: =V14/$G14 -> 0.39910884 | Q14: =SUMIFS(InterventionCosts!$K$2:$K$3432,InterventionCosts!$D$2:$D$3432,'Summary of unit costs'!Q$1,InterventionCosts!$A$2:$A$3432,'Summary of unit costs'!$A14) -> 0 | R14: =SUMIFS(InterventionCosts!$K$2:$K$3432,InterventionCosts!$D$2:$D$3432,'Summary of unit costs'!R$1,InterventionCosts!$A$2:$A$3432,'Summary of unit costs'!$A14) -> 1613.6116 | S14: =SUMIFS(InterventionCosts!$K$2:$K$3432,InterventionCosts!$D$2:$D$3432,'Summary of unit costs'!S$1,InterventionCosts!$A$2:$A$3432,'Summary of unit costs'!$A14) -> 0 | T14: =SUMIFS(InterventionCosts!$K$2:$K$3432,InterventionCosts!$D$2:$D$3432,'Summary of unit costs'!T$1,InterventionCosts!$A$2:$A$3432,'Summary of unit costs'!$A14) -> 1076.761 | U14: =SUMIFS(InterventionCosts!$K$2:$K$3432,InterventionCosts!$D$2:$D$3432,'Summary of unit costs'!U$1,InterventionCosts!$A$2:$A$3432,'Summary of unit costs'!$A14) -> 665.45285 | V14: =SUMIFS(InterventionCosts!$K$2:$K$3432,InterventionCosts!$D$2:$D$3432,'Summary of unit costs'!V$1,InterventionCosts!$A$2:$A$3432,'Summary of unit costs'!$A14) -> 2228.9221
A15: ART Paeds Kids 10-14 (followup) | C15: Peadiatric ART, in year after initiation at ages 10-14 yrs | D15: 40359 | E15: Ingredients | F15: ART | G15: {=IF(E15="Literature",INDEX(LiteratureCost!$I$2:$I$10,MATCH('Summary of unit costs'!A15,LiteratureCost!$A$2:$A$10,0)),INDEX(InterventionCosts!$L$1:$L$2363,MATCH(A15,IF(InterventionCosts!$F$1:$F$2363="Cost per intervention",InterventionCosts!$A$1:$A$2363),0)))} -> 3730.7647 | H15: =G15/exrate -> 199.92675 | I15: {=IF(E15="Literature",INDEX(LiteratureCost!$G$2:$G$22,MATCH('Summary of unit costs'!A15,LiteratureCost!$A$2:$A$22,0)),INDEX(InterventionCosts!$L$1:$L$3432,MATCH(A15,IF(InterventionCosts!$F$1:$F$3432="Unit",InterventionCosts!$A$1:$A$3432),0)))} -> per person per year | J15: =G15/SUM(Q15:V15) -> 1 | K15: =Q15/$G15 -> 0 | L15: =R15/$G15 -> 0.43251497 | M15: =S15/$G15 -> 0 | N15: =T15/$G15 -> 0.15591326 | O15: =U15/$G15 -> 0.094625476 | P15: =V15/$G15 -> 0.31694629 | Q15: =SUMIFS(InterventionCosts!$K$2:$K$3432,InterventionCosts!$D$2:$D$3432,'Summary of unit costs'!Q$1,InterventionCosts!$A$2:$A$3432,'Summary of unit costs'!$A15) -> 0 | R15: =SUMIFS(InterventionCosts!$K$2:$K$3432,InterventionCosts!$D$2:$D$3432,'Summary of unit costs'!R$1,InterventionCosts!$A$2:$A$3432,'Summary of unit costs'!$A15) -> 1613.6116 | S15: =SUMIFS(InterventionCosts!$K$2:$K$3432,InterventionCosts!$D$2:$D$3432,'Summary of unit costs'!S$1,InterventionCosts!$A$2:$A$3432,'Summary of unit costs'!$A15) -> 0 | T15: =SUMIFS(InterventionCosts!$K$2:$K$3432,InterventionCosts!$D$2:$D$3432,'Summary of unit costs'!T$1,InterventionCosts!$A$2:$A$3432,'Summary of unit costs'!$A15) -> 581.67569 | U15: =SUMIFS(InterventionCosts!$K$2:$K$3432,InterventionCosts!$D$2:$D$3432,'Summary of unit costs'!U$1,InterventionCosts!$A$2:$A$3432,'Summary of unit costs'!$A15) -> 353.02539 | V15: =SUMIFS(InterventionCosts!$K$2:$K$3432,InterventionCosts!$D$2:$D$3432,'Summary of unit costs'!V$1,InterventionCosts!$A$2:$A$3432,'Summary of unit costs'!$A15) -> 1182.452
A16: ART Paed (average cost) | C16: Average cost estimate of above, weighted by est. population size | E16: Ingredients | F16: ART | G16: =SUMPRODUCT(G7:G15,$D$7:$D$15)/SUM($D$7:$D$15) -> 4589.8057 | H16: =G16/exrate -> 245.96162 | I16: per person per year | J16: =G16/SUM(Q16:V16) -> 1 | K16: =Q16/$G16 -> 0 | L16: =R16/$G16 -> 0.51506967 | M16: =S16/$G16 -> 0 | N16: =T16/$G16 -> 0.13222422 | O16: =U16/$G16 -> 0.08109153 | P16: =V16/$G16 -> 0.27161459 | Q16: =SUMPRODUCT(Q7:Q15,$D$7:$D$15)/SUM($D$7:$D$15) -> 0 | R16: =SUMPRODUCT(R7:R15,$D$7:$D$15)/SUM($D$7:$D$15) -> 2364.0697 | S16: =SUMPRODUCT(S7:S15,$D$7:$D$15)/SUM($D$7:$D$15) -> 0 | T16: =SUMPRODUCT(T7:T15,$D$7:$D$15)/SUM($D$7:$D$15) -> 606.88346 | U16: =SUMPRODUCT(U7:U15,$D$7:$D$15)/SUM($D$7:$D$15) -> 372.19437 | V16: =SUMPRODUCT(V7:V15,$D$7:$D$15)/SUM($D$7:$D$15) -> 1246.6582
A17: POC VL testing | C17: Adults on ART in 20% of clinics (high demand clinics) | E17: Ingredients | F17: ART | G17: {=IF(E17="Literature",INDEX(LiteratureCost!$I$2:$I$42,MATCH('Summary of unit costs'!A17,LiteratureCost!$A$2:$A$42,0)),INDEX(InterventionCosts!$L$1:$L$3432,MATCH(A17,IF(InterventionCosts!$F$1:$F$3432="Cost per intervention",InterventionCosts!$A$1:$A$3432),0)))} -> 564.88179 | H17: =G17/exrate -> 30.271269 | I17: {=IF(E17="Literature",INDEX(LiteratureCost!$G$2:$G$22,MATCH('Summary of unit costs'!A17,LiteratureCost!$A$2:$A$22,0)),INDEX(InterventionCosts!$L$1:$L$3432,MATCH(A17,IF(InterventionCosts!$F$1:$F$3432="Unit",InterventionCosts!$A$1:$A$3432),0)))} -> per test | K17: =Q17/$G17 -> 0.57243639 | L17: =R17/$G17 -> 0 | M17: =S17/$G17 -> 0.13921977 | N17: =T17/$G17 -> 0 | O17: =U17/$G17 -> 0.084028752 | P17: =V17/$G17 -> 0.20431509 | Q17: =SUMIFS(InterventionCosts!$K$2:$K$3432,InterventionCosts!$D$2:$D$3432,'Summary of unit costs'!Q$1,InterventionCosts!$A$2:$A$3432,'Summary of unit costs'!$A17) -> 323.35889 | R17: =SUMIFS(InterventionCosts!$K$2:$K$3432,InterventionCosts!$D$2:$D$3432,'Summary of unit costs'!R$1,InterventionCosts!$A$2:$A$3432,'Summary of unit costs'!$A17) -> 0 | S17: =SUMIFS(InterventionCosts!$K$2:$K$3432,InterventionCosts!$D$2:$D$3432,'Summary of unit costs'!S$1,InterventionCosts!$A$2:$A$3432,'Summary of unit costs'!$A17) -> 78.64271 | T17: =SUMIFS(InterventionCosts!$K$2:$K$3432,InterventionCosts!$D$2:$D$3432,'Summary of unit costs'!T$1,InterventionCosts!$A$2:$A$3432,'Summary of unit costs'!$A17) -> 0 | U17: =SUMIFS(InterventionCosts!$K$2:$K$3432,InterventionCosts!$D$2:$D$3432,'Summary of unit costs'!U$1,InterventionCosts!$A$2:$A$3432,'Summary of unit costs'!$A17) -> 47.466312 | V17: =SUMIFS(InterventionCosts!$K$2:$K$3432,InterventionCosts!$D$2:$D$3432,'Summary of unit costs'!V$1,InterventionCosts!$A$2:$A$3432,'Summary of unit costs'!$A17) -> 115.41387
A18: ART with POCVL Adults (1st line 1st year) | C18: As ART costs above, but replacing PCR-based VL with point-of-care GeneXpert testing | E18: Ingredients | F18: ART | G18: {=IF(E18="Literature",INDEX(LiteratureCost!$I$2:$I$10,MATCH('Summary of unit costs'!A18,LiteratureCost!$A$2:$A$10,0)),INDEX(InterventionCosts!$L$1:$L$2363,MATCH(A18,IF(InterventionCosts!$F$1:$F$2363="Cost per intervention",InterventionCosts!$A$1:$A$2363),0)))} -> 5484.0979 | H18: =G18/exrate -> 293.88556 | I18: per person per year | J18: =G18/SUM(Q18:V18) -> 1 | K18: =Q18/$G18 -> 0.11792601 | L18: =R18/$G18 -> 0.23748844 | M18: =S18/$G18 -> 0.028680272 | N18: =T18/$G18 -> 0.030209038 | O18: =U18/$G18 -> 0.13865279 | P18: =V18/$G18 -> 0.44704345 | Q18: =SUMIFS(InterventionCosts!$K$2:$K$3432,InterventionCosts!$D$2:$D$3432,'Summary of unit costs'!Q$1,InterventionCosts!$A$2:$A$3432,'Summary of unit costs'!$A18) -> 646.71779 | R18: =SUMIFS(InterventionCosts!$K$2:$K$3432,InterventionCosts!$D$2:$D$3432,'Summary of unit costs'!R$1,InterventionCosts!$A$2:$A$3432,'Summary of unit costs'!$A18) -> 1302.4098 | S18: =SUMIFS(InterventionCosts!$K$2:$K$3432,InterventionCosts!$D$2:$D$3432,'Summary of unit costs'!S$1,InterventionCosts!$A$2:$A$3432,'Summary of unit costs'!$A18) -> 157.28542 | T18: =SUMIFS(InterventionCosts!$K$2:$K$3432,InterventionCosts!$D$2:$D$3432,'Summary of unit costs'!T$1,InterventionCosts!$A$2:$A$3432,'Summary of unit costs'!$A18) -> 165.66932 | U18: =SUMIFS(InterventionCosts!$K$2:$K$3432,InterventionCosts!$D$2:$D$3432,'Summary of unit costs'!U$1,InterventionCosts!$A$2:$A$3432,'Summary of unit costs'!$A18) -> 760.38547 | V18: =SUMIFS(InterventionCosts!$K$2:$K$3432,InterventionCosts!$D$2:$D$3432,'Summary of unit costs'!V$1,InterventionCosts!$A$2:$A$3432,'Summary of unit costs'!$A18) -> 2451.63
A19: ART with POCVL Adults (1st line followup) | C19: As ART costs above, but replacing PCR-based VL with point-of-care GeneXpert testing | E19: Ingredients | F19: ART | G19: {=IF(E19="Literature",INDEX(LiteratureCost!$I$2:$I$10,MATCH('Summary of unit costs'!A19,LiteratureCost!$A$2:$A$10,0)),INDEX(InterventionCosts!$L$1:$L$2363,MATCH(A19,IF(InterventionCosts!$F$1:$F$2363="Cost per intervention",InterventionCosts!$A$1:$A$2363),0)))} -> 3416.3737 | H19: =G19/exrate -> 183.07895 | I19: per person per year | J19: =G19/SUM(Q19:V19) -> 1 | K19: =Q19/$G19 -> 0.094649742 | L19: =R19/$G19 -> 0.34828879 | M19: =S19/$G19 -> 0.023019352 | N19: =T19/$G19 -> 0.036919218 | O19: =U19/$G19 -> 0.11722713 | P19: =V19/$G19 -> 0.37989576 | Q19: =SUMIFS(InterventionCosts!$K$2:$K$3432,InterventionCosts!$D$2:$D$3432,'Summary of unit costs'!Q$1,InterventionCosts!$A$2:$A$3432,'Summary of unit costs'!$A19) -> 323.35889 | R19: =SUMIFS(InterventionCosts!$K$2:$K$3432,InterventionCosts!$D$2:$D$3432,'Summary of unit costs'!R$1,InterventionCosts!$A$2:$A$3432,'Summary of unit costs'!$A19) -> 1189.8847 | S19: =SUMIFS(InterventionCosts!$K$2:$K$3432,InterventionCosts!$D$2:$D$3432,'Summary of unit costs'!S$1,InterventionCosts!$A$2:$A$3432,'Summary of unit costs'!$A19) -> 78.64271 | T19: =SUMIFS(InterventionCosts!$K$2:$K$3432,InterventionCosts!$D$2:$D$3432,'Summary of unit costs'!T$1,InterventionCosts!$A$2:$A$3432,'Summary of unit costs'!$A19) -> 126.12985 | U19: =SUMIFS(InterventionCosts!$K$2:$K$3432,InterventionCosts!$D$2:$D$3432,'Summary of unit costs'!U$1,InterventionCosts!$A$2:$A$3432,'Summary of unit costs'!$A19) -> 400.4917 | V19: =SUMIFS(InterventionCosts!$K$2:$K$3432,InterventionCosts!$D$2:$D$3432,'Summary of unit costs'!V$1,InterventionCosts!$A$2:$A$3432,'Summary of unit costs'!$A19) -> 1297.8659
A20: ART with POCVL Adults (2nd line followup) | C20: As ART costs above, but replacing PCR-based VL with point-of-care GeneXpert testing | E20: Ingredients | F20: ART | G20: {=IF(E20="Literature",INDEX(LiteratureCost!$I$2:$I$10,MATCH('Summary of unit costs'!A20,LiteratureCost!$A$2:$A$10,0)),INDEX(InterventionCosts!$L$1:$L$2363,MATCH(A20,IF(InterventionCosts!$F$1:$F$2363="Cost per intervention",InterventionCosts!$A$1:$A$2363),0)))} -> 6022.1141 | H20: =G20/exrate -> 322.71713 | I20: per person per year | J20: =G20/SUM(Q20:V20) -> 1 | K20: =Q20/$G20 -> 0.10739049 | L20: =R20/$G20 -> 0.47273662 | M20: =S20/$G20 -> 0.026117974 | N20: =T20/$G20 -> 0.020944446 | O20: =U20/$G20 -> 0.089040883 | P20: =V20/$G20 -> 0.28376958 | Q20: =SUMIFS(InterventionCosts!$K$2:$K$3432,InterventionCosts!$D$2:$D$3432,'Summary of unit costs'!Q$1,InterventionCosts!$A$2:$A$3432,'Summary of unit costs'!$A20) -> 646.71779 | R20: =SUMIFS(InterventionCosts!$K$2:$K$3432,InterventionCosts!$D$2:$D$3432,'Summary of unit costs'!R$1,InterventionCosts!$A$2:$A$3432,'Summary of unit costs'!$A20) -> 2846.8739 | S20: =SUMIFS(InterventionCosts!$K$2:$K$3432,InterventionCosts!$D$2:$D$3432,'Summary of unit costs'!S$1,InterventionCosts!$A$2:$A$3432,'Summary of unit costs'!$A20) -> 157.28542 | T20: =SUMIFS(InterventionCosts!$K$2:$K$3432,InterventionCosts!$D$2:$D$3432,'Summary of unit costs'!T$1,InterventionCosts!$A$2:$A$3432,'Summary of unit costs'!$A20) -> 126.12985 | U20: =SUMIFS(InterventionCosts!$K$2:$K$3432,InterventionCosts!$D$2:$D$3432,'Summary of unit costs'!U$1,InterventionCosts!$A$2:$A$3432,'Summary of unit costs'!$A20) -> 536.21435 | V20: =SUMIFS(InterventionCosts!$K$2:$K$3432,InterventionCosts!$D$2:$D$3432,'Summary of unit costs'!V$1,InterventionCosts!$A$2:$A$3432,'Summary of unit costs'!$A20) -> 1708.8928
A21: ART with POCVL Paeds Kids <1 | C21: As ART costs above, but replacing PCR-based VL with point-of-care GeneXpert testing | E21: Ingredients | F21: ART | G21: {=IF(E21="Literature",INDEX(LiteratureCost!$I$2:$I$10,MATCH('Summary of unit costs'!A21,LiteratureCost!$A$2:$A$10,0)),INDEX(InterventionCosts!$L$1:$L$2363,MATCH(A21,IF(InterventionCosts!$F$1:$F$2363="Cost per intervention",InterventionCosts!$A$1:$A$2363),0)))} -> 5654.1133 | H21: =G21/exrate -> 302.99646 | I21: per person per year | J21: =G21/SUM(Q21:V21) -> 1 | K21: =Q21/$G21 -> 0.057190027 | L21: =R21/$G21 -> 0.372873 | M21: =S21/$G21 -> 0.013908938 | N21: =T21/$G21 -> 0.01531458 | O21: =U21/$G21 -> 0.12608859 | P21: =V21/$G21 -> 0.41462487 | Q21: =SUMIFS(InterventionCosts!$K$2:$K$3432,InterventionCosts!$D$2:$D$3432,'Summary of unit costs'!Q$1,InterventionCosts!$A$2:$A$3432,'Summary of unit costs'!$A21) -> 323.35889 | R21: =SUMIFS(InterventionCosts!$K$2:$K$3432,InterventionCosts!$D$2:$D$3432,'Summary of unit costs'!R$1,InterventionCosts!$A$2:$A$3432,'Summary of unit costs'!$A21) -> 2108.2662 | S21: =SUMIFS(InterventionCosts!$K$2:$K$3432,InterventionCosts!$D$2:$D$3432,'Summary of unit costs'!S$1,InterventionCosts!$A$2:$A$3432,'Summary of unit costs'!$A21) -> 78.64271 | T21: =SUMIFS(InterventionCosts!$K$2:$K$3432,InterventionCosts!$D$2:$D$3432,'Summary of unit costs'!T$1,InterventionCosts!$A$2:$A$3432,'Summary of unit costs'!$A21) -> 86.590372 | U21: =SUMIFS(InterventionCosts!$K$2:$K$3432,InterventionCosts!$D$2:$D$3432,'Summary of unit costs'!U$1,InterventionCosts!$A$2:$A$3432,'Summary of unit costs'!$A21) -> 712.91916 | V21: =SUMIFS(InterventionCosts!$K$2:$K$3432,InterventionCosts!$D$2:$D$3432,'Summary of unit costs'!V$1,InterventionCosts!$A$2:$A$3432,'Summary of unit costs'!$A21) -> 2344.336
A22: ART with POCVL Paeds Kids 1-2 (1st year) | C22: As ART costs above, but replacing PCR-based VL with point-of-care GeneXpert testing | E22: Ingredients | F22: ART | G22: {=IF(E22="Literature",INDEX(LiteratureCost!$I$2:$I$10,MATCH('Summary of unit costs'!A22,LiteratureCost!$A$2:$A$10,0)),INDEX(InterventionCosts!$L$1:$L$2363,MATCH(A22,IF(InterventionCosts!$F$1:$F$2363="Cost per intervention",InterventionCosts!$A$1:$A$2363),0)))} -> 8135.5529 | H22: =G22/exrate -> 435.97353 | I22: per person per year | J22: =G22/SUM(Q22:V22) -> 1 | K22: =Q22/$G22 -> 0.079492788 | L22: =R22/$G22 -> 0.4947204 | M22: =S22/$G22 -> 0.019333095 | N22: =T22/$G22 -> 0.010643453 | O22: =U22/$G22 -> 0.093464511 | P22: =V22/$G22 -> 0.30234575 | Q22: =SUMIFS(InterventionCosts!$K$2:$K$3432,InterventionCosts!$D$2:$D$3432,'Summary of unit costs'!Q$1,InterventionCosts!$A$2:$A$3432,'Summary of unit costs'!$A22) -> 646.71779 | R22: =SUMIFS(InterventionCosts!$K$2:$K$3432,InterventionCosts!$D$2:$D$3432,'Summary of unit costs'!R$1,InterventionCosts!$A$2:$A$3432,'Summary of unit costs'!$A22) -> 4024.824 | S22: =SUMIFS(InterventionCosts!$K$2:$K$3432,InterventionCosts!$D$2:$D$3432,'Summary of unit costs'!S$1,InterventionCosts!$A$2:$A$3432,'Summary of unit costs'!$A22) -> 157.28542 | T22: =SUMIFS(InterventionCosts!$K$2:$K$3432,InterventionCosts!$D$2:$D$3432,'Summary of unit costs'!T$1,InterventionCosts!$A$2:$A$3432,'Summary of unit costs'!$A22) -> 86.590372 | U22: =SUMIFS(InterventionCosts!$K$2:$K$3432,InterventionCosts!$D$2:$D$3432,'Summary of unit costs'!U$1,InterventionCosts!$A$2:$A$3432,'Summary of unit costs'!$A22) -> 760.38547 | V22: =SUMIFS(InterventionCosts!$K$2:$K$3432,InterventionCosts!$D$2:$D$3432,'Summary of unit costs'!V$1,InterventionCosts!$A$2:$A$3432,'Summary of unit costs'!$A22) -> 2459.7498
A23: ART with POCVL Paeds Kids 1-2 (followup) | C23: As ART costs above, but replacing PCR-based VL with point-of-care GeneXpert testing | E23: Ingredients | F23: ART | G23: {=IF(E23="Literature",INDEX(LiteratureCost!$I$2:$I$10,MATCH('Summary of unit costs'!A23,LiteratureCost!$A$2:$A$10,0)),INDEX(InterventionCosts!$L$1:$L$2363,MATCH(A23,IF(InterventionCosts!$F$1:$F$2363="Cost per intervention",InterventionCosts!$A$1:$A$2363),0)))} -> 6211.7736 | H23: =G23/exrate -> 332.88074 | I23: per person per year | J23: =G23/SUM(Q23:V23) -> 1 | K23: =Q23/$G23 -> 0.052055808 | L23: =R23/$G23 -> 0.64793476 | M23: =S23/$G23 -> 0.012660267 | N23: =T23/$G23 -> 0.013939718 | O23: =U23/$G23 -> 0.064473003 | P23: =V23/$G23 -> 0.20893645 | Q23: =SUMIFS(InterventionCosts!$K$2:$K$3432,InterventionCosts!$D$2:$D$3432,'Summary of unit costs'!Q$1,InterventionCosts!$A$2:$A$3432,'Summary of unit costs'!$A23) -> 323.35889 | R23: =SUMIFS(InterventionCosts!$K$2:$K$3432,InterventionCosts!$D$2:$D$3432,'Summary of unit costs'!R$1,InterventionCosts!$A$2:$A$3432,'Summary of unit costs'!$A23) -> 4024.824 | S23: =SUMIFS(InterventionCosts!$K$2:$K$3432,InterventionCosts!$D$2:$D$3432,'Summary of unit costs'!S$1,InterventionCosts!$A$2:$A$3432,'Summary of unit costs'!$A23) -> 78.64271 | T23: =SUMIFS(InterventionCosts!$K$2:$K$3432,InterventionCosts!$D$2:$D$3432,'Summary of unit costs'!T$1,InterventionCosts!$A$2:$A$3432,'Summary of unit costs'!$A23) -> 86.590372 | U23: =SUMIFS(InterventionCosts!$K$2:$K$3432,InterventionCosts!$D$2:$D$3432,'Summary of unit costs'!U$1,InterventionCosts!$A$2:$A$3432,'Summary of unit costs'!$A23) -> 400.4917 | V23: =SUMIFS(InterventionCosts!$K$2:$K$3432,InterventionCosts!$D$2:$D$3432,'Summary of unit costs'!V$1,InterventionCosts!$A$2:$A$3432,'Summary of unit costs'!$A23) -> 1297.8659
A24: ART with POCVL Paeds Kids 3-5 (1st year) | C24: As ART costs above, but replacing PCR-based VL with point-of-care GeneXpert testing | E24: Ingredients | F24: ART | G24: {=IF(E24="Literature",INDEX(LiteratureCost!$I$2:$I$10,MATCH('Summary of unit costs'!A24,LiteratureCost!$A$2:$A$10,0)),INDEX(InterventionCosts!$L$1:$L$2363,MATCH(A24,IF(InterventionCosts!$F$1:$F$2363="Cost per intervention",InterventionCosts!$A$1:$A$2363),0)))} -> 9325.8173 | H24: =G24/exrate -> 499.75822 | I24: per person per year | J24: =G24/SUM(Q24:V24) -> 1 | K24: =Q24/$G24 -> 0.069347036 | L24: =R24/$G24 -> 0.5592098 | M24: =S24/$G24 -> 0.016865591 | N24: =T24/$G24 -> 0.009285017 | O24: =U24/$G24 -> 0.081535532 | P24: =V24/$G24 -> 0.26375703 | Q24: =SUMIFS(InterventionCosts!$K$2:$K$3432,InterventionCosts!$D$2:$D$3432,'Summary of unit costs'!Q$1,InterventionCosts!$A$2:$A$3432,'Summary of unit costs'!$A24) -> 646.71779 | R24: =SUMIFS(InterventionCosts!$K$2:$K$3432,InterventionCosts!$D$2:$D$3432,'Summary of unit costs'!R$1,InterventionCosts!$A$2:$A$3432,'Summary of unit costs'!$A24) -> 5215.0884 | S24: =SUMIFS(InterventionCosts!$K$2:$K$3432,InterventionCosts!$D$2:$D$3432,'Summary of unit costs'!S$1,InterventionCosts!$A$2:$A$3432,'Summary of unit costs'!$A24) -> 157.28542 | T24: =SUMIFS(InterventionCosts!$K$2:$K$3432,InterventionCosts!$D$2:$D$3432,'Summary of unit costs'!T$1,InterventionCosts!$A$2:$A$3432,'Summary of unit costs'!$A24) -> 86.590372 | U24: =SUMIFS(InterventionCosts!$K$2:$K$3432,InterventionCosts!$D$2:$D$3432,'Summary of unit costs'!U$1,InterventionCosts!$A$2:$A$3432,'Summary of unit costs'!$A24) -> 760.38547 | V24: =SUMIFS(InterventionCosts!$K$2:$K$3432,InterventionCosts!$D$2:$D$3432,'Summary of unit costs'!V$1,InterventionCosts!$A$2:$A$3432,'Summary of unit costs'!$A24) -> 2459.7498
A25: ART with POCVL Paeds Kids 3-5 (followup) | C25: As ART costs above, but replacing PCR-based VL with point-of-care GeneXpert testing | E25: Ingredients | F25: ART | G25: {=IF(E25="Literature",INDEX(LiteratureCost!$I$2:$I$10,MATCH('Summary of unit costs'!A25,LiteratureCost!$A$2:$A$10,0)),INDEX(InterventionCosts!$L$1:$L$2363,MATCH(A25,IF(InterventionCosts!$F$1:$F$2363="Cost per intervention",InterventionCosts!$A$1:$A$2363),0)))} -> 7402.038 | H25: =G25/exrate -> 396.66543 | I25: per person per year | J25: =G25/SUM(Q25:V25) -> 1 | K25: =Q25/$G25 -> 0.043685117 | L25: =R25/$G25 -> 0.70454764 | M25: =S25/$G25 -> 0.010624467 | N25: =T25/$G25 -> 0.01169818 | O25: =U25/$G25 -> 0.054105599 | P25: =V25/$G25 -> 0.175339 | Q25: =SUMIFS(InterventionCosts!$K$2:$K$3432,InterventionCosts!$D$2:$D$3432,'Summary of unit costs'!Q$1,InterventionCosts!$A$2:$A$3432,'Summary of unit costs'!$A25) -> 323.35889 | R25: =SUMIFS(InterventionCosts!$K$2:$K$3432,InterventionCosts!$D$2:$D$3432,'Summary of unit costs'!R$1,InterventionCosts!$A$2:$A$3432,'Summary of unit costs'!$A25) -> 5215.0884 | S25: =SUMIFS(InterventionCosts!$K$2:$K$3432,InterventionCosts!$D$2:$D$3432,'Summary of unit costs'!S$1,InterventionCosts!$A$2:$A$3432,'Summary of unit costs'!$A25) -> 78.64271 | T25: =SUMIFS(InterventionCosts!$K$2:$K$3432,InterventionCosts!$D$2:$D$3432,'Summary of unit costs'!T$1,InterventionCosts!$A$2:$A$3432,'Summary of unit costs'!$A25) -> 86.590372 | U25: =SUMIFS(InterventionCosts!$K$2:$K$3432,InterventionCosts!$D$2:$D$3432,'Summary of unit costs'!U$1,InterventionCosts!$A$2:$A$3432,'Summary of unit costs'!$A25) -> 400.4917 | V25: =SUMIFS(InterventionCosts!$K$2:$K$3432,InterventionCosts!$D$2:$D$3432,'Summary of unit costs'!V$1,InterventionCosts!$A$2:$A$3432,'Summary of unit costs'!$A25) -> 1297.8659
A26: ART with POCVL Paeds Kids 6-9 (1st year) | C26: As ART costs above, but replacing PCR-based VL with point-of-care GeneXpert testing | E26: Ingredients | F26: ART | G26: {=IF(E26="Literature",INDEX(LiteratureCost!$I$2:$I$10,MATCH('Summary of unit costs'!A26,LiteratureCost!$A$2:$A$10,0)),INDEX(InterventionCosts!$L$1:$L$2363,MATCH(A26,IF(InterventionCosts!$F$1:$F$2363="Cost per intervention",InterventionCosts!$A$1:$A$2363),0)))} -> 6952.0755 | H26: =G26/exrate -> 372.55254 | I26: per person per year | J26: =G26/SUM(Q26:V26) -> 1 | K26: =Q26/$G26 -> 0.093025139 | L26: =R26/$G26 -> 0.40870479 | M26: =S26/$G26 -> 0.022624239 | N26: =T26/$G26 -> 0.012455327 | O26: =U26/$G26 -> 0.10937532 | P26: =V26/$G26 -> 0.35381518 | Q26: =SUMIFS(InterventionCosts!$K$2:$K$3432,InterventionCosts!$D$2:$D$3432,'Summary of unit costs'!Q$1,InterventionCosts!$A$2:$A$3432,'Summary of unit costs'!$A26) -> 646.71779 | R26: =SUMIFS(InterventionCosts!$K$2:$K$3432,InterventionCosts!$D$2:$D$3432,'Summary of unit costs'!R$1,InterventionCosts!$A$2:$A$3432,'Summary of unit costs'!$A26) -> 2841.3466 | S26: =SUMIFS(InterventionCosts!$K$2:$K$3432,InterventionCosts!$D$2:$D$3432,'Summary of unit costs'!S$1,InterventionCosts!$A$2:$A$3432,'Summary of unit costs'!$A26) -> 157.28542 | T26: =SUMIFS(InterventionCosts!$K$2:$K$3432,InterventionCosts!$D$2:$D$3432,'Summary of unit costs'!T$1,InterventionCosts!$A$2:$A$3432,'Summary of unit costs'!$A26) -> 86.590372 | U26: =SUMIFS(InterventionCosts!$K$2:$K$3432,InterventionCosts!$D$2:$D$3432,'Summary of unit costs'!U$1,InterventionCosts!$A$2:$A$3432,'Summary of unit costs'!$A26) -> 760.38547 | V26: =SUMIFS(InterventionCosts!$K$2:$K$3432,InterventionCosts!$D$2:$D$3432,'Summary of unit costs'!V$1,InterventionCosts!$A$2:$A$3432,'Summary of unit costs'!$A26) -> 2459.7498
A27: ART with POCVL Paeds Kids 6-9 (followup) | C27: As ART costs above, but replacing PCR-based VL with point-of-care GeneXpert testing | E27: Ingredients | F27: ART | G27: {=IF(E27="Literature",INDEX(LiteratureCost!$I$2:$I$10,MATCH('Summary of unit costs'!A27,LiteratureCost!$A$2:$A$10,0)),INDEX(InterventionCosts!$L$1:$L$2363,MATCH(A27,IF(InterventionCosts!$F$1:$F$2363="Cost per intervention",InterventionCosts!$A$1:$A$2363),0)))} -> 5028.2962 | H27: =G27/exrate -> 269.45975 | I27: per person per year | J27: =G27/SUM(Q27:V27) -> 1 | K27: =Q27/$G27 -> 0.064307846 | L27: =R27/$G27 -> 0.56507144 | M27: =S27/$G27 -> 0.015640031 | N27: =T27/$G27 -> 0.017220619 | O27: =U27/$G27 -> 0.079647595 | P27: =V27/$G27 -> 0.25811247 | Q27: =SUMIFS(InterventionCosts!$K$2:$K$3432,InterventionCosts!$D$2:$D$3432,'Summary of unit costs'!Q$1,InterventionCosts!$A$2:$A$3432,'Summary of unit costs'!$A27) -> 323.35889 | R27: =SUMIFS(InterventionCosts!$K$2:$K$3432,InterventionCosts!$D$2:$D$3432,'Summary of unit costs'!R$1,InterventionCosts!$A$2:$A$3432,'Summary of unit costs'!$A27) -> 2841.3466 | S27: =SUMIFS(InterventionCosts!$K$2:$K$3432,InterventionCosts!$D$2:$D$3432,'Summary of unit costs'!S$1,InterventionCosts!$A$2:$A$3432,'Summary of unit costs'!$A27) -> 78.64271 | T27: =SUMIFS(InterventionCosts!$K$2:$K$3432,InterventionCosts!$D$2:$D$3432,'Summary of unit costs'!T$1,InterventionCosts!$A$2:$A$3432,'Summary of unit costs'!$A27) -> 86.590372 | U27: =SUMIFS(InterventionCosts!$K$2:$K$3432,InterventionCosts!$D$2:$D$3432,'Summary of unit costs'!U$1,InterventionCosts!$A$2:$A$3432,'Summary of unit costs'!$A27) -> 400.4917 | V27: =SUMIFS(InterventionCosts!$K$2:$K$3432,InterventionCosts!$D$2:$D$3432,'Summary of unit costs'!V$1,InterventionCosts!$A$2:$A$3432,'Summary of unit costs'!$A27) -> 1297.8659
A28: ART with POCVL Paeds Kids 10-14 (1st year) | C28: As ART costs above, but replacing PCR-based VL with point-of-care GeneXpert testing | E28: Ingredients | F28: ART | G28: {=IF(E28="Literature",INDEX(LiteratureCost!$I$2:$I$10,MATCH('Summary of unit costs'!A28,LiteratureCost!$A$2:$A$10,0)),INDEX(InterventionCosts!$L$1:$L$2363,MATCH(A28,IF(InterventionCosts!$F$1:$F$2363="Cost per intervention",InterventionCosts!$A$1:$A$2363),0)))} -> 5724.3405 | H28: =G28/exrate -> 306.75984 | I28: per person per year | J28: =G28/SUM(Q28:V28) -> 1 | K28: =Q28/$G28 -> 0.11297682 | L28: =R28/$G28 -> 0.28188603 | M28: =S28/$G28 -> 0.027476601 | N28: =T28/$G28 -> 0.015126698 | O28: =U28/$G28 -> 0.13283373 | P28: =V28/$G28 -> 0.42970013 | Q28: =SUMIFS(InterventionCosts!$K$2:$K$3432,InterventionCosts!$D$2:$D$3432,'Summary of unit costs'!Q$1,InterventionCosts!$A$2:$A$3432,'Summary of unit costs'!$A28) -> 646.71779 | R28: =SUMIFS(InterventionCosts!$K$2:$K$3432,InterventionCosts!$D$2:$D$3432,'Summary of unit costs'!R$1,InterventionCosts!$A$2:$A$3432,'Summary of unit costs'!$A28) -> 1613.6116 | S28: =SUMIFS(InterventionCosts!$K$2:$K$3432,InterventionCosts!$D$2:$D$3432,'Summary of unit costs'!S$1,InterventionCosts!$A$2:$A$3432,'Summary of unit costs'!$A28) -> 157.28542 | T28: =SUMIFS(InterventionCosts!$K$2:$K$3432,InterventionCosts!$D$2:$D$3432,'Summary of unit costs'!T$1,InterventionCosts!$A$2:$A$3432,'Summary of unit costs'!$A28) -> 86.590372 | U28: =SUMIFS(InterventionCosts!$K$2:$K$3432,InterventionCosts!$D$2:$D$3432,'Summary of unit costs'!U$1,InterventionCosts!$A$2:$A$3432,'Summary of unit costs'!$A28) -> 760.38547 | V28: =SUMIFS(InterventionCosts!$K$2:$K$3432,InterventionCosts!$D$2:$D$3432,'Summary of unit costs'!V$1,InterventionCosts!$A$2:$A$3432,'Summary of unit costs'!$A28) -> 2459.7498
A29: ART with POCVL Paeds Kids 10-14 (followup) | C29: As ART costs above, but replacing PCR-based VL with point-of-care GeneXpert testing | E29: Ingredients | F29: ART | G29: {=IF(E29="Literature",INDEX(LiteratureCost!$I$2:$I$10,MATCH('Summary of unit costs'!A29,LiteratureCost!$A$2:$A$10,0)),INDEX(InterventionCosts!$L$1:$L$2363,MATCH(A29,IF(InterventionCosts!$F$1:$F$2363="Cost per intervention",InterventionCosts!$A$1:$A$2363),0)))} -> 3800.5612 | H29: =G29/exrate -> 203.66705 | I29: per person per year | J29: =G29/SUM(Q29:V29) -> 1 | K29: =Q29/$G29 -> 0.085081881 | L29: =R29/$G29 -> 0.42457193 | M29: =S29/$G29 -> 0.020692394 | N29: =T29/$G29 -> 0.022783575 | O29: =U29/$G29 -> 0.10537699 | P29: =V29/$G29 -> 0.34149323 | Q29: =SUMIFS(InterventionCosts!$K$2:$K$3432,InterventionCosts!$D$2:$D$3432,'Summary of unit costs'!Q$1,InterventionCosts!$A$2:$A$3432,'Summary of unit costs'!$A29) -> 323.35889 | R29: =SUMIFS(InterventionCosts!$K$2:$K$3432,InterventionCosts!$D$2:$D$3432,'Summary of unit costs'!R$1,InterventionCosts!$A$2:$A$3432,'Summary of unit costs'!$A29) -> 1613.6116 | S29: =SUMIFS(InterventionCosts!$K$2:$K$3432,InterventionCosts!$D$2:$D$3432,'Summary of unit costs'!S$1,InterventionCosts!$A$2:$A$3432,'Summary of unit costs'!$A29) -> 78.64271 | T29: =SUMIFS(InterventionCosts!$K$2:$K$3432,InterventionCosts!$D$2:$D$3432,'Summary of unit costs'!T$1,InterventionCosts!$A$2:$A$3432,'Summary of unit costs'!$A29) -> 86.590372 | U29: =SUMIFS(InterventionCosts!$K$2:$K$3432,InterventionCosts!$D$2:$D$3432,'Summary of unit costs'!U$1,InterventionCosts!$A$2:$A$3432,'Summary of unit costs'!$A29) -> 400.4917 | V29: =SUMIFS(InterventionCosts!$K$2:$K$3432,InterventionCosts!$D$2:$D$3432,'Summary of unit costs'!V$1,InterventionCosts!$A$2:$A$3432,'Summary of unit costs'!$A29) -> 1297.8659
A30: Medical male circumcision | C30: Number of MMCs in 10+ year olds | E30: Ingredients | F30: MMC | G30: {=IF(E30="Literature",INDEX(LiteratureCost!$I$2:$I$10,MATCH('Summary of unit costs'!A30,LiteratureCost!$A$2:$A$10,0)),INDEX(InterventionCosts!$L$1:$L$2363,MATCH(A30,IF(InterventionCosts!$F$1:$F$2363="Cost per intervention",InterventionCosts!$A$1:$A$2363),0)))} -> 1481.154 | H30: =G30/exrate -> 79.373085 | I30: {=IF(E30="Literature",INDEX(LiteratureCost!$G$2:$G$22,MATCH('Summary of unit costs'!A30,LiteratureCost!$A$2:$A$22,0)),INDEX(InterventionCosts!$L$1:$L$3432,MATCH(A30,IF(InterventionCosts!$F$1:$F$3432="Unit",InterventionCosts!$A$1:$A$3432),0)))} -> per circumcision | K30: Full service cost- do not have this breakdown
A31: Early infant male circumcision | C31: Number of early infant male circumcisions | E31: Ingredients | F31: MMC | G31: {=IF(E31="Literature",INDEX(LiteratureCost!$I$2:$I$10,MATCH('Summary of unit costs'!A31,LiteratureCost!$A$2:$A$10,0)),INDEX(InterventionCosts!$L$1:$L$2363,MATCH(A31,IF(InterventionCosts!$F$1:$F$2363="Cost per intervention",InterventionCosts!$A$1:$A$2363),0)))} -> 740.577 | H31: =G31/exrate -> 39.686543 | I31: {=IF(E31="Literature",INDEX(LiteratureCost!$G$2:$G$22,MATCH('Summary of unit costs'!A31,LiteratureCost!$A$2:$A$22,0)),INDEX(InterventionCosts!$L$1:$L$3432,MATCH(A31,IF(InterventionCosts!$F$1:$F$3432="Unit",InterventionCosts!$A$1:$A$3432),0)))} -> per circumcision | K31: Assumed half of adult cost
A32: Condom distribution in clinics | C32: Total condoms distributed * 80% | E32: Ingredients | F32: PREV | G32: {=IF(E32="Literature",INDEX(LiteratureCost!$I$2:$I$10,MATCH('Summary of unit costs'!A32,LiteratureCost!$A$2:$A$10,0)),INDEX(InterventionCosts!$L$1:$L$2363,MATCH(A32,IF(InterventionCosts!$F$1:$F$2363="Cost per intervention",InterventionCosts!$A$1:$A$2363),0)))} -> 0.94920714 | H32: =G32/exrate -> 0.050866756 | I32: {=IF(E32="Literature",INDEX(LiteratureCost!$G$2:$G$22,MATCH('Summary of unit costs'!A32,LiteratureCost!$A$2:$A$22,0)),INDEX(InterventionCosts!$L$1:$L$3432,MATCH(A32,IF(InterventionCosts!$F$1:$F$3432="Unit",InterventionCosts!$A$1:$A$3432),0)))} -> per condom distributed | J32: =G32/SUM(Q32:V32) -> 1 | K32: =Q32/$G32 -> 0.82385896 | L32: =R32/$G32 -> 0 | M32: =S32/$G32 -> 0 | N32: =T32/$G32 -> 0 | O32: =U32/$G32 -> 0.17614104 | P32: =V32/$G32 -> 0 | Q32: =SUMIFS(InterventionCosts!$K$2:$K$3432,InterventionCosts!$D$2:$D$3432,'Summary of unit costs'!Q$1,InterventionCosts!$A$2:$A$3432,'Summary of unit costs'!$A32) -> 0.7820128 | R32: =SUMIFS(InterventionCosts!$K$2:$K$3432,InterventionCosts!$D$2:$D$3432,'Summary of unit costs'!R$1,InterventionCosts!$A$2:$A$3432,'Summary of unit costs'!$A32) -> 0 | S32: =SUMIFS(InterventionCosts!$K$2:$K$3432,InterventionCosts!$D$2:$D$3432,'Summary of unit costs'!S$1,InterventionCosts!$A$2:$A$3432,'Summary of unit costs'!$A32) -> 0 | T32: =SUMIFS(InterventionCosts!$K$2:$K$3432,InterventionCosts!$D$2:$D$3432,'Summary of unit costs'!T$1,InterventionCosts!$A$2:$A$3432,'Summary of unit costs'!$A32) -> 0 | U32: =SUMIFS(InterventionCosts!$K$2:$K$3432,InterventionCosts!$D$2:$D$3432,'Summary of unit costs'!U$1,InterventionCosts!$A$2:$A$3432,'Summary of unit costs'!$A32) -> 0.16719434 | V32: =SUMIFS(InterventionCosts!$K$2:$K$3432,InterventionCosts!$D$2:$D$3432,'Summary of unit costs'!V$1,InterventionCosts!$A$2:$A$3432,'Summary of unit costs'!$A32) -> 0
A33: Condom distribution in non-traditional outlets (hotels; shops; malls) | C33: Total condoms distributed * 20% | E33: Ingredients | F33: PREV | G33: {=IF(E33="Literature",INDEX(LiteratureCost!$I$2:$I$10,MATCH('Summary of unit costs'!A33,LiteratureCost!$A$2:$A$10,0)),INDEX(InterventionCosts!$L$1:$L$2363,MATCH(A33,IF(InterventionCosts!$F$1:$F$2363="Cost per intervention",InterventionCosts!$A$1:$A$2363),0)))} -> 1.1164015 | H33: =G33/exrate -> 0.05982648 | I33: {=IF(E33="Literature",INDEX(LiteratureCost!$G$2:$G$22,MATCH('Summary of unit costs'!A33,LiteratureCost!$A$2:$A$22,0)),INDEX(InterventionCosts!$L$1:$L$3432,MATCH(A33,IF(InterventionCosts!$F$1:$F$3432="Unit",InterventionCosts!$A$1:$A$3432),0)))} -> per condom distributed | J33: =G33/SUM(Q33:V33) -> 1 | K33: =Q33/$G33 -> 0.70047632 | L33: =R33/$G33 -> 0 | M33: =S33/$G33 -> 0 | N33: =T33/$G33 -> 0 | O33: =U33/$G33 -> 0.29952368 | P33: =V33/$G33 -> 0 | Q33: =SUMIFS(InterventionCosts!$K$2:$K$3432,InterventionCosts!$D$2:$D$3432,'Summary of unit costs'!Q$1,InterventionCosts!$A$2:$A$3432,'Summary of unit costs'!$A33) -> 0.7820128 | R33: =SUMIFS(InterventionCosts!$K$2:$K$3432,InterventionCosts!$D$2:$D$3432,'Summary of unit costs'!R$1,InterventionCosts!$A$2:$A$3432,'Summary of unit costs'!$A33) -> 0 | S33: =SUMIFS(InterventionCosts!$K$2:$K$3432,InterventionCosts!$D$2:$D$3432,'Summary of unit costs'!S$1,InterventionCosts!$A$2:$A$3432,'Summary of unit costs'!$A33) -> 0 | T33: =SUMIFS(InterventionCosts!$K$2:$K$3432,InterventionCosts!$D$2:$D$3432,'Summary of unit costs'!T$1,InterventionCosts!$A$2:$A$3432,'Summary of unit costs'!$A33) -> 0 | U33: =SUMIFS(InterventionCosts!$K$2:$K$3432,InterventionCosts!$D$2:$D$3432,'Summary of unit costs'!U$1,InterventionCosts!$A$2:$A$3432,'Summary of unit costs'!$A33) -> 0.33438867 | V33: =SUMIFS(InterventionCosts!$K$2:$K$3432,InterventionCosts!$D$2:$D$3432,'Summary of unit costs'!V$1,InterventionCosts!$A$2:$A$3432,'Summary of unit costs'!$A33) -> 0
A34: PrEP (oral) Young women | B34: 6 | C34: ="Numbers initiating oral PrEP; average "&B34&" months PrEP use" -> Numbers initiating oral PrEP; average 6 months PrEP use | E34: Ingredients | F34: PREV | G34: {=IF(E34="Literature",INDEX(LiteratureCost!$I$2:$I$10,MATCH('Summary of unit costs'!A34,LiteratureCost!$A$2:$A$10,0)),INDEX(InterventionCosts!$L$1:$L$2363,MATCH(A34,IF(InterventionCosts!$F$1:$F$2363="Cost per intervention",InterventionCosts!$A$1:$A$2363),0)))} -> 1332.638 | H34: =G34/exrate -> 71.414307 | I34: {=IF(E34="Literature",INDEX(LiteratureCost!$G$2:$G$22,MATCH('Summary of unit costs'!A34,LiteratureCost!$A$2:$A$22,0)),INDEX(InterventionCosts!$L$1:$L$3432,MATCH(A34,IF(InterventionCosts!$F$1:$F$3432="Unit",InterventionCosts!$A$1:$A$3432),0)))} -> per user initiated | J34: =G34/SUM(Q34:V34) -> 1 | K34: =Q34/$G34 -> 0.042346274 | L34: =R34/$G34 -> 0.34083976 | M34: =S34/$G34 -> 0 | N34: =T34/$G34 -> 0.18828641 | O34: =U34/$G34 -> 0.12780879 | P34: =V34/$G34 -> 0.30071876 | Q34: =SUMIFS(InterventionCosts!$K$2:$K$3432,InterventionCosts!$D$2:$D$3432,'Summary of unit costs'!Q$1,InterventionCosts!$A$2:$A$3432,'Summary of unit costs'!$A34) -> 56.432252 | R34: =SUMIFS(InterventionCosts!$K$2:$K$3432,InterventionCosts!$D$2:$D$3432,'Summary of unit costs'!R$1,InterventionCosts!$A$2:$A$3432,'Summary of unit costs'!$A34) -> 454.216 | S34: =SUMIFS(InterventionCosts!$K$2:$K$3432,InterventionCosts!$D$2:$D$3432,'Summary of unit costs'!S$1,InterventionCosts!$A$2:$A$3432,'Summary of unit costs'!$A34) -> 0 | T34: =SUMIFS(InterventionCosts!$K$2:$K$3432,InterventionCosts!$D$2:$D$3432,'Summary of unit costs'!T$1,InterventionCosts!$A$2:$A$3432,'Summary of unit costs'!$A34) -> 250.91762 | U34: =SUMIFS(InterventionCosts!$K$2:$K$3432,InterventionCosts!$D$2:$D$3432,'Summary of unit costs'!U$1,InterventionCosts!$A$2:$A$3432,'Summary of unit costs'!$A34) -> 170.32285 | V34: =SUMIFS(InterventionCosts!$K$2:$K$3432,InterventionCosts!$D$2:$D$3432,'Summary of unit costs'!V$1,InterventionCosts!$A$2:$A$3432,'Summary of unit costs'!$A34) -> 400.74923
A35: PrEP (oral) FSW | B35: 3 | C35: ="Numbers initiating oral PrEP; average "&B35&" months PrEP use" -> Numbers initiating oral PrEP; average 3 months PrEP use | E35: Ingredients | F35: PREV | G35: {=IF(E35="Literature",INDEX(LiteratureCost!$I$2:$I$10,MATCH('Summary of unit costs'!A35,LiteratureCost!$A$2:$A$10,0)),INDEX(InterventionCosts!$L$1:$L$2363,MATCH(A35,IF(InterventionCosts!$F$1:$F$2363="Cost per intervention",InterventionCosts!$A$1:$A$2363),0)))} -> 1081.2212 | H35: =G35/exrate -> 57.941216 | I35: {=IF(E35="Literature",INDEX(LiteratureCost!$G$2:$G$22,MATCH('Summary of unit costs'!A35,LiteratureCost!$A$2:$A$22,0)),INDEX(InterventionCosts!$L$1:$L$3432,MATCH(A35,IF(InterventionCosts!$F$1:$F$3432="Unit",InterventionCosts!$A$1:$A$3432),0)))} -> per user initiated | J35: =G35/SUM(Q35:V35) -> 1 | K35: =Q35/$G35 -> 0.064612667 | L35: =R35/$G35 -> 0.24005448 | M35: =S35/$G35 -> 0 | N35: =T35/$G35 -> 0.20395002 | O35: =U35/$G35 -> 0.14231595 | P35: =V35/$G35 -> 0.34906687 | Q35: =SUMIFS(InterventionCosts!$K$2:$K$3432,InterventionCosts!$D$2:$D$3432,'Summary of unit costs'!Q$1,InterventionCosts!$A$2:$A$3432,'Summary of unit costs'!$A35) -> 69.860586 | R35: =SUMIFS(InterventionCosts!$K$2:$K$3432,InterventionCosts!$D$2:$D$3432,'Summary of unit costs'!R$1,InterventionCosts!$A$2:$A$3432,'Summary of unit costs'!$A35) -> 259.552 | S35: =SUMIFS(InterventionCosts!$K$2:$K$3432,InterventionCosts!$D$2:$D$3432,'Summary of unit costs'!S$1,InterventionCosts!$A$2:$A$3432,'Summary of unit costs'!$A35) -> 0 | T35: =SUMIFS(InterventionCosts!$K$2:$K$3432,InterventionCosts!$D$2:$D$3432,'Summary of unit costs'!T$1,InterventionCosts!$A$2:$A$3432,'Summary of unit costs'!$A35) -> 220.51509 | U35: =SUMIFS(InterventionCosts!$K$2:$K$3432,InterventionCosts!$D$2:$D$3432,'Summary of unit costs'!U$1,InterventionCosts!$A$2:$A$3432,'Summary of unit costs'!$A35) -> 153.87503 | V35: =SUMIFS(InterventionCosts!$K$2:$K$3432,InterventionCosts!$D$2:$D$3432,'Summary of unit costs'!V$1,InterventionCosts!$A$2:$A$3432,'Summary of unit costs'!$A35) -> 377.41851
A36: PrEP (oral) Young men | B36: 3 | C36: ="Numbers initiating oral PrEP; average "&B36&" months PrEP use" -> Numbers initiating oral PrEP; average 3 months PrEP use | E36: Ingredients | F36: PREV | G36: {=IF(E36="Literature",INDEX(LiteratureCost!$I$2:$I$10,MATCH('Summary of unit costs'!A36,LiteratureCost!$A$2:$A$10,0)),INDEX(InterventionCosts!$L$1:$L$2363,MATCH(A36,IF(InterventionCosts!$F$1:$F$2363="Cost per intervention",InterventionCosts!$A$1:$A$2363),0)))} -> 1048.7534 | H36: =G36/exrate -> 56.201311 | I36: {=IF(E36="Literature",INDEX(LiteratureCost!$G$2:$G$22,MATCH('Summary of unit costs'!A36,LiteratureCost!$A$2:$A$22,0)),INDEX(InterventionCosts!$L$1:$L$3432,MATCH(A36,IF(InterventionCosts!$F$1:$F$3432="Unit",InterventionCosts!$A$1:$A$3432),0)))} -> per user initiated | J36: =G36/SUM(Q36:V36) -> 1 | K36: =Q36/$G36 -> 0.029030925 | L36: =R36/$G36 -> 0.2474862 | M36: =S36/$G36 -> 0 | N36: =T36/$G36 -> 0.23788224 | O36: =U36/$G36 -> 0.14469651 | P36: =V36/$G36 -> 0.34090413 | Q36: =SUMIFS(InterventionCosts!$K$2:$K$3432,InterventionCosts!$D$2:$D$3432,'Summary of unit costs'!Q$1,InterventionCosts!$A$2:$A$3432,'Summary of unit costs'!$A36) -> 30.446282 | R36: =SUMIFS(InterventionCosts!$K$2:$K$3432,InterventionCosts!$D$2:$D$3432,'Summary of unit costs'!R$1,InterventionCosts!$A$2:$A$3432,'Summary of unit costs'!$A36) -> 259.552 | S36: =SUMIFS(InterventionCosts!$K$2:$K$3432,InterventionCosts!$D$2:$D$3432,'Summary of unit costs'!S$1,InterventionCosts!$A$2:$A$3432,'Summary of unit costs'!$A36) -> 0 | T36: =SUMIFS(InterventionCosts!$K$2:$K$3432,InterventionCosts!$D$2:$D$3432,'Summary of unit costs'!T$1,InterventionCosts!$A$2:$A$3432,'Summary of unit costs'!$A36) -> 249.47982 | U36: =SUMIFS(InterventionCosts!$K$2:$K$3432,InterventionCosts!$D$2:$D$3432,'Summary of unit costs'!U$1,InterventionCosts!$A$2:$A$3432,'Summary of unit costs'!$A36) -> 151.75097 | V36: =SUMIFS(InterventionCosts!$K$2:$K$3432,InterventionCosts!$D$2:$D$3432,'Summary of unit costs'!V$1,InterventionCosts!$A$2:$A$3432,'Summary of unit costs'!$A36) -> 357.52438
A37: PrEP (oral) MSM | B37: 6 | C37: ="Numbers initiating oral PrEP; average "&B37&" months PrEP use" -> Numbers initiating oral PrEP; average 6 months PrEP use | E37: Ingredients | F37: PREV | G37: {=IF(E37="Literature",INDEX(LiteratureCost!$I$2:$I$10,MATCH('Summary of unit costs'!A37,LiteratureCost!$A$2:$A$10,0)),INDEX(InterventionCosts!$L$1:$L$2363,MATCH(A37,IF(InterventionCosts!$F$1:$F$2363="Cost per intervention",InterventionCosts!$A$1:$A$2363),0)))} -> 1289.3426 | H37: =G37/exrate -> 69.094166 | I37: {=IF(E37="Literature",INDEX(LiteratureCost!$G$2:$G$22,MATCH('Summary of unit costs'!A37,LiteratureCost!$A$2:$A$22,0)),INDEX(InterventionCosts!$L$1:$L$3432,MATCH(A37,IF(InterventionCosts!$F$1:$F$3432="Unit",InterventionCosts!$A$1:$A$3432),0)))} -> per user initiated | J37: =G37/SUM(Q37:V37) -> 1 | K37: =Q37/$G37 -> 0.035564301 | L37: =R37/$G37 -> 0.35228496 | M37: =S37/$G37 -> 0 | N37: =T37/$G37 -> 0.17214423 | O37: =U37/$G37 -> 0.12990375 | P37: =V37/$G37 -> 0.31010276 | Q37: =SUMIFS(InterventionCosts!$K$2:$K$3432,InterventionCosts!$D$2:$D$3432,'Summary of unit costs'!Q$1,InterventionCosts!$A$2:$A$3432,'Summary of unit costs'!$A37) -> 45.854568 | R37: =SUMIFS(InterventionCosts!$K$2:$K$3432,InterventionCosts!$D$2:$D$3432,'Summary of unit costs'!R$1,InterventionCosts!$A$2:$A$3432,'Summary of unit costs'!$A37) -> 454.216 | S37: =SUMIFS(InterventionCosts!$K$2:$K$3432,InterventionCosts!$D$2:$D$3432,'Summary of unit costs'!S$1,InterventionCosts!$A$2:$A$3432,'Summary of unit costs'!$A37) -> 0 | T37: =SUMIFS(InterventionCosts!$K$2:$K$3432,InterventionCosts!$D$2:$D$3432,'Summary of unit costs'!T$1,InterventionCosts!$A$2:$A$3432,'Summary of unit costs'!$A37) -> 221.95289 | U37: =SUMIFS(InterventionCosts!$K$2:$K$3432,InterventionCosts!$D$2:$D$3432,'Summary of unit costs'!U$1,InterventionCosts!$A$2:$A$3432,'Summary of unit costs'!$A37) -> 167.49044 | V37: =SUMIFS(InterventionCosts!$K$2:$K$3432,InterventionCosts!$D$2:$D$3432,'Summary of unit costs'!V$1,InterventionCosts!$A$2:$A$3432,'Summary of unit costs'!$A37) -> 399.8287
A38: CAB-LA Young women | B38: 12 | C38: ="Numbers initiating CAB-LA; average "&B38&" months PrEP use" -> Numbers initiating CAB-LA; average 12 months PrEP use | E38: Ingredients | F38: PREV | G38: {=IF(E38="Literature",INDEX(LiteratureCost!$I$2:$I$10,MATCH('Summary of unit costs'!A38,LiteratureCost!$A$2:$A$10,0)),INDEX(InterventionCosts!$L$1:$L$2363,MATCH(A38,IF(InterventionCosts!$F$1:$F$2363="Cost per intervention",InterventionCosts!$A$1:$A$2363),0)))} -> 5021.9471 | H38: =G38/exrate -> 269.11951 | I38: {=IF(E38="Literature",INDEX(LiteratureCost!$G$2:$G$22,MATCH('Summary of unit costs'!A38,LiteratureCost!$A$2:$A$22,0)),INDEX(InterventionCosts!$L$1:$L$3432,MATCH(A38,IF(InterventionCosts!$F$1:$F$3432="Unit",InterventionCosts!$A$1:$A$3432),0)))} -> per user initiated | J38: =G38/SUM(Q38:V38) -> 1 | K38: =Q38/$G38 -> 0.023836363 | L38: =R38/$G38 -> 0.74572817 | M38: =S38/$G38 -> 0 | N38: =T38/$G38 -> 0.021938332 | O38: =U38/$G38 -> 0.06668755 | P38: =V38/$G38 -> 0.14180959 | Q38: =SUMIFS(InterventionCosts!$K$2:$K$3432,InterventionCosts!$D$2:$D$3432,'Summary of unit costs'!Q$1,InterventionCosts!$A$2:$A$3432,'Summary of unit costs'!$A38) -> 119.70495 | R38: =SUMIFS(InterventionCosts!$K$2:$K$3432,InterventionCosts!$D$2:$D$3432,'Summary of unit costs'!R$1,InterventionCosts!$A$2:$A$3432,'Summary of unit costs'!$A38) -> 3745.0074 | S38: =SUMIFS(InterventionCosts!$K$2:$K$3432,InterventionCosts!$D$2:$D$3432,'Summary of unit costs'!S$1,InterventionCosts!$A$2:$A$3432,'Summary of unit costs'!$A38) -> 0 | T38: =SUMIFS(InterventionCosts!$K$2:$K$3432,InterventionCosts!$D$2:$D$3432,'Summary of unit costs'!T$1,InterventionCosts!$A$2:$A$3432,'Summary of unit costs'!$A38) -> 110.17314 | U38: =SUMIFS(InterventionCosts!$K$2:$K$3432,InterventionCosts!$D$2:$D$3432,'Summary of unit costs'!U$1,InterventionCosts!$A$2:$A$3432,'Summary of unit costs'!$A38) -> 334.90135 | V38: =SUMIFS(InterventionCosts!$K$2:$K$3432,InterventionCosts!$D$2:$D$3432,'Summary of unit costs'!V$1,InterventionCosts!$A$2:$A$3432,'Summary of unit costs'!$A38) -> 712.16024
A39: CAB-LA FSW | B39: 12 | C39: ="Numbers initiating CAB-LA; average "&B39&" months PrEP use" -> Numbers initiating CAB-LA; average 12 months PrEP use | E39: Ingredients | F39: PREV | G39: {=IF(E39="Literature",INDEX(LiteratureCost!$I$2:$I$10,MATCH('Summary of unit costs'!A39,LiteratureCost!$A$2:$A$10,0)),INDEX(InterventionCosts!$L$1:$L$2363,MATCH(A39,IF(InterventionCosts!$F$1:$F$2363="Cost per intervention",InterventionCosts!$A$1:$A$2363),0)))} -> 5053.7391 | H39: =G39/exrate -> 270.8232 | I39: {=IF(E39="Literature",INDEX(LiteratureCost!$G$2:$G$22,MATCH('Summary of unit costs'!A39,LiteratureCost!$A$2:$A$22,0)),INDEX(InterventionCosts!$L$1:$L$3432,MATCH(A39,IF(InterventionCosts!$F$1:$F$3432="Unit",InterventionCosts!$A$1:$A$3432),0)))} -> per user initiated | J39: =G39/SUM(Q39:V39) -> 1 | K39: =Q39/$G39 -> 0.030713025 | L39: =R39/$G39 -> 0.74103695 | M39: =S39/$G39 -> 0 | N39: =T39/$G39 -> 0.016068976 | O39: =U39/$G39 -> 0.06667958 | P39: =V39/$G39 -> 0.14550147 | Q39: =SUMIFS(InterventionCosts!$K$2:$K$3432,InterventionCosts!$D$2:$D$3432,'Summary of unit costs'!Q$1,InterventionCosts!$A$2:$A$3432,'Summary of unit costs'!$A39) -> 155.21561 | R39: =SUMIFS(InterventionCosts!$K$2:$K$3432,InterventionCosts!$D$2:$D$3432,'Summary of unit costs'!R$1,InterventionCosts!$A$2:$A$3432,'Summary of unit costs'!$A39) -> 3745.0074 | S39: =SUMIFS(InterventionCosts!$K$2:$K$3432,InterventionCosts!$D$2:$D$3432,'Summary of unit costs'!S$1,InterventionCosts!$A$2:$A$3432,'Summary of unit costs'!$A39) -> 0 | T39: =SUMIFS(InterventionCosts!$K$2:$K$3432,InterventionCosts!$D$2:$D$3432,'Summary of unit costs'!T$1,InterventionCosts!$A$2:$A$3432,'Summary of unit costs'!$A39) -> 81.208414 | U39: =SUMIFS(InterventionCosts!$K$2:$K$3432,InterventionCosts!$D$2:$D$3432,'Summary of unit costs'!U$1,InterventionCosts!$A$2:$A$3432,'Summary of unit costs'!$A39) -> 336.9812 | V39: =SUMIFS(InterventionCosts!$K$2:$K$3432,InterventionCosts!$D$2:$D$3432,'Summary of unit costs'!V$1,InterventionCosts!$A$2:$A$3432,'Summary of unit costs'!$A39) -> 735.32646
A40: CAB-LA Young men | B40: 12 | C40: ="Numbers initiating CAB-LA; average "&B40&" months PrEP use" -> Numbers initiating CAB-LA; average 12 months PrEP use | E40: Ingredients | F40: PREV | G40: {=IF(E40="Literature",INDEX(LiteratureCost!$I$2:$I$10,MATCH('Summary of unit costs'!A40,LiteratureCost!$A$2:$A$10,0)),INDEX(InterventionCosts!$L$1:$L$2363,MATCH(A40,IF(InterventionCosts!$F$1:$F$2363="Cost per intervention",InterventionCosts!$A$1:$A$2363),0)))} -> 4980.7324 | H40: =G40/exrate -> 266.91087 | I40: {=IF(E40="Literature",INDEX(LiteratureCost!$G$2:$G$22,MATCH('Summary of unit costs'!A40,LiteratureCost!$A$2:$A$22,0)),INDEX(InterventionCosts!$L$1:$L$3432,MATCH(A40,IF(InterventionCosts!$F$1:$F$3432="Unit",InterventionCosts!$A$1:$A$3432),0)))} -> per user initiated | J40: =G40/SUM(Q40:V40) -> 1 | K40: =Q40/$G40 -> 0.016775259 | L40: =R40/$G40 -> 0.75189894 | M40: =S40/$G40 -> 0 | N40: =T40/$G40 -> 0.022119868 | O40: =U40/$G40 -> 0.066698034 | P40: =V40/$G40 -> 0.1425079 | Q40: =SUMIFS(InterventionCosts!$K$2:$K$3432,InterventionCosts!$D$2:$D$3432,'Summary of unit costs'!Q$1,InterventionCosts!$A$2:$A$3432,'Summary of unit costs'!$A40) -> 83.553074 | R40: =SUMIFS(InterventionCosts!$K$2:$K$3432,InterventionCosts!$D$2:$D$3432,'Summary of unit costs'!R$1,InterventionCosts!$A$2:$A$3432,'Summary of unit costs'!$A40) -> 3745.0074 | S40: =SUMIFS(InterventionCosts!$K$2:$K$3432,InterventionCosts!$D$2:$D$3432,'Summary of unit costs'!S$1,InterventionCosts!$A$2:$A$3432,'Summary of unit costs'!$A40) -> 0 | T40: =SUMIFS(InterventionCosts!$K$2:$K$3432,InterventionCosts!$D$2:$D$3432,'Summary of unit costs'!T$1,InterventionCosts!$A$2:$A$3432,'Summary of unit costs'!$A40) -> 110.17314 | U40: =SUMIFS(InterventionCosts!$K$2:$K$3432,InterventionCosts!$D$2:$D$3432,'Summary of unit costs'!U$1,InterventionCosts!$A$2:$A$3432,'Summary of unit costs'!$A40) -> 332.20506 | V40: =SUMIFS(InterventionCosts!$K$2:$K$3432,InterventionCosts!$D$2:$D$3432,'Summary of unit costs'!V$1,InterventionCosts!$A$2:$A$3432,'Summary of unit costs'!$A40) -> 709.79372
A41: CAB-LA MSM | B41: 18 | C41: ="Numbers initiating CAB-LA; average "&B41&" months PrEP use" -> Numbers initiating CAB-LA; average 18 months PrEP use | E41: Ingredients | F41: PREV | G41: {=IF(E41="Literature",INDEX(LiteratureCost!$I$2:$I$10,MATCH('Summary of unit costs'!A41,LiteratureCost!$A$2:$A$10,0)),INDEX(InterventionCosts!$L$1:$L$2363,MATCH(A41,IF(InterventionCosts!$F$1:$F$2363="Cost per intervention",InterventionCosts!$A$1:$A$2363),0)))} -> 6911.0631 | H41: =G41/exrate -> 370.35474 | I41: {=IF(E41="Literature",INDEX(LiteratureCost!$G$2:$G$22,MATCH('Summary of unit costs'!A41,LiteratureCost!$A$2:$A$22,0)),INDEX(InterventionCosts!$L$1:$L$3432,MATCH(A41,IF(InterventionCosts!$F$1:$F$3432="Unit",InterventionCosts!$A$1:$A$3432),0)))} -> per user initiated | J41: =G41/SUM(Q41:V41) -> 1 | K41: =Q41/$G41 -> 0.017248955 | L41: =R41/$G41 -> 0.77412267 | M41: =S41/$G41 -> 0 | N41: =T41/$G41 -> 0.012374625 | O41: =U41/$G41 -> 0.066341223 | P41: =V41/$G41 -> 0.12991253 | Q41: =SUMIFS(InterventionCosts!$K$2:$K$3432,InterventionCosts!$D$2:$D$3432,'Summary of unit costs'!Q$1,InterventionCosts!$A$2:$A$3432,'Summary of unit costs'!$A41) -> 119.20862 | R41: =SUMIFS(InterventionCosts!$K$2:$K$3432,InterventionCosts!$D$2:$D$3432,'Summary of unit costs'!R$1,InterventionCosts!$A$2:$A$3432,'Summary of unit costs'!$A41) -> 5350.0106 | S41: =SUMIFS(InterventionCosts!$K$2:$K$3432,InterventionCosts!$D$2:$D$3432,'Summary of unit costs'!S$1,InterventionCosts!$A$2:$A$3432,'Summary of unit costs'!$A41) -> 0 | T41: =SUMIFS(InterventionCosts!$K$2:$K$3432,InterventionCosts!$D$2:$D$3432,'Summary of unit costs'!T$1,InterventionCosts!$A$2:$A$3432,'Summary of unit costs'!$A41) -> 85.521811 | U41: =SUMIFS(InterventionCosts!$K$2:$K$3432,InterventionCosts!$D$2:$D$3432,'Summary of unit costs'!U$1,InterventionCosts!$A$2:$A$3432,'Summary of unit costs'!$A41) -> 458.48838 | V41: =SUMIFS(InterventionCosts!$K$2:$K$3432,InterventionCosts!$D$2:$D$3432,'Summary of unit costs'!V$1,InterventionCosts!$A$2:$A$3432,'Summary of unit costs'!$A41) -> 897.83366
A42: Dapivirine ring | B42: 6 | C42: ="Numbers initiating DVR; average "&B42&" months PrEP use" -> Numbers initiating DVR; average 6 months PrEP use | E42: Ingredients | F42: PREV | G42: {=IF(E42="Literature",INDEX(LiteratureCost!$I$2:$I$10,MATCH('Summary of unit costs'!A42,LiteratureCost!$A$2:$A$10,0)),INDEX(InterventionCosts!$L$1:$L$2363,MATCH(A42,IF(InterventionCosts!$F$1:$F$2363="Cost per intervention",InterventionCosts!$A$1:$A$2363),0)))} -> 2551.3166 | H42: =G42/exrate -> 136.72169 | I42: {=IF(E42="Literature",INDEX(LiteratureCost!$G$2:$G$22,MATCH('Summary of unit costs'!A42,LiteratureCost!$A$2:$A$22,0)),INDEX(InterventionCosts!$L$1:$L$3432,MATCH(A42,IF(InterventionCosts!$F$1:$F$3432="Unit",InterventionCosts!$A$1:$A$3432),0)))} -> per user initiated | J42: =G42/SUM(Q42:V42) -> 1 | K42: =Q42/$G42 -> 0.01360862 | L42: =R42/$G42 -> 0.72198831 | M42: =S42/$G42 -> 0 | N42: =T42/$G42 -> 0.017167734 | O42: =U42/$G42 -> 0.067914471 | P42: =V42/$G42 -> 0.17932087 | Q42: =SUMIFS(InterventionCosts!$K$2:$K$3432,InterventionCosts!$D$2:$D$3432,'Summary of unit costs'!Q$1,InterventionCosts!$A$2:$A$3432,'Summary of unit costs'!$A42) -> 34.719898 | R42: =SUMIFS(InterventionCosts!$K$2:$K$3432,InterventionCosts!$D$2:$D$3432,'Summary of unit costs'!R$1,InterventionCosts!$A$2:$A$3432,'Summary of unit costs'!$A42) -> 1842.0208 | S42: =SUMIFS(InterventionCosts!$K$2:$K$3432,InterventionCosts!$D$2:$D$3432,'Summary of unit costs'!S$1,InterventionCosts!$A$2:$A$3432,'Summary of unit costs'!$A42) -> 0 | T42: =SUMIFS(InterventionCosts!$K$2:$K$3432,InterventionCosts!$D$2:$D$3432,'Summary of unit costs'!T$1,InterventionCosts!$A$2:$A$3432,'Summary of unit costs'!$A42) -> 43.800326 | U42: =SUMIFS(InterventionCosts!$K$2:$K$3432,InterventionCosts!$D$2:$D$3432,'Summary of unit costs'!U$1,InterventionCosts!$A$2:$A$3432,'Summary of unit costs'!$A42) -> 173.27132 | V42: =SUMIFS(InterventionCosts!$K$2:$K$3432,InterventionCosts!$D$2:$D$3432,'Summary of unit costs'!V$1,InterventionCosts!$A$2:$A$3432,'Summary of unit costs'!$A42) -> 457.50431
A43: PMTCT (mother not on any ART; presentation in labour) | C43: HIV+ pregnant women diagnosed at birth | E43: Ingredients | F43: PREV | G43: {=IF(E43="Literature",0,INDEX(InterventionCosts!$L$1:$L$3432,MATCH(A43,IF(InterventionCosts!$F$1:$F$3432="Cost per intervention",InterventionCosts!$A$1:$A$3432),0)))} -> 262.94033 | H43: =G43/exrate -> 14.090625 | I43: {=IF(E43="Literature",INDEX(LiteratureCost!$G$2:$G$22,MATCH('Summary of unit costs'!A43,LiteratureCost!$A$2:$A$22,0)),INDEX(InterventionCosts!$L$1:$L$3432,MATCH(A43,IF(InterventionCosts!$F$1:$F$3432="Unit",InterventionCosts!$A$1:$A$3432),0)))} -> per mother-baby pair | J43: =G43/SUM(Q43:V43) -> 1 | K43: =Q43/$G43 -> 0 | L43: =R43/$G43 -> 1 | M43: =S43/$G43 -> 0 | N43: =T43/$G43 -> 0 | O43: =U43/$G43 -> 0 | P43: =V43/$G43 -> 0 | Q43: =SUMIFS(InterventionCosts!$K$2:$K$3432,InterventionCosts!$D$2:$D$3432,'Summary of unit costs'!Q$1,InterventionCosts!$A$2:$A$3432,'Summary of unit costs'!$A43) -> 0 | R43: =SUMIFS(InterventionCosts!$K$2:$K$3432,InterventionCosts!$D$2:$D$3432,'Summary of unit costs'!R$1,InterventionCosts!$A$2:$A$3432,'Summary of unit costs'!$A43) -> 262.94033 | S43: =SUMIFS(InterventionCosts!$K$2:$K$3432,InterventionCosts!$D$2:$D$3432,'Summary of unit costs'!S$1,InterventionCosts!$A$2:$A$3432,'Summary of unit costs'!$A43) -> 0 | T43: =SUMIFS(InterventionCosts!$K$2:$K$3432,InterventionCosts!$D$2:$D$3432,'Summary of unit costs'!T$1,InterventionCosts!$A$2:$A$3432,'Summary of unit costs'!$A43) -> 0 | U43: =SUMIFS(InterventionCosts!$K$2:$K$3432,InterventionCosts!$D$2:$D$3432,'Summary of unit costs'!U$1,InterventionCosts!$A$2:$A$3432,'Summary of unit costs'!$A43) -> 0 | V43: =SUMIFS(InterventionCosts!$K$2:$K$3432,InterventionCosts!$D$2:$D$3432,'Summary of unit costs'!V$1,InterventionCosts!$A$2:$A$3432,'Summary of unit costs'!$A43) -> 0
A44: Testing at birth | C44: PCR HIV testing of infants at birth | E44: Ingredients | F44: PMTCT | G44: {=IF(E44="Literature",0,INDEX(InterventionCosts!$L$1:$L$3432,MATCH(A44,IF(InterventionCosts!$F$1:$F$3432="Cost per intervention",InterventionCosts!$A$1:$A$3432),0)))} -> 573.37584 | H44: =G44/exrate -> 30.726454 | I44: {=IF(E44="Literature",INDEX(LiteratureCost!$G$2:$G$22,MATCH('Summary of unit costs'!A44,LiteratureCost!$A$2:$A$22,0)),INDEX(InterventionCosts!$L$1:$L$3432,MATCH(A44,IF(InterventionCosts!$F$1:$F$3432="Unit",InterventionCosts!$A$1:$A$3432),0)))} -> per client tested | J44: =G44/SUM(Q44:V44) -> 1 | K44: =Q44/$G44 -> 0.0018514906 | L44: =R44/$G44 -> 0 | M44: =S44/$G44 -> 0 | N44: =T44/$G44 -> 0.86345688 | O44: =U44/$G44 -> 0 | P44: =V44/$G44 -> 0.13469163 | Q44: =SUMIFS(InterventionCosts!$K$2:$K$3432,InterventionCosts!$D$2:$D$3432,'Summary of unit costs'!Q$1,InterventionCosts!$A$2:$A$3432,'Summary of unit costs'!$A44) -> 1.0616 | R44: =SUMIFS(InterventionCosts!$K$2:$K$3432,InterventionCosts!$D$2:$D$3432,'Summary of unit costs'!R$1,InterventionCosts!$A$2:$A$3432,'Summary of unit costs'!$A44) -> 0 | S44: =SUMIFS(InterventionCosts!$K$2:$K$3432,InterventionCosts!$D$2:$D$3432,'Summary of unit costs'!S$1,InterventionCosts!$A$2:$A$3432,'Summary of unit costs'!$A44) -> 0 | T44: =SUMIFS(InterventionCosts!$K$2:$K$3432,InterventionCosts!$D$2:$D$3432,'Summary of unit costs'!T$1,InterventionCosts!$A$2:$A$3432,'Summary of unit costs'!$A44) -> 495.08532 | U44: =SUMIFS(InterventionCosts!$K$2:$K$3432,InterventionCosts!$D$2:$D$3432,'Summary of unit costs'!U$1,InterventionCosts!$A$2:$A$3432,'Summary of unit costs'!$A44) -> 0 | V44: =SUMIFS(InterventionCosts!$K$2:$K$3432,InterventionCosts!$D$2:$D$3432,'Summary of unit costs'!V$1,InterventionCosts!$A$2:$A$3432,'Summary of unit costs'!$A44) -> 77.228926
A45: Testing at 10 weeks | C45: PCR HIV testing of infants at 10 weeks of age | E45: Ingredients | F45: PMTCT | G45: {=IF(E45="Literature",0,INDEX(InterventionCosts!$L$1:$L$3432,MATCH(A45,IF(InterventionCosts!$F$1:$F$3432="Cost per intervention",InterventionCosts!$A$1:$A$3432),0)))} -> 540.98356 | H45: =G45/exrate -> 28.990594 | I45: {=IF(E45="Literature",INDEX(LiteratureCost!$G$2:$G$22,MATCH('Summary of unit costs'!A45,LiteratureCost!$A$2:$A$22,0)),INDEX(InterventionCosts!$L$1:$L$3432,MATCH(A45,IF(InterventionCosts!$F$1:$F$3432="Unit",InterventionCosts!$A$1:$A$3432),0)))} -> per client tested | J45: =G45/SUM(Q45:V45) -> 1 | K45: =Q45/$G45 -> 0.0019623517 | L45: =R45/$G45 -> 0 | M45: =S45/$G45 -> 0 | N45: =T45/$G45 -> 0.91515778 | O45: =U45/$G45 -> 0 | P45: =V45/$G45 -> 0.082879867 | Q45: =SUMIFS(InterventionCosts!$K$2:$K$3432,InterventionCosts!$D$2:$D$3432,'Summary of unit costs'!Q$1,InterventionCosts!$A$2:$A$3432,'Summary of unit costs'!$A45) -> 1.0616 | R45: =SUMIFS(InterventionCosts!$K$2:$K$3432,InterventionCosts!$D$2:$D$3432,'Summary of unit costs'!R$1,InterventionCosts!$A$2:$A$3432,'Summary of unit costs'!$A45) -> 0 | S45: =SUMIFS(InterventionCosts!$K$2:$K$3432,InterventionCosts!$D$2:$D$3432,'Summary of unit costs'!S$1,InterventionCosts!$A$2:$A$3432,'Summary of unit costs'!$A45) -> 0 | T45: =SUMIFS(InterventionCosts!$K$2:$K$3432,InterventionCosts!$D$2:$D$3432,'Summary of unit costs'!T$1,InterventionCosts!$A$2:$A$3432,'Summary of unit costs'!$A45) -> 495.08532 | U45: =SUMIFS(InterventionCosts!$K$2:$K$3432,InterventionCosts!$D$2:$D$3432,'Summary of unit costs'!U$1,InterventionCosts!$A$2:$A$3432,'Summary of unit costs'!$A45) -> 0 | V45: =SUMIFS(InterventionCosts!$K$2:$K$3432,InterventionCosts!$D$2:$D$3432,'Summary of unit costs'!V$1,InterventionCosts!$A$2:$A$3432,'Summary of unit costs'!$A45) -> 44.836646
A46: Testing at 6 months | C46: PCR HIV testing of infants at 6 months of age | E46: Ingredients | F46: PMTCT | G46: {=IF(E46="Literature",0,INDEX(InterventionCosts!$L$1:$L$3432,MATCH(A46,IF(InterventionCosts!$F$1:$F$3432="Cost per intervention",InterventionCosts!$A$1:$A$3432),0)))} -> 540.98356 | H46: =G46/exrate -> 28.990594 | I46: {=IF(E46="Literature",INDEX(LiteratureCost!$G$2:$G$22,MATCH('Summary of unit costs'!A46,LiteratureCost!$A$2:$A$22,0)),INDEX(InterventionCosts!$L$1:$L$3432,MATCH(A46,IF(InterventionCosts!$F$1:$F$3432="Unit",InterventionCosts!$A$1:$A$3432),0)))} -> per client tested | J46: =G46/SUM(Q46:V46) -> 1 | K46: =Q46/$G46 -> 0.0019623517 | L46: =R46/$G46 -> 0 | M46: =S46/$G46 -> 0 | N46: =T46/$G46 -> 0.91515778 | O46: =U46/$G46 -> 0 | P46: =V46/$G46 -> 0.082879867 | Q46: =SUMIFS(InterventionCosts!$K$2:$K$3432,InterventionCosts!$D$2:$D$3432,'Summary of unit costs'!Q$1,InterventionCosts!$A$2:$A$3432,'Summary of unit costs'!$A46) -> 1.0616 | R46: =SUMIFS(InterventionCosts!$K$2:$K$3432,InterventionCosts!$D$2:$D$3432,'Summary of unit costs'!R$1,InterventionCosts!$A$2:$A$3432,'Summary of unit costs'!$A46) -> 0 | S46: =SUMIFS(InterventionCosts!$K$2:$K$3432,InterventionCosts!$D$2:$D$3432,'Summary of unit costs'!S$1,InterventionCosts!$A$2:$A$3432,'Summary of unit costs'!$A46) -> 0 | T46: =SUMIFS(InterventionCosts!$K$2:$K$3432,InterventionCosts!$D$2:$D$3432,'Summary of unit costs'!T$1,InterventionCosts!$A$2:$A$3432,'Summary of unit costs'!$A46) -> 495.08532 | U46: =SUMIFS(InterventionCosts!$K$2:$K$3432,InterventionCosts!$D$2:$D$3432,'Summary of unit costs'!U$1,InterventionCosts!$A$2:$A$3432,'Summary of unit costs'!$A46) -> 0 | V46: =SUMIFS(InterventionCosts!$K$2:$K$3432,InterventionCosts!$D$2:$D$3432,'Summary of unit costs'!V$1,InterventionCosts!$A$2:$A$3432,'Summary of unit costs'!$A46) -> 44.836646
A47: General HTS (negative) | C47: HTS in the general population, negative test | E47: Ingredients | F47: HTS | G47: {=IF(E47="Literature",0,INDEX(InterventionCosts!$L$1:$L$3432,MATCH(A47,IF(InterventionCosts!$F$1:$F$3432="Cost per intervention",InterventionCosts!$A$1:$A$3432),0)))} -> 72.369909 | H47: =G47/exrate -> 3.8782078 | I47: {=IF(E47="Literature",INDEX(LiteratureCost!$G$2:$G$22,MATCH('Summary of unit costs'!A47,LiteratureCost!$A$2:$A$22,0)),INDEX(InterventionCosts!$L$1:$L$3432,MATCH(A47,IF(InterventionCosts!$F$1:$F$3432="Unit",InterventionCosts!$A$1:$A$3432),0)))} -> per client tested | J47: =G47/SUM(Q47:V47) -> 1 | K47: =Q47/$G47 -> 0.46829132 | L47: =R47/$G47 -> 0 | M47: =S47/$G47 -> 0.019927329 | N47: =T47/$G47 -> 0 | O47: =U47/$G47 -> 0.059188506 | P47: =V47/$G47 -> 0.45259284 | Q47: =SUMIFS(InterventionCosts!$K$2:$K$3432,InterventionCosts!$D$2:$D$3432,'Summary of unit costs'!Q$1,InterventionCosts!$A$2:$A$3432,'Summary of unit costs'!$A47) -> 33.8902 | R47: =SUMIFS(InterventionCosts!$K$2:$K$3432,InterventionCosts!$D$2:$D$3432,'Summary of unit costs'!R$1,InterventionCosts!$A$2:$A$3432,'Summary of unit costs'!$A47) -> 0 | S47: =SUMIFS(InterventionCosts!$K$2:$K$3432,InterventionCosts!$D$2:$D$3432,'Summary of unit costs'!S$1,InterventionCosts!$A$2:$A$3432,'Summary of unit costs'!$A47) -> 1.442139 | T47: =SUMIFS(InterventionCosts!$K$2:$K$3432,InterventionCosts!$D$2:$D$3432,'Summary of unit costs'!T$1,InterventionCosts!$A$2:$A$3432,'Summary of unit costs'!$A47) -> 0 | U47: =SUMIFS(InterventionCosts!$K$2:$K$3432,InterventionCosts!$D$2:$D$3432,'Summary of unit costs'!U$1,InterventionCosts!$A$2:$A$3432,'Summary of unit costs'!$A47) -> 4.2834667 | V47: =SUMIFS(InterventionCosts!$K$2:$K$3432,InterventionCosts!$D$2:$D$3432,'Summary of unit costs'!V$1,InterventionCosts!$A$2:$A$3432,'Summary of unit costs'!$A47) -> 32.754103
A48: General HTS (positive) | C48: HTS in the general population, positive test | E48: Ingredients | F48: HTS | G48: {=IF(E48="Literature",0,INDEX(InterventionCosts!$L$1:$L$3432,MATCH(A48,IF(InterventionCosts!$F$1:$F$3432="Cost per intervention",InterventionCosts!$A$1:$A$3432),0)))} -> 105.44739 | H48: =G48/exrate -> 5.6507864 | I48: {=IF(E48="Literature",INDEX(LiteratureCost!$G$2:$G$22,MATCH('Summary of unit costs'!A48,LiteratureCost!$A$2:$A$22,0)),INDEX(InterventionCosts!$L$1:$L$3432,MATCH(A48,IF(InterventionCosts!$F$1:$F$3432="Unit",InterventionCosts!$A$1:$A$3432),0)))} -> per client tested | J48: =G48/SUM(Q48:V48) -> 1 | K48: =Q48/$G48 -> 0.39823548 | L48: =R48/$G48 -> 0 | M48: =S48/$G48 -> 0.013676384 | N48: =T48/$G48 -> 0.00013635226 | O48: =U48/$G48 -> 0.040621837 | P48: =V48/$G48 -> 0.54732995 | Q48: =SUMIFS(InterventionCosts!$K$2:$K$3432,InterventionCosts!$D$2:$D$3432,'Summary of unit costs'!Q$1,InterventionCosts!$A$2:$A$3432,'Summary of unit costs'!$A48) -> 41.992892 | R48: =SUMIFS(InterventionCosts!$K$2:$K$3432,InterventionCosts!$D$2:$D$3432,'Summary of unit costs'!R$1,InterventionCosts!$A$2:$A$3432,'Summary of unit costs'!$A48) -> 0 | S48: =SUMIFS(InterventionCosts!$K$2:$K$3432,InterventionCosts!$D$2:$D$3432,'Summary of unit costs'!S$1,InterventionCosts!$A$2:$A$3432,'Summary of unit costs'!$A48) -> 1.442139 | T48: =SUMIFS(InterventionCosts!$K$2:$K$3432,InterventionCosts!$D$2:$D$3432,'Summary of unit costs'!T$1,InterventionCosts!$A$2:$A$3432,'Summary of unit costs'!$A48) -> 0.01437799 | U48: =SUMIFS(InterventionCosts!$K$2:$K$3432,InterventionCosts!$D$2:$D$3432,'Summary of unit costs'!U$1,InterventionCosts!$A$2:$A$3432,'Summary of unit costs'!$A48) -> 4.2834667 | V48: =SUMIFS(InterventionCosts!$K$2:$K$3432,InterventionCosts!$D$2:$D$3432,'Summary of unit costs'!V$1,InterventionCosts!$A$2:$A$3432,'Summary of unit costs'!$A48) -> 57.714516
A49: ANC testing (negative) | C49: Antenatal Care HIV testing, negative test | E49: Ingredients | F49: HTS | G49: {=IF(E49="Literature",0,INDEX(InterventionCosts!$L$1:$L$3432,MATCH(A49,IF(InterventionCosts!$F$1:$F$3432="Cost per intervention",InterventionCosts!$A$1:$A$3432),0)))} -> 62.820225 | H49: =G49/exrate -> 3.3664528 | I49: {=IF(E49="Literature",INDEX(LiteratureCost!$G$2:$G$22,MATCH('Summary of unit costs'!A49,LiteratureCost!$A$2:$A$22,0)),INDEX(InterventionCosts!$L$1:$L$3432,MATCH(A49,IF(InterventionCosts!$F$1:$F$3432="Unit",InterventionCosts!$A$1:$A$3432),0)))} -> per client tested | J49: =G49/SUM(Q49:V49) -> 1 | K49: =Q49/$G49 -> 0.58135196 | L49: =R49/$G49 -> 0 | M49: =S49/$G49 -> 0.022956604 | N49: =T49/$G49 -> 0 | O49: =U49/$G49 -> 0.072392113 | P49: =V49/$G49 -> 0.32329932 | Q49: =SUMIFS(InterventionCosts!$K$2:$K$3432,InterventionCosts!$D$2:$D$3432,'Summary of unit costs'!Q$1,InterventionCosts!$A$2:$A$3432,'Summary of unit costs'!$A49) -> 36.520661 | R49: =SUMIFS(InterventionCosts!$K$2:$K$3432,InterventionCosts!$D$2:$D$3432,'Summary of unit costs'!R$1,InterventionCosts!$A$2:$A$3432,'Summary of unit costs'!$A49) -> 0 | S49: =SUMIFS(InterventionCosts!$K$2:$K$3432,InterventionCosts!$D$2:$D$3432,'Summary of unit costs'!S$1,InterventionCosts!$A$2:$A$3432,'Summary of unit costs'!$A49) -> 1.442139 | T49: =SUMIFS(InterventionCosts!$K$2:$K$3432,InterventionCosts!$D$2:$D$3432,'Summary of unit costs'!T$1,InterventionCosts!$A$2:$A$3432,'Summary of unit costs'!$A49) -> 0 | U49: =SUMIFS(InterventionCosts!$K$2:$K$3432,InterventionCosts!$D$2:$D$3432,'Summary of unit costs'!U$1,InterventionCosts!$A$2:$A$3432,'Summary of unit costs'!$A49) -> 4.5476888 | V49: =SUMIFS(InterventionCosts!$K$2:$K$3432,InterventionCosts!$D$2:$D$3432,'Summary of unit costs'!V$1,InterventionCosts!$A$2:$A$3432,'Summary of unit costs'!$A49) -> 20.309736
A50: ANC testing (positive) | C50: Antenatal Care HIV testing, positive test | E50: Ingredients | F50: HTS | G50: {=IF(E50="Literature",0,INDEX(InterventionCosts!$L$1:$L$3432,MATCH(A50,IF(InterventionCosts!$F$1:$F$3432="Cost per intervention",InterventionCosts!$A$1:$A$3432),0)))} -> 95.530107 | H50: =G50/exrate -> 5.1193322 | I50: {=IF(E50="Literature",INDEX(LiteratureCost!$G$2:$G$22,MATCH('Summary of unit costs'!A50,LiteratureCost!$A$2:$A$22,0)),INDEX(InterventionCosts!$L$1:$L$3432,MATCH(A50,IF(InterventionCosts!$F$1:$F$3432="Unit",InterventionCosts!$A$1:$A$3432),0)))} -> per client tested | J50: =G50/SUM(Q50:V50) -> 1 | K50: =Q50/$G50 -> 0.46415777 | L50: =R50/$G50 -> 0 | M50: =S50/$G50 -> 0.015096173 | N50: =T50/$G50 -> 0.00015050742 | O50: =U50/$G50 -> 0.044838919 | P50: =V50/$G50 -> 0.47575663 | Q50: =SUMIFS(InterventionCosts!$K$2:$K$3432,InterventionCosts!$D$2:$D$3432,'Summary of unit costs'!Q$1,InterventionCosts!$A$2:$A$3432,'Summary of unit costs'!$A50) -> 44.341041 | R50: =SUMIFS(InterventionCosts!$K$2:$K$3432,InterventionCosts!$D$2:$D$3432,'Summary of unit costs'!R$1,InterventionCosts!$A$2:$A$3432,'Summary of unit costs'!$A50) -> 0 | S50: =SUMIFS(InterventionCosts!$K$2:$K$3432,InterventionCosts!$D$2:$D$3432,'Summary of unit costs'!S$1,InterventionCosts!$A$2:$A$3432,'Summary of unit costs'!$A50) -> 1.442139 | T50: =SUMIFS(InterventionCosts!$K$2:$K$3432,InterventionCosts!$D$2:$D$3432,'Summary of unit costs'!T$1,InterventionCosts!$A$2:$A$3432,'Summary of unit costs'!$A50) -> 0.01437799 | U50: =SUMIFS(InterventionCosts!$K$2:$K$3432,InterventionCosts!$D$2:$D$3432,'Summary of unit costs'!U$1,InterventionCosts!$A$2:$A$3432,'Summary of unit costs'!$A50) -> 4.2834667 | V50: =SUMIFS(InterventionCosts!$K$2:$K$3432,InterventionCosts!$D$2:$D$3432,'Summary of unit costs'!V$1,InterventionCosts!$A$2:$A$3432,'Summary of unit costs'!$A50) -> 45.449082
A51: Partner notification (negative) | C51: Partner notification, negative test | E51: Ingredients | F51: HTS | G51: {=IF(E51="Literature",0,INDEX(InterventionCosts!$L$1:$L$3432,MATCH(A51,IF(InterventionCosts!$F$1:$F$3432="Cost per intervention",InterventionCosts!$A$1:$A$3432),0)))} -> 66.395867 | H51: =G51/exrate -> 3.5580668 | I51: {=IF(E51="Literature",INDEX(LiteratureCost!$G$2:$G$22,MATCH('Summary of unit costs'!A51,LiteratureCost!$A$2:$A$22,0)),INDEX(InterventionCosts!$L$1:$L$3432,MATCH(A51,IF(InterventionCosts!$F$1:$F$3432="Unit",InterventionCosts!$A$1:$A$3432),0)))} -> per client tested | J51: =G51/SUM(Q51:V51) -> 1 | K51: =Q51/$G51 -> 0.61102984 | L51: =R51/$G51 -> 0 | M51: =S51/$G51 -> 0.021720313 | N51: =T51/$G51 -> 0 | O51: =U51/$G51 -> 0.064514057 | P51: =V51/$G51 -> 0.30273579 | Q51: =SUMIFS(InterventionCosts!$K$2:$K$3432,InterventionCosts!$D$2:$D$3432,'Summary of unit costs'!Q$1,InterventionCosts!$A$2:$A$3432,'Summary of unit costs'!$A51) -> 40.569856 | R51: =SUMIFS(InterventionCosts!$K$2:$K$3432,InterventionCosts!$D$2:$D$3432,'Summary of unit costs'!R$1,InterventionCosts!$A$2:$A$3432,'Summary of unit costs'!$A51) -> 0 | S51: =SUMIFS(InterventionCosts!$K$2:$K$3432,InterventionCosts!$D$2:$D$3432,'Summary of unit costs'!S$1,InterventionCosts!$A$2:$A$3432,'Summary of unit costs'!$A51) -> 1.442139 | T51: =SUMIFS(InterventionCosts!$K$2:$K$3432,InterventionCosts!$D$2:$D$3432,'Summary of unit costs'!T$1,InterventionCosts!$A$2:$A$3432,'Summary of unit costs'!$A51) -> 0 | U51: =SUMIFS(InterventionCosts!$K$2:$K$3432,InterventionCosts!$D$2:$D$3432,'Summary of unit costs'!U$1,InterventionCosts!$A$2:$A$3432,'Summary of unit costs'!$A51) -> 4.2834667 | V51: =SUMIFS(InterventionCosts!$K$2:$K$3432,InterventionCosts!$D$2:$D$3432,'Summary of unit costs'!V$1,InterventionCosts!$A$2:$A$3432,'Summary of unit costs'!$A51) -> 20.100405
A52: Partner notification (positive) | C52: Partner notification, positive test | E52: Ingredients | F52: HTS | G52: {=IF(E52="Literature",0,INDEX(InterventionCosts!$L$1:$L$3432,MATCH(A52,IF(InterventionCosts!$F$1:$F$3432="Cost per intervention",InterventionCosts!$A$1:$A$3432),0)))} -> 105.79479 | H52: =G52/exrate -> 5.6694029 | I52: {=IF(E52="Literature",INDEX(LiteratureCost!$G$2:$G$22,MATCH('Summary of unit costs'!A52,LiteratureCost!$A$2:$A$22,0)),INDEX(InterventionCosts!$L$1:$L$3432,MATCH(A52,IF(InterventionCosts!$F$1:$F$3432="Unit",InterventionCosts!$A$1:$A$3432),0)))} -> per client tested | J52: =G52/SUM(Q52:V52) -> 1 | K52: =Q52/$G52 -> 0.51615777 | L52: =R52/$G52 -> 0 | M52: =S52/$G52 -> 0.013631475 | N52: =T52/$G52 -> 0.0001562902 | O52: =U52/$G52 -> 0.040488447 | P52: =V52/$G52 -> 0.42956602 | Q52: =SUMIFS(InterventionCosts!$K$2:$K$3432,InterventionCosts!$D$2:$D$3432,'Summary of unit costs'!Q$1,InterventionCosts!$A$2:$A$3432,'Summary of unit costs'!$A52) -> 54.606802 | R52: =SUMIFS(InterventionCosts!$K$2:$K$3432,InterventionCosts!$D$2:$D$3432,'Summary of unit costs'!R$1,InterventionCosts!$A$2:$A$3432,'Summary of unit costs'!$A52) -> 0 | S52: =SUMIFS(InterventionCosts!$K$2:$K$3432,InterventionCosts!$D$2:$D$3432,'Summary of unit costs'!S$1,InterventionCosts!$A$2:$A$3432,'Summary of unit costs'!$A52) -> 1.442139 | T52: =SUMIFS(InterventionCosts!$K$2:$K$3432,InterventionCosts!$D$2:$D$3432,'Summary of unit costs'!T$1,InterventionCosts!$A$2:$A$3432,'Summary of unit costs'!$A52) -> 0.016534689 | U52: =SUMIFS(InterventionCosts!$K$2:$K$3432,InterventionCosts!$D$2:$D$3432,'Summary of unit costs'!U$1,InterventionCosts!$A$2:$A$3432,'Summary of unit costs'!$A52) -> 4.2834667 | V52: =SUMIFS(InterventionCosts!$K$2:$K$3432,InterventionCosts!$D$2:$D$3432,'Summary of unit costs'!V$1,InterventionCosts!$A$2:$A$3432,'Summary of unit costs'!$A52) -> 45.445847
A53: PITC (negative) | C53: Provider-initiated testing and counselling, negative test | E53: Ingredients | F53: HTS | G53: {=IF(E53="Literature",0,INDEX(InterventionCosts!$L$1:$L$3432,MATCH(A53,IF(InterventionCosts!$F$1:$F$3432="Cost per intervention",InterventionCosts!$A$1:$A$3432),0)))} -> 72.369909 | H53: =G53/exrate -> 3.8782078 | I53: {=IF(E53="Literature",INDEX(LiteratureCost!$G$2:$G$22,MATCH('Summary of unit costs'!A53,LiteratureCost!$A$2:$A$22,0)),INDEX(InterventionCosts!$L$1:$L$3432,MATCH(A53,IF(InterventionCosts!$F$1:$F$3432="Unit",InterventionCosts!$A$1:$A$3432),0)))} -> per client tested | J53: =G53/SUM(Q53:V53) -> 1 | K53: =Q53/$G53 -> 0.46829132 | L53: =R53/$G53 -> 0 | M53: =S53/$G53 -> 0.019927329 | N53: =T53/$G53 -> 0 | O53: =U53/$G53 -> 0.059188506 | P53: =V53/$G53 -> 0.45259284 | Q53: =SUMIFS(InterventionCosts!$K$2:$K$3432,InterventionCosts!$D$2:$D$3432,'Summary of unit costs'!Q$1,InterventionCosts!$A$2:$A$3432,'Summary of unit costs'!$A53) -> 33.8902 | R53: =SUMIFS(InterventionCosts!$K$2:$K$3432,InterventionCosts!$D$2:$D$3432,'Summary of unit costs'!R$1,InterventionCosts!$A$2:$A$3432,'Summary of unit costs'!$A53) -> 0 | S53: =SUMIFS(InterventionCosts!$K$2:$K$3432,InterventionCosts!$D$2:$D$3432,'Summary of unit costs'!S$1,InterventionCosts!$A$2:$A$3432,'Summary of unit costs'!$A53) -> 1.442139 | T53: =SUMIFS(InterventionCosts!$K$2:$K$3432,InterventionCosts!$D$2:$D$3432,'Summary of unit costs'!T$1,InterventionCosts!$A$2:$A$3432,'Summary of unit costs'!$A53) -> 0 | U53: =SUMIFS(InterventionCosts!$K$2:$K$3432,InterventionCosts!$D$2:$D$3432,'Summary of unit costs'!U$1,InterventionCosts!$A$2:$A$3432,'Summary of unit costs'!$A53) -> 4.2834667 | V53: =SUMIFS(InterventionCosts!$K$2:$K$3432,InterventionCosts!$D$2:$D$3432,'Summary of unit costs'!V$1,InterventionCosts!$A$2:$A$3432,'Summary of unit costs'!$A53) -> 32.754103
A54: PITC (positive) | C54: Provider-initiated testing and counselling, positive test | E54: Ingredients | F54: HTS | G54: {=IF(E54="Literature",0,INDEX(InterventionCosts!$L$1:$L$3432,MATCH(A54,IF(InterventionCosts!$F$1:$F$3432="Cost per intervention",InterventionCosts!$A$1:$A$3432),0)))} -> 105.44739 | H54: =G54/exrate -> 5.6507864 | I54: {=IF(E54="Literature",INDEX(LiteratureCost!$G$2:$G$22,MATCH('Summary of unit costs'!A54,LiteratureCost!$A$2:$A$22,0)),INDEX(InterventionCosts!$L$1:$L$3432,MATCH(A54,IF(InterventionCosts!$F$1:$F$3432="Unit",InterventionCosts!$A$1:$A$3432),0)))} -> per client tested | J54: =G54/SUM(Q54:V54) -> 1 | K54: =Q54/$G54 -> 0.39823548 | L54: =R54/$G54 -> 0 | M54: =S54/$G54 -> 0.013676384 | N54: =T54/$G54 -> 0.00013635226 | O54: =U54/$G54 -> 0.040621837 | P54: =V54/$G54 -> 0.54732995 | Q54: =SUMIFS(InterventionCosts!$K$2:$K$3432,InterventionCosts!$D$2:$D$3432,'Summary of unit costs'!Q$1,InterventionCosts!$A$2:$A$3432,'Summary of unit costs'!$A54) -> 41.992892 | R54: =SUMIFS(InterventionCosts!$K$2:$K$3432,InterventionCosts!$D$2:$D$3432,'Summary of unit costs'!R$1,InterventionCosts!$A$2:$A$3432,'Summary of unit costs'!$A54) -> 0 | S54: =SUMIFS(InterventionCosts!$K$2:$K$3432,InterventionCosts!$D$2:$D$3432,'Summary of unit costs'!S$1,InterventionCosts!$A$2:$A$3432,'Summary of unit costs'!$A54) -> 1.442139 | T54: =SUMIFS(InterventionCosts!$K$2:$K$3432,InterventionCosts!$D$2:$D$3432,'Summary of unit costs'!T$1,InterventionCosts!$A$2:$A$3432,'Summary of unit costs'!$A54) -> 0.01437799 | U54: =SUMIFS(InterventionCosts!$K$2:$K$3432,InterventionCosts!$D$2:$D$3432,'Summary of unit costs'!U$1,InterventionCosts!$A$2:$A$3432,'Summary of unit costs'!$A54) -> 4.2834667 | V54: =SUMIFS(InterventionCosts!$K$2:$K$3432,InterventionCosts!$D$2:$D$3432,'Summary of unit costs'!V$1,InterventionCosts!$A$2:$A$3432,'Summary of unit costs'!$A54) -> 57.714516
... A58: Home based testing (positive) | C58: Home-based HIV testing, positive test | E58: Ingredients | F58: HTS | G58: {=IF(E58="Literature",0,INDEX(InterventionCosts!$L$1:$L$3432,MATCH(A58,IF(InterventionCosts!$F$1:$F$3432="Cost per intervention",InterventionCosts!$A$1:$A$3432),0)))} -> 110.79281 | H58: =G58/exrate -> 5.9372403 | I58: {=IF(E58="Literature",INDEX(LiteratureCost!$G$2:$G$22,MATCH('Summary of unit costs'!A58,LiteratureCost!$A$2:$A$22,0)),INDEX(InterventionCosts!$L$1:$L$3432,MATCH(A58,IF(InterventionCosts!$F$1:$F$3432="Unit",InterventionCosts!$A$1:$A$3432),0)))} -> per client tested | J58: =G58/SUM(Q58:V58) -> 1 | K58: =Q58/$G58 -> 0.2668306 | L58: =R58/$G58 -> 0 | M58: =S58/$G58 -> 0.042804216 | N58: =T58/$G58 -> 0 | O58: =U58/$G58 -> 0.008183868 | P58: =V58/$G58 -> 0.68218132 | Q58: =SUMIFS(InterventionCosts!$K$2:$K$3432,InterventionCosts!$D$2:$D$3432,'Summary of unit costs'!Q$1,InterventionCosts!$A$2:$A$3432,'Summary of unit costs'!$A58) -> 29.562912 | R58: =SUMIFS(InterventionCosts!$K$2:$K$3432,InterventionCosts!$D$2:$D$3432,'Summary of unit costs'!R$1,InterventionCosts!$A$2:$A$3432,'Summary of unit costs'!$A58) -> 0 | S58: =SUMIFS(InterventionCosts!$K$2:$K$3432,InterventionCosts!$D$2:$D$3432,'Summary of unit costs'!S$1,InterventionCosts!$A$2:$A$3432,'Summary of unit costs'!$A58) -> 4.7423994 | T58: =SUMIFS(InterventionCosts!$K$2:$K$3432,InterventionCosts!$D$2:$D$3432,'Summary of unit costs'!T$1,InterventionCosts!$A$2:$A$3432,'Summary of unit costs'!$A58) -> 0 | U58: =SUMIFS(InterventionCosts!$K$2:$K$3432,InterventionCosts!$D$2:$D$3432,'Summary of unit costs'!U$1,InterventionCosts!$A$2:$A$3432,'Summary of unit costs'!$A58) -> 0.90671374 | V58: =SUMIFS(InterventionCosts!$K$2:$K$3432,InterventionCosts!$D$2:$D$3432,'Summary of unit costs'!V$1,InterventionCosts!$A$2:$A$3432,'Summary of unit costs'!$A58) -> 75.580786
A59: HIVST fixed point | C59: HIV self-testing, fixed point modality | E59: Literature | F59: HTS | G59: {=IF(E59="Literature",INDEX(LiteratureCost!$I$2:$I$42,MATCH('Summary of unit costs'!A59,LiteratureCost!$A$2:$A$42,0)),INDEX(InterventionCosts!$L$1:$L$3432,MATCH(A59,IF(InterventionCosts!$F$1:$F$3432="Cost per intervention",InterventionCosts!$A$1:$A$3432),0)))} -> 145.34677 | H59: =G59/exrate -> 7.7889415 | I59: {=IF(E59="Literature",INDEX(LiteratureCost!$G$2:$G$22,MATCH('Summary of unit costs'!A59,LiteratureCost!$A$2:$A$22,0)),INDEX(InterventionCosts!$L$1:$L$3432,MATCH(A59,IF(InterventionCosts!$F$1:$F$3432="Unit",InterventionCosts!$A$1:$A$3432),0)))} -> per test kit distributed | K59: Literature costs- do not have this breakdown
A60: HIVST taxi ranks | C60: HIV self-testing, taxi ranks/transport hubs modality | E60: Literature | F60: HTS | G60: {=IF(E60="Literature",INDEX(LiteratureCost!$I$2:$I$42,MATCH('Summary of unit costs'!A60,LiteratureCost!$A$2:$A$42,0)),INDEX(InterventionCosts!$L$1:$L$3432,MATCH(A60,IF(InterventionCosts!$F$1:$F$3432="Cost per intervention",InterventionCosts!$A$1:$A$3432),0)))} -> 130.4824 | H60: =G60/exrate -> 6.9923791 | I60: {=IF(E60="Literature",INDEX(LiteratureCost!$G$2:$G$22,MATCH('Summary of unit costs'!A60,LiteratureCost!$A$2:$A$22,0)),INDEX(InterventionCosts!$L$1:$L$3432,MATCH(A60,IF(InterventionCosts!$F$1:$F$3432="Unit",InterventionCosts!$A$1:$A$3432),0)))} -> per test kit distributed | K60: Literature costs- do not have this breakdown
A61: HIVST partners of ANC clients | C61: HIV self-testing, secondary distribution to partners of ANC clients | E61: Literature | F61: HTS | G61: {=IF(E61="Literature",INDEX(LiteratureCost!$I$2:$I$42,MATCH('Summary of unit costs'!A61,LiteratureCost!$A$2:$A$42,0)),INDEX(InterventionCosts!$L$1:$L$3432,MATCH(A61,IF(InterventionCosts!$F$1:$F$3432="Cost per intervention",InterventionCosts!$A$1:$A$3432),0)))} -> 281.82216 | H61: =G61/exrate -> 15.102477 | I61: {=IF(E61="Literature",INDEX(LiteratureCost!$G$2:$G$22,MATCH('Summary of unit costs'!A61,LiteratureCost!$A$2:$A$22,0)),INDEX(InterventionCosts!$L$1:$L$3432,MATCH(A61,IF(InterventionCosts!$F$1:$F$3432="Unit",InterventionCosts!$A$1:$A$3432),0)))} -> per test kit distributed | K61: Literature costs- do not have this breakdown
A62: HIVST partners of index cases | C62: HIV self-testing, secondary distribution to partners of index cases | E62: Literature | F62: HTS | G62: {=IF(E62="Literature",INDEX(LiteratureCost!$I$2:$I$42,MATCH('Summary of unit costs'!A62,LiteratureCost!$A$2:$A$42,0)),INDEX(InterventionCosts!$L$1:$L$3432,MATCH(A62,IF(InterventionCosts!$F$1:$F$3432="Cost per intervention",InterventionCosts!$A$1:$A$3432),0)))} -> 268.3373 | H62: =G62/exrate -> 14.379841 | I62: {=IF(E62="Literature",INDEX(LiteratureCost!$G$2:$G$22,MATCH('Summary of unit costs'!A62,LiteratureCost!$A$2:$A$22,0)),INDEX(InterventionCosts!$L$1:$L$3432,MATCH(A62,IF(InterventionCosts!$F$1:$F$3432="Unit",InterventionCosts!$A$1:$A$3432),0)))} -> per test kit distributed | K62: Literature costs- do not have this breakdown
A63: HIVST workplace distribution | C63: HIV self-testing, workplace distribution | E63: Literature | F63: HTS | G63: {=IF(E63="Literature",INDEX(LiteratureCost!$I$2:$I$42,MATCH('Summary of unit costs'!A63,LiteratureCost!$A$2:$A$42,0)),INDEX(InterventionCosts!$L$1:$L$3432,MATCH(A63,IF(InterventionCosts!$F$1:$F$3432="Cost per intervention",InterventionCosts!$A$1:$A$3432),0)))} -> 139.9043 | H63: =G63/exrate -> 7.4972868 | I63: {=IF(E63="Literature",INDEX(LiteratureCost!$G$2:$G$22,MATCH('Summary of unit costs'!A63,LiteratureCost!$A$2:$A$22,0)),INDEX(InterventionCosts!$L$1:$L$3432,MATCH(A63,IF(InterventionCosts!$F$1:$F$3432="Unit",InterventionCosts!$A$1:$A$3432),0)))} -> per test kit distributed | K63: Literature costs- do not have this breakdown
A64: HIVST general PHC | C64: HIV self-testing, general primary healthcare clinics | E64: Ingredients | F64: HTS | G64: {=IF(E64="Literature",INDEX(LiteratureCost!$I$2:$I$42,MATCH('Summary of unit costs'!A64,LiteratureCost!$A$2:$A$42,0)),INDEX(InterventionCosts!$L$1:$L$3432,MATCH(A64,IF(InterventionCosts!$F$1:$F$3432="Cost per intervention",InterventionCosts!$A$1:$A$3432),0)))} -> 141.12936 | H64: =G64/exrate -> 7.5629361 | I64: {=IF(E64="Literature",INDEX(LiteratureCost!$G$2:$G$22,MATCH('Summary of unit costs'!A64,LiteratureCost!$A$2:$A$22,0)),INDEX(InterventionCosts!$L$1:$L$3432,MATCH(A64,IF(InterventionCosts!$F$1:$F$3432="Unit",InterventionCosts!$A$1:$A$3432),0)))} -> per client tested | K64: Literature costs- do not have this breakdown
A65: Post-Exposure Prophylaxis (PEP) | C65: Survivors of sexual assault (estimated from rate of crimes in general population) | E65: Ingredients | F65: PREV | G65: {=IF(E65="Literature",INDEX(LiteratureCost!$I$2:$I$10,MATCH('Summary of unit costs'!A65,LiteratureCost!$A$2:$A$10,0)),INDEX(InterventionCosts!$L$1:$L$3432,MATCH(A65,IF(InterventionCosts!$F$1:$F$3432="Cost per intervention",InterventionCosts!$A$1:$A$3432),0)))} -> 1290.5294 | H65: =G65/exrate -> 69.157766 | I65: {=IF(E65="Literature",INDEX(LiteratureCost!$G$2:$G$22,MATCH('Summary of unit costs'!A65,LiteratureCost!$A$2:$A$22,0)),INDEX(InterventionCosts!$L$1:$L$3432,MATCH(A65,IF(InterventionCosts!$F$1:$F$3432="Unit",InterventionCosts!$A$1:$A$3432),0)))} -> per person | J65: =G65/SUM(Q65:V65) -> 1 | K65: =Q65/$G65 -> 0.42541611 | L65: =R65/$G65 -> 0.25511933 | M65: =S65/$G65 -> 4.6492548e-05 | N65: =T65/$G65 -> 0 | O65: =U65/$G65 -> 0.015670579 | P65: =V65/$G65 -> 0.30374749 | Q65: =SUMIFS(InterventionCosts!$K$2:$K$3432,InterventionCosts!$D$2:$D$3432,'Summary of unit costs'!Q$1,InterventionCosts!$A$2:$A$3432,'Summary of unit costs'!$A65) -> 549.012 | R65: =SUMIFS(InterventionCosts!$K$2:$K$3432,InterventionCosts!$D$2:$D$3432,'Summary of unit costs'!R$1,InterventionCosts!$A$2:$A$3432,'Summary of unit costs'!$A65) -> 329.239 | S65: =SUMIFS(InterventionCosts!$K$2:$K$3432,InterventionCosts!$D$2:$D$3432,'Summary of unit costs'!S$1,InterventionCosts!$A$2:$A$3432,'Summary of unit costs'!$A65) -> 0.06 | T65: =SUMIFS(InterventionCosts!$K$2:$K$3432,InterventionCosts!$D$2:$D$3432,'Summary of unit costs'!T$1,InterventionCosts!$A$2:$A$3432,'Summary of unit costs'!$A65) -> 0 | U65: =SUMIFS(InterventionCosts!$K$2:$K$3432,InterventionCosts!$D$2:$D$3432,'Summary of unit costs'!U$1,InterventionCosts!$A$2:$A$3432,'Summary of unit costs'!$A65) -> 20.223343 | V65: =SUMIFS(InterventionCosts!$K$2:$K$3432,InterventionCosts!$D$2:$D$3432,'Summary of unit costs'!V$1,InterventionCosts!$A$2:$A$3432,'Summary of unit costs'!$A65) -> 391.99507
A66: Combination prevention package service provision through outreach to FSW | C66: All sex workers | E66: Ingredients | F66: KP | G66: {=IF(E66="Literature",0,INDEX(InterventionCosts!$L$1:$L$3432,MATCH(A66,IF(InterventionCosts!$F$1:$F$3432="Cost per intervention",InterventionCosts!$A$1:$A$3432),0)))} -> 1118.1469 | H66: =G66/exrate -> 59.920015 | I66: {=IF(E66="Literature",INDEX(LiteratureCost!$G$2:$G$22,MATCH('Summary of unit costs'!A66,LiteratureCost!$A$2:$A$22,0)),INDEX(InterventionCosts!$L$1:$L$3432,MATCH(A66,IF(InterventionCosts!$F$1:$F$3432="Unit",InterventionCosts!$A$1:$A$3432),0)))} -> per client tested | J66: =G66/SUM(Q66:V66) -> 1 | K66: =Q66/$G66 -> 0.12246231 | L66: =R66/$G66 -> 0 | M66: =S66/$G66 -> 0.00042928169 | N66: =T66/$G66 -> 0 | O66: =U66/$G66 -> 0.30235191 | P66: =V66/$G66 -> 0.57475649 | Q66: =SUMIFS(InterventionCosts!$K$2:$K$3432,InterventionCosts!$D$2:$D$3432,'Summary of unit costs'!Q$1,InterventionCosts!$A$2:$A$3432,'Summary of unit costs'!$A66) -> 136.93086 | R66: =SUMIFS(InterventionCosts!$K$2:$K$3432,InterventionCosts!$D$2:$D$3432,'Summary of unit costs'!R$1,InterventionCosts!$A$2:$A$3432,'Summary of unit costs'!$A66) -> 0 | S66: =SUMIFS(InterventionCosts!$K$2:$K$3432,InterventionCosts!$D$2:$D$3432,'Summary of unit costs'!S$1,InterventionCosts!$A$2:$A$3432,'Summary of unit costs'!$A66) -> 0.48 | T66: =SUMIFS(InterventionCosts!$K$2:$K$3432,InterventionCosts!$D$2:$D$3432,'Summary of unit costs'!T$1,InterventionCosts!$A$2:$A$3432,'Summary of unit costs'!$A66) -> 0 | U66: =SUMIFS(InterventionCosts!$K$2:$K$3432,InterventionCosts!$D$2:$D$3432,'Summary of unit costs'!U$1,InterventionCosts!$A$2:$A$3432,'Summary of unit costs'!$A66) -> 338.07385 | V66: =SUMIFS(InterventionCosts!$K$2:$K$3432,InterventionCosts!$D$2:$D$3432,'Summary of unit costs'!V$1,InterventionCosts!$A$2:$A$3432,'Summary of unit costs'!$A66) -> 642.6622
A67: U=U messaging (per HIV test) | C67: All males over 15 years testing because of U=U messaging intervention | E67: Literature | F67: ENB | G67: {=IF(E67="Literature",INDEX(LiteratureCost!$I$2:$I$42,MATCH('Summary of unit costs'!A67,LiteratureCost!$A$2:$A$42,0)),INDEX(InterventionCosts!$L$1:$L$3432,MATCH(A67,IF(InterventionCosts!$F$1:$F$3432="Cost per intervention",InterventionCosts!$A$1:$A$3432),0)))} -> 189.29585 | H67: =G67/exrate -> 10.144114 | I67: {=IF(E67="Literature",INDEX(LiteratureCost!$G$2:$G$22,MATCH('Summary of unit costs'!A67,LiteratureCost!$A$2:$A$22,0)),INDEX(InterventionCosts!$L$1:$L$3432,MATCH(A67,IF(InterventionCosts!$F$1:$F$3432="Unit",InterventionCosts!$A$1:$A$3432),0)))} -> per person tested | K67: Literature costs- do not have this breakdown
A68: U=U messaging (per person reached) | C68: All males over 15 years reached with U=U messaging intervention | E68: Literature | F68: ENB | G68: {=IF(E68="Literature",INDEX(LiteratureCost!$I$2:$I$42,MATCH('Summary of unit costs'!A68,LiteratureCost!$A$2:$A$42,0)),INDEX(InterventionCosts!$L$1:$L$3432,MATCH(A68,IF(InterventionCosts!$F$1:$F$3432="Cost per intervention",InterventionCosts!$A$1:$A$3432),0)))} -> 42.065744 | H68: =G68/exrate -> 2.2542476 | I68: per person reached
A69: Palliative care | C69: All AIDS deaths | E69: Literature | F69: OTH | G69: {=IF(E69="Literature",INDEX(LiteratureCost!$I$2:$I$42,MATCH('Summary of unit costs'!A69,LiteratureCost!$A$2:$A$42,0)),INDEX(InterventionCosts!$L$1:$L$3432,MATCH(A69,IF(InterventionCosts!$F$1:$F$3432="Cost per intervention",InterventionCosts!$A$1:$A$3432),0)))} -> 1274.5184 | H69: =G69/exrate -> 68.299757 | I69: {=IF(E69="Literature",INDEX(LiteratureCost!$G$2:$G$22,MATCH('Summary of unit costs'!A69,LiteratureCost!$A$2:$A$22,0)),INDEX(InterventionCosts!$L$1:$L$3432,MATCH(A69,IF(InterventionCosts!$F$1:$F$3432="Unit",InterventionCosts!$A$1:$A$3432),0)))} -> per patient | K69: Full service cost- do not have this breakdown
A70: Inpatient care (ART; <200 cells/microl) | C70: Number of adults on ART at CD4<200 | E70: Ingredients | F70: OTH | G70: {=IF(E70="Literature",INDEX(LiteratureCost!$I$2:$I$42,MATCH('Summary of unit costs'!A70,LiteratureCost!$A$2:$A$42,0)),INDEX(InterventionCosts!$L$1:$L$3432,MATCH(A70,IF(InterventionCosts!$F$1:$F$3432="Cost per intervention",InterventionCosts!$A$1:$A$3432),0)))} -> 8028.4905 | H70: =G70/exrate -> 430.2362 | I70: {=IF(E70="Literature",INDEX(LiteratureCost!$G$2:$G$22,MATCH('Summary of unit costs'!A70,LiteratureCost!$A$2:$A$22,0)),INDEX(InterventionCosts!$L$1:$L$3432,MATCH(A70,IF(InterventionCosts!$F$1:$F$3432="Unit",InterventionCosts!$A$1:$A$3432),0)))} -> per patient year in cohort | K70: Full service cost- do not have this breakdown
A71: Inpatient care (ART; 200-349 cells/microl) | C71: Number of adults on ART at CD4 200-349 | E71: Ingredients | F71: OTH | G71: {=IF(E71="Literature",INDEX(LiteratureCost!$I$2:$I$42,MATCH('Summary of unit costs'!A71,LiteratureCost!$A$2:$A$42,0)),INDEX(InterventionCosts!$L$1:$L$3432,MATCH(A71,IF(InterventionCosts!$F$1:$F$3432="Cost per intervention",InterventionCosts!$A$1:$A$3432),0)))} -> 2534.5934 | H71: =G71/exrate -> 135.82551 | I71: {=IF(E71="Literature",INDEX(LiteratureCost!$G$2:$G$22,MATCH('Summary of unit costs'!A71,LiteratureCost!$A$2:$A$22,0)),INDEX(InterventionCosts!$L$1:$L$3432,MATCH(A71,IF(InterventionCosts!$F$1:$F$3432="Unit",InterventionCosts!$A$1:$A$3432),0)))} -> per patient year in cohort | K71: Full service cost- do not have this breakdown
A72: Inpatient care (ART; 350-500 cells/microl) | C72: Number of adults on ART at CD4 350-499 | E72: Ingredients | F72: OTH | G72: {=IF(E72="Literature",INDEX(LiteratureCost!$I$2:$I$42,MATCH('Summary of unit costs'!A72,LiteratureCost!$A$2:$A$42,0)),INDEX(InterventionCosts!$L$1:$L$3432,MATCH(A72,IF(InterventionCosts!$F$1:$F$3432="Cost per intervention",InterventionCosts!$A$1:$A$3432),0)))} -> 747.33795 | H72: =G72/exrate -> 40.048853 | I72: {=IF(E72="Literature",INDEX(LiteratureCost!$G$2:$G$22,MATCH('Summary of unit costs'!A72,LiteratureCost!$A$2:$A$22,0)),INDEX(InterventionCosts!$L$1:$L$3432,MATCH(A72,IF(InterventionCosts!$F$1:$F$3432="Unit",InterventionCosts!$A$1:$A$3432),0)))} -> per patient year in cohort | K72: Full service cost- do not have this breakdown
A73: Inpatient care (ART; >500 cells/microl) | C73: Number of adults on ART at CD4>=500 | E73: Ingredients | F73: OTH | G73: {=IF(E73="Literature",INDEX(LiteratureCost!$I$2:$I$42,MATCH('Summary of unit costs'!A73,LiteratureCost!$A$2:$A$42,0)),INDEX(InterventionCosts!$L$1:$L$3432,MATCH(A73,IF(InterventionCosts!$F$1:$F$3432="Cost per intervention",InterventionCosts!$A$1:$A$3432),0)))} -> 747.33795 | H73: =G73/exrate -> 40.048853 | I73: {=IF(E73="Literature",INDEX(LiteratureCost!$G$2:$G$22,MATCH('Summary of unit costs'!A73,LiteratureCost!$A$2:$A$22,0)),INDEX(InterventionCosts!$L$1:$L$3432,MATCH(A73,IF(InterventionCosts!$F$1:$F$3432="Unit",InterventionCosts!$A$1:$A$3432),0)))} -> per patient year in cohort | K73: Full service cost- do not have this breakdown
A74: Inpatient care (pre-ART; <200 cells/microl) | C74: ART naïve and defaulters (CD4 <200) | E74: Ingredients | F74: OTH | G74: {=IF(E74="Literature",INDEX(LiteratureCost!$I$2:$I$42,MATCH('Summary of unit costs'!A74,LiteratureCost!$A$2:$A$42,0)),INDEX(InterventionCosts!$L$1:$L$3432,MATCH(A74,IF(InterventionCosts!$F$1:$F$3432="Cost per intervention",InterventionCosts!$A$1:$A$3432),0)))} -> 3125.1665 | H74: =G74/exrate -> 167.47354 | I74: {=IF(E74="Literature",INDEX(LiteratureCost!$G$2:$G$22,MATCH('Summary of unit costs'!A74,LiteratureCost!$A$2:$A$22,0)),INDEX(InterventionCosts!$L$1:$L$3432,MATCH(A74,IF(InterventionCosts!$F$1:$F$3432="Unit",InterventionCosts!$A$1:$A$3432),0)))} -> per patient year in cohort | K74: Full service cost- do not have this breakdown
A75: Inpatient care (pre-ART; 200-349 cells/microl) | C75: ART naïve and defaulters (CD4 200-349) | E75: Ingredients | F75: OTH | G75: {=IF(E75="Literature",INDEX(LiteratureCost!$I$2:$I$42,MATCH('Summary of unit costs'!A75,LiteratureCost!$A$2:$A$42,0)),INDEX(InterventionCosts!$L$1:$L$3432,MATCH(A75,IF(InterventionCosts!$F$1:$F$3432="Cost per intervention",InterventionCosts!$A$1:$A$3432),0)))} -> 1676.014 | H75: =G75/exrate -> 89.815374 | I75: {=IF(E75="Literature",INDEX(LiteratureCost!$G$2:$G$22,MATCH('Summary of unit costs'!A75,LiteratureCost!$A$2:$A$22,0)),INDEX(InterventionCosts!$L$1:$L$3432,MATCH(A75,IF(InterventionCosts!$F$1:$F$3432="Unit",InterventionCosts!$A$1:$A$3432),0)))} -> per patient year in cohort | K75: Full service cost- do not have this breakdown
A76: Inpatient care (pre-ART; 350-500 cells/microl) | C76: ART naïve and defaulters (CD4 350-499) | E76: Ingredients | F76: OTH | G76: {=IF(E76="Literature",INDEX(LiteratureCost!$I$2:$I$42,MATCH('Summary of unit costs'!A76,LiteratureCost!$A$2:$A$42,0)),INDEX(InterventionCosts!$L$1:$L$3432,MATCH(A76,IF(InterventionCosts!$F$1:$F$3432="Cost per intervention",InterventionCosts!$A$1:$A$3432),0)))} -> 935.60932 | H76: =G76/exrate -> 50.138067 | I76: {=IF(E76="Literature",INDEX(LiteratureCost!$G$2:$G$22,MATCH('Summary of unit costs'!A76,LiteratureCost!$A$2:$A$22,0)),INDEX(InterventionCosts!$L$1:$L$3432,MATCH(A76,IF(InterventionCosts!$F$1:$F$3432="Unit",InterventionCosts!$A$1:$A$3432),0)))} -> per patient year in cohort | K76: Full service cost- do not have this breakdown
A77: Inpatient care (pre-ART; >500 cells/microl) | C77: ART naïve and defaulters (CD4 >=500) | E77: Ingredients | F77: OTH | G77: {=IF(E77="Literature",INDEX(LiteratureCost!$I$2:$I$42,MATCH('Summary of unit costs'!A77,LiteratureCost!$A$2:$A$42,0)),INDEX(InterventionCosts!$L$1:$L$3432,MATCH(A77,IF(InterventionCosts!$F$1:$F$3432="Cost per intervention",InterventionCosts!$A$1:$A$3432),0)))} -> 935.60932 | H77: =G77/exrate -> 50.138067 | I77: {=IF(E77="Literature",INDEX(LiteratureCost!$G$2:$G$22,MATCH('Summary of unit costs'!A77,LiteratureCost!$A$2:$A$22,0)),INDEX(InterventionCosts!$L$1:$L$3432,MATCH(A77,IF(InterventionCosts!$F$1:$F$3432="Unit",InterventionCosts!$A$1:$A$3432),0)))} -> per patient year in cohort | K77: Full service cost- do not have this breakdown
A78: Inpatient care per event (ART; <200 cells/microl) | C78: Number of inpatients on ART at CD4<200 | E78: Ingredients | F78: OTH | G78: {=IF(E78="Literature",INDEX(LiteratureCost!$I$2:$I$42,MATCH('Summary of unit costs'!A78,LiteratureCost!$A$2:$A$42,0)),INDEX(InterventionCosts!$L$1:$L$3432,MATCH(A78,IF(InterventionCosts!$F$1:$F$3432="Cost per intervention",InterventionCosts!$A$1:$A$3432),0)))} -> 52992.268 | H78: =G78/exrate -> 2839.7856 | I78: {=IF(E78="Literature",INDEX(LiteratureCost!$G$2:$G$22,MATCH('Summary of unit costs'!A78,LiteratureCost!$A$2:$A$22,0)),INDEX(InterventionCosts!$L$1:$L$3432,MATCH(A78,IF(InterventionCosts!$F$1:$F$3432="Unit",InterventionCosts!$A$1:$A$3432),0)))} -> per patient admitted | K78: Full service cost- do not have this breakdown
A79: Inpatient care per event (ART; 200-349 cells/microl) | C79: Number of inpatients on ART at CD4 200-349 | E79: Ingredients | F79: OTH | G79: {=IF(E79="Literature",INDEX(LiteratureCost!$I$2:$I$42,MATCH('Summary of unit costs'!A79,LiteratureCost!$A$2:$A$42,0)),INDEX(InterventionCosts!$L$1:$L$3432,MATCH(A79,IF(InterventionCosts!$F$1:$F$3432="Cost per intervention",InterventionCosts!$A$1:$A$3432),0)))} -> 37609.451 | H79: =G79/exrate -> 2015.4408 | I79: {=IF(E79="Literature",INDEX(LiteratureCost!$G$2:$G$22,MATCH('Summary of unit costs'!A79,LiteratureCost!$A$2:$A$22,0)),INDEX(InterventionCosts!$L$1:$L$3432,MATCH(A79,IF(InterventionCosts!$F$1:$F$3432="Unit",InterventionCosts!$A$1:$A$3432),0)))} -> per patient admitted | K79: Full service cost- do not have this breakdown
A80: Inpatient care per event (ART; 350-500 cells/microl) | C80: Number of inpatients on ART at CD4 350-499 | E80: Ingredients | F80: OTH | G80: {=IF(E80="Literature",INDEX(LiteratureCost!$I$2:$I$42,MATCH('Summary of unit costs'!A80,LiteratureCost!$A$2:$A$42,0)),INDEX(InterventionCosts!$L$1:$L$3432,MATCH(A80,IF(InterventionCosts!$F$1:$F$3432="Cost per intervention",InterventionCosts!$A$1:$A$3432),0)))} -> 27903.786 | H80: =G80/exrate -> 1495.327 | I80: {=IF(E80="Literature",INDEX(LiteratureCost!$G$2:$G$22,MATCH('Summary of unit costs'!A80,LiteratureCost!$A$2:$A$22,0)),INDEX(InterventionCosts!$L$1:$L$3432,MATCH(A80,IF(InterventionCosts!$F$1:$F$3432="Unit",InterventionCosts!$A$1:$A$3432),0)))} -> per patient admitted | K80: Full service cost- do not have this breakdown
... A88: Supply chain management reform 3: Prov'l Control Tower | C88: Costs fixed; from Pharmaceutical Services Unit | E88: Literature | F88: ENB | G88: {=IF(E88="Literature",INDEX(LiteratureCost!$I$2:$I$42,MATCH('Summary of unit costs'!A88,LiteratureCost!$A$2:$A$42,0)),INDEX(InterventionCosts!$L$1:$L$3432,MATCH(A88,IF(InterventionCosts!$F$1:$F$3432="Cost per intervention",InterventionCosts!$A$1:$A$3432),0)))} -> 4483790.1 | H88: =G88/exrate -> 240280.39 | I88: {=IF(E88="Literature",INDEX(LiteratureCost!$G$2:$G$22,MATCH('Summary of unit costs'!A88,LiteratureCost!$A$2:$A$22,0)),INDEX(InterventionCosts!$L$1:$L$3432,MATCH(A88,IF(InterventionCosts!$F$1:$F$3432="Unit",InterventionCosts!$A$1:$A$3432),0)))} -> per programme | K88: Literature costs- do not have this breakdown
A89: Pharmacovigilance | C89: Costs fixed; NDoH 5-year pharmacovigilance plan | E89: Literature | F89: ENB | G89: =LiteratureCost!I10 -> 68700555 | H89: =G89/exrate -> 3681572 | I89: {=IF(E89="Literature",INDEX(LiteratureCost!$G$2:$G$22,MATCH('Summary of unit costs'!A89,LiteratureCost!$A$2:$A$22,0)),INDEX(InterventionCosts!$L$1:$L$3432,MATCH(A89,IF(InterventionCosts!$F$1:$F$3432="Unit",InterventionCosts!$A$1:$A$3432),0)))} -> per programme | K89: Literature costs- do not have this breakdown
A90: Retention Intervention | C90: Based on the staff contingent of the PEPFAR surge, Siyenza programme scaled to all PHCs in South Africa | E90: Ingredients | F90: ENB | G90: {=IF(E90="Literature",INDEX(LiteratureCost!$I$2:$I$42,MATCH('Summary of unit costs'!A90,LiteratureCost!$A$2:$A$42,0)),INDEX(InterventionCosts!$L$1:$L$3432,MATCH(A90,IF(InterventionCosts!$F$1:$F$3432="Cost per intervention",InterventionCosts!$A$1:$A$3432),0)))} -> 1.9314161e+09 | H90: =G90/exrate -> 1.0350204e+08 | I90: {=IF(E90="Literature",INDEX(LiteratureCost!$G$2:$G$22,MATCH('Summary of unit costs'!A90,LiteratureCost!$A$2:$A$22,0)),INDEX(InterventionCosts!$L$1:$L$3432,MATCH(A90,IF(InterventionCosts!$F$1:$F$3432="Unit",InterventionCosts!$A$1:$A$3432),0)))} -> per year | J90: =G90/SUM(Q90:V90) -> 1 | K90: =Q90/$G90 -> 0 | L90: =R90/$G90 -> 0 | M90: =S90/$G90 -> 0 | N90: =T90/$G90 -> 0 | O90: =U90/$G90 -> 0 | P90: =V90/$G90 -> 1 | Q90: =SUMIFS(InterventionCosts!$K$2:$K$3432,InterventionCosts!$D$2:$D$3432,'Summary of unit costs'!Q$1,InterventionCosts!$A$2:$A$3432,'Summary of unit costs'!$A90) -> 0 | R90: =SUMIFS(InterventionCosts!$K$2:$K$3432,InterventionCosts!$D$2:$D$3432,'Summary of unit costs'!R$1,InterventionCosts!$A$2:$A$3432,'Summary of unit costs'!$A90) -> 0 | S90: =SUMIFS(InterventionCosts!$K$2:$K$3432,InterventionCosts!$D$2:$D$3432,'Summary of unit costs'!S$1,InterventionCosts!$A$2:$A$3432,'Summary of unit costs'!$A90) -> 0 | T90: =SUMIFS(InterventionCosts!$K$2:$K$3432,InterventionCosts!$D$2:$D$3432,'Summary of unit costs'!T$1,InterventionCosts!$A$2:$A$3432,'Summary of unit costs'!$A90) -> 0 | U90: =SUMIFS(InterventionCosts!$K$2:$K$3432,InterventionCosts!$D$2:$D$3432,'Summary of unit costs'!U$1,InterventionCosts!$A$2:$A$3432,'Summary of unit costs'!$A90) -> 0 | V90: =SUMIFS(InterventionCosts!$K$2:$K$3432,InterventionCosts!$D$2:$D$3432,'Summary of unit costs'!V$1,InterventionCosts!$A$2:$A$3432,'Summary of unit costs'!$A90) -> 1.9314161e+09
A91: Men's clinics for HIV treatment (STI component only) | C91: Adult men on ART served by men's clinics (cost of ART already accounted for in ART costs above) | E91: Ingredients | F91: ENB | G91: {=IF(E91="Literature",INDEX(LiteratureCost!$I$2:$I$42,MATCH('Summary of unit costs'!A91,LiteratureCost!$A$2:$A$42,0)),INDEX(InterventionCosts!$L$1:$L$3432,MATCH(A91,IF(InterventionCosts!$F$1:$F$3432="Cost per intervention",InterventionCosts!$A$1:$A$3432),0)))} -> 29.878729 | H91: =G91/exrate -> 1.6011616 | I91: {=IF(E91="Literature",INDEX(LiteratureCost!$G$2:$G$22,MATCH('Summary of unit costs'!A91,LiteratureCost!$A$2:$A$22,0)),INDEX(InterventionCosts!$L$1:$L$3432,MATCH(A91,IF(InterventionCosts!$F$1:$F$3432="Unit",InterventionCosts!$A$1:$A$3432),0)))} -> per person per year | J91: =G91/SUM(Q91:V91) -> 1 | K91: =Q91/$G91 -> 0.021955419 | L91: =R91/$G91 -> 0.022064192 | M91: =S91/$G91 -> 0 | N91: =T91/$G91 -> 0 | O91: =U91/$G91 -> 0 | P91: =V91/$G91 -> 0.95598039 | Q91: =SUMIFS(InterventionCosts!$K$2:$K$3432,InterventionCosts!$D$2:$D$3432,'Summary of unit costs'!Q$1,InterventionCosts!$A$2:$A$3432,'Summary of unit costs'!$A91) -> 0.656 | R91: =SUMIFS(InterventionCosts!$K$2:$K$3432,InterventionCosts!$D$2:$D$3432,'Summary of unit costs'!R$1,InterventionCosts!$A$2:$A$3432,'Summary of unit costs'!$A91) -> 0.65925 | S91: =SUMIFS(InterventionCosts!$K$2:$K$3432,InterventionCosts!$D$2:$D$3432,'Summary of unit costs'!S$1,InterventionCosts!$A$2:$A$3432,'Summary of unit costs'!$A91) -> 0 | T91: =SUMIFS(InterventionCosts!$K$2:$K$3432,InterventionCosts!$D$2:$D$3432,'Summary of unit costs'!T$1,InterventionCosts!$A$2:$A$3432,'Summary of unit costs'!$A91) -> 0 | U91: =SUMIFS(InterventionCosts!$K$2:$K$3432,InterventionCosts!$D$2:$D$3432,'Summary of unit costs'!U$1,InterventionCosts!$A$2:$A$3432,'Summary of unit costs'!$A91) -> 0 | V91: =SUMIFS(InterventionCosts!$K$2:$K$3432,InterventionCosts!$D$2:$D$3432,'Summary of unit costs'!V$1,InterventionCosts!$A$2:$A$3432,'Summary of unit costs'!$A91) -> 28.563479
A92: Peer navigator for HIV treatment | C92: Applied to adults on ART, at feasible maximum coverage of this intervention | E92: Ingredients | F92: ENB | G92: {=IF(E92="Literature",INDEX(LiteratureCost!$I$2:$I$42,MATCH('Summary of unit costs'!A92,LiteratureCost!$A$2:$A$42,0)),INDEX(InterventionCosts!$L$1:$L$3432,MATCH(A92,IF(InterventionCosts!$F$1:$F$3432="Cost per intervention",InterventionCosts!$A$1:$A$3432),0)))} -> 1482.1927 | H92: =G92/exrate -> 79.428749 | I92: {=IF(E92="Literature",INDEX(LiteratureCost!$G$2:$G$22,MATCH('Summary of unit costs'!A92,LiteratureCost!$A$2:$A$22,0)),INDEX(InterventionCosts!$L$1:$L$3432,MATCH(A92,IF(InterventionCosts!$F$1:$F$3432="Unit",InterventionCosts!$A$1:$A$3432),0)))} -> per client | J92: =G92/SUM(Q92:V92) -> 1 | K92: =Q92/$G92 -> 0.074390915 | L92: =R92/$G92 -> 0 | M92: =S92/$G92 -> 0.2105988 | N92: =T92/$G92 -> 0 | O92: =U92/$G92 -> 0.18075198 | P92: =V92/$G92 -> 0.53425831 | Q92: =SUMIFS(InterventionCosts!$K$2:$K$3432,InterventionCosts!$D$2:$D$3432,'Summary of unit costs'!Q$1,InterventionCosts!$A$2:$A$3432,'Summary of unit costs'!$A92) -> 110.26167 | R92: =SUMIFS(InterventionCosts!$K$2:$K$3432,InterventionCosts!$D$2:$D$3432,'Summary of unit costs'!R$1,InterventionCosts!$A$2:$A$3432,'Summary of unit costs'!$A92) -> 0 | S92: =SUMIFS(InterventionCosts!$K$2:$K$3432,InterventionCosts!$D$2:$D$3432,'Summary of unit costs'!S$1,InterventionCosts!$A$2:$A$3432,'Summary of unit costs'!$A92) -> 312.148 | T92: =SUMIFS(InterventionCosts!$K$2:$K$3432,InterventionCosts!$D$2:$D$3432,'Summary of unit costs'!T$1,InterventionCosts!$A$2:$A$3432,'Summary of unit costs'!$A92) -> 0 | U92: =SUMIFS(InterventionCosts!$K$2:$K$3432,InterventionCosts!$D$2:$D$3432,'Summary of unit costs'!U$1,InterventionCosts!$A$2:$A$3432,'Summary of unit costs'!$A92) -> 267.90926 | V92: =SUMIFS(InterventionCosts!$K$2:$K$3432,InterventionCosts!$D$2:$D$3432,'Summary of unit costs'!V$1,InterventionCosts!$A$2:$A$3432,'Summary of unit costs'!$A92) -> 791.87378

Sheet Ingredients
A1: Ingredients | B1: Description (optional) | C1: Cost from source | D1: Cost Unit | E1: Cost year | F1: Source of unit cost | G1: Equipment life years (if applicable) | H1: Scale parameter (eg. used to scale annual cost to a monthly cost, or monthly to per minute) | I1: ="Unit Cost (ZAR "&CostYear&")" -> Unit Cost (ZAR 2024) | J1: Cost Unit (adjusted for scale) | K1: Notes | L1: Used in ingredient costing directly?
A2: Consumables
A3: Comfort packs | C3: 500 | D3: per pack | E3: 2023 | F3: 2023/24 CG business plans. Steve Cohen personal communication | I3: =IF(G3="",VLOOKUP(IF(Inflation!$B$1-Ingredients!E3>0,Inflation!$B$1-Ingredients!E3,0),Inflation!$C$5:$D$20,2,FALSE)*C3,-PMT(0.08,G3,VLOOKUP(IF(Inflation!$B$1-Ingredients!E3>0,Inflation!$B$1-Ingredients!E3,0),Inflation!$C$5:$D$20,2,FALSE)*C3,0,1))/MAX(1,H3) -> 534.5 | J3: =IF(H3="",D3,"REDO") -> per pack | L3: =IF(IFERROR(INDEX(InterventionCosts!$A$2:$A$2363,(MATCH(A3,InterventionCosts!$B$2:$B$2363,0))),1)=1,"","Yes") -> Yes
A4: Cotton wool swabs | B4: Swabs, cleansing, Type 3, 100 swabsDiameter: 30mm | C4: 31.4 | D4: per 100 swabs | E4: 2024 | F4: http://www.treasury.gov.za/divisions/ocpo/ostb/contracts/RT42-2022zip | I4: =IF(G4="",VLOOKUP(IF(Inflation!$B$1-Ingredients!E4>0,Inflation!$B$1-Ingredients!E4,0),Inflation!$C$5:$D$20,2,FALSE)*C4,-PMT(0.08,G4,VLOOKUP(IF(Inflation!$B$1-Ingredients!E4>0,Inflation!$B$1-Ingredients!E4,0),Inflation!$C$5:$D$20,2,FALSE)*C4,0,1))/MAX(1,H4) -> 31.4 | J4: =IF(H4="",D4,"REDO") -> per 100 swabs | L4: =IF(IFERROR(INDEX(InterventionCosts!$A$2:$A$2363,(MATCH(A4,InterventionCosts!$B$2:$B$2363,0))),1)=1,"","Yes") -> Yes
A5: Disinfectant | B5: Chlorhexidine 0.5% in Alcohol 70%, solution with emollient, 500ml Coloured red | C5: 17.92 | D5: per 500ml | E5: 2024 | F5: https://www.health.gov.za/wp-content/uploads/2024/04/HP12-2023LQ-CPA-Add-4-12-Effective-1-May-2024.pdf | I5: =IF(G5="",VLOOKUP(IF(Inflation!$B$1-Ingredients!E5>0,Inflation!$B$1-Ingredients!E5,0),Inflation!$C$5:$D$20,2,FALSE)*C5,-PMT(0.08,G5,VLOOKUP(IF(Inflation!$B$1-Ingredients!E5>0,Inflation!$B$1-Ingredients!E5,0),Inflation!$C$5:$D$20,2,FALSE)*C5,0,1))/MAX(1,H5) -> 17.92 | J5: =IF(H5="",D5,"REDO") -> per 500ml | L5: =IF(IFERROR(INDEX(InterventionCosts!$A$2:$A$2363,(MATCH(A5,InterventionCosts!$B$2:$B$2363,0))),1)=1,"","Yes") -> Yes
A6: Female condom | B6: Weighted average cost of female condoms (see Condoms sheet) | C6: 9.816359 | D6: per condom | E6: 2024 | F6: http://www.treasury.gov.za/divisions/ocpo/ostb/contracts/RT75-2021.zip | I6: =IF(G6="",VLOOKUP(IF(Inflation!$B$1-Ingredients!E6>0,Inflation!$B$1-Ingredients!E6,0),Inflation!$C$5:$D$20,2,FALSE)*C6,-PMT(0.08,G6,VLOOKUP(IF(Inflation!$B$1-Ingredients!E6>0,Inflation!$B$1-Ingredients!E6,0),Inflation!$C$5:$D$20,2,FALSE)*C6,0,1))/MAX(1,H6) -> 9.816359 | J6: =IF(H6="",D6,"REDO") -> per condom | L6: =IF(IFERROR(INDEX(InterventionCosts!$A$2:$A$2363,(MATCH(A6,InterventionCosts!$B$2:$B$2363,0))),1)=1,"","Yes") -> Yes
A7: Male condom | B7: Weighted average cost of male condoms (see Condoms sheet) | C7: 0.6193946 | D7: per condom | E7: 2024 | F7: https://www.treasury.gov.za/divisions/ocpo/ostb/contracts/RT75-2021.zip | I7: =IF(G7="",VLOOKUP(IF(Inflation!$B$1-Ingredients!E7>0,Inflation!$B$1-Ingredients!E7,0),Inflation!$C$5:$D$20,2,FALSE)*C7,-PMT(0.08,G7,VLOOKUP(IF(Inflation!$B$1-Ingredients!E7>0,Inflation!$B$1-Ingredients!E7,0),Inflation!$C$5:$D$20,2,FALSE)*C7,0,1))/MAX(1,H7) -> 0.6193946 | J7: =IF(H7="",D7,"REDO") -> per condom | L7: =IF(IFERROR(INDEX(InterventionCosts!$A$2:$A$2363,(MATCH(A7,InterventionCosts!$B$2:$B$2363,0))),1)=1,"","Yes") -> Yes
A8: Lubricant | B8: Lubricant, water based, non-irritant, for use during intercourse; Treasury tender (weighted average) | C8: 0.42 | D8: per sachet | E8: 2024 | F8: https://www.treasury.gov.za/divisions/ocpo/ostb/contracts/RT75-2021.zip | I8: =IF(G8="",VLOOKUP(IF(Inflation!$B$1-Ingredients!E8>0,Inflation!$B$1-Ingredients!E8,0),Inflation!$C$5:$D$20,2,FALSE)*C8,-PMT(0.08,G8,VLOOKUP(IF(Inflation!$B$1-Ingredients!E8>0,Inflation!$B$1-Ingredients!E8,0),Inflation!$C$5:$D$20,2,FALSE)*C8,0,1))/MAX(1,H8) -> 0.42 | J8: =IF(H8="",D8,"REDO") -> per sachet | L8: =IF(IFERROR(INDEX(InterventionCosts!$A$2:$A$2363,(MATCH(A8,InterventionCosts!$B$2:$B$2363,0))),1)=1,"","Yes") -> Yes
A9: Gloves (non-sterile) | B9: Glove, examination, non-sterile, type 1 Latex, single use, Powder free, Ambidextrous, SANS 11193-1, Size: Medium, 50 pairs per box of 100 | C9: 53.08 | D9: per pack 100, 50 pairs | E9: 2024 | F9: https://www.treasury.gov.za/divisions/ocpo/ostb/contracts/RT76-2023%20CPA%20Amendment%204-%20Effective%2001%20May%202024.pdf | I9: =IF(G9="",VLOOKUP(IF(Inflation!$B$1-Ingredients!E9>0,Inflation!$B$1-Ingredients!E9,0),Inflation!$C$5:$D$20,2,FALSE)*C9,-PMT(0.08,G9,VLOOKUP(IF(Inflation!$B$1-Ingredients!E9>0,Inflation!$B$1-Ingredients!E9,0),Inflation!$C$5:$D$20,2,FALSE)*C9,0,1))/MAX(1,H9) -> 53.08 | J9: =IF(H9="",D9,"REDO") -> per pack 100, 50 pairs | L9: =IF(IFERROR(INDEX(InterventionCosts!$A$2:$A$2363,(MATCH(A9,InterventionCosts!$B$2:$B$2363,0))),1)=1,"","Yes") -> Yes
A10: IEC flyer | B10: Patient information | C10: =0.6 -> 0.6 | D10: per material | E10: 2016 | F10: RSA Global Fund Grant portfolio budgets 2016 | I10: =IF(G10="",VLOOKUP(IF(Inflation!$B$1-Ingredients!E10>0,Inflation!$B$1-Ingredients!E10,0),Inflation!$C$5:$D$20,2,FALSE)*C10,-PMT(0.08,G10,VLOOKUP(IF(Inflation!$B$1-Ingredients!E10>0,Inflation!$B$1-Ingredients!E10,0),Inflation!$C$5:$D$20,2,FALSE)*C10,0,1))/MAX(1,H10) -> 0.90383818 | J10: =IF(H10="",D10,"REDO") -> per material | L10: =IF(IFERROR(INDEX(InterventionCosts!$A$2:$A$2363,(MATCH(A10,InterventionCosts!$B$2:$B$2363,0))),1)=1,"","Yes") -> Yes
A11: Needle | B11: Needle Hypoderm.Inj. 21G; L/point | C11: =(0.45+0.47+0.46)/3*100 -> 46 | D11: per pack 100 | E11: 2024 | F11: https://www.treasury.gov.za/divisions/ocpo/ostb/contracts/RT284-2023.zip | I11: =IF(G11="",VLOOKUP(IF(Inflation!$B$1-Ingredients!E11>0,Inflation!$B$1-Ingredients!E11,0),Inflation!$C$5:$D$20,2,FALSE)*C11,-PMT(0.08,G11,VLOOKUP(IF(Inflation!$B$1-Ingredients!E11>0,Inflation!$B$1-Ingredients!E11,0),Inflation!$C$5:$D$20,2,FALSE)*C11,0,1))/MAX(1,H11) -> 46 | J11: =IF(H11="",D11,"REDO") -> per pack 100 | L11: =IF(IFERROR(INDEX(InterventionCosts!$A$2:$A$2363,(MATCH(A11,InterventionCosts!$B$2:$B$2363,0))),1)=1,"","Yes") -> Yes
A12: Swabs, gauze, absorbent, type 3, bleached, 8 ply, 100 swabs | C12: 13.5 | D12: per pack 100 | E12: 2024 | F12: http://www.treasury.gov.za/divisions/ocpo/ostb/contracts/RT42-2022zip | I12: =IF(G12="",VLOOKUP(IF(Inflation!$B$1-Ingredients!E12>0,Inflation!$B$1-Ingredients!E12,0),Inflation!$C$5:$D$20,2,FALSE)*C12,-PMT(0.08,G12,VLOOKUP(IF(Inflation!$B$1-Ingredients!E12>0,Inflation!$B$1-Ingredients!E12,0),Inflation!$C$5:$D$20,2,FALSE)*C12,0,1))/MAX(1,H12) -> 13.5 | J12: =IF(H12="",D12,"REDO") -> per pack 100 | L12: =IF(IFERROR(INDEX(InterventionCosts!$A$2:$A$2363,(MATCH(A12,InterventionCosts!$B$2:$B$2363,0))),1)=1,"","Yes") -> Yes
A13: Advance test kits | B13: ABON HIV 1/2 | C13: 7.86 | D13: per test kit | E13: 2024 | F13: https://www.treasury.gov.za/divisions/ocpo/ostb/contracts/RT41-2020.zip | I13: =IF(G13="",VLOOKUP(IF(Inflation!$B$1-Ingredients!E13>0,Inflation!$B$1-Ingredients!E13,0),Inflation!$C$5:$D$20,2,FALSE)*C13,-PMT(0.08,G13,VLOOKUP(IF(Inflation!$B$1-Ingredients!E13>0,Inflation!$B$1-Ingredients!E13,0),Inflation!$C$5:$D$20,2,FALSE)*C13,0,1))/MAX(1,H13) -> 7.86 | J13: =IF(H13="",D13,"REDO") -> per test kit | L13: =IF(IFERROR(INDEX(InterventionCosts!$A$2:$A$2363,(MATCH(A13,InterventionCosts!$B$2:$B$2363,0))),1)=1,"","Yes") -> Yes
A14: HIV rapid test | B14: First response HIV 1/2 | C14: 9.3 | D14: per test | E14: 2024 | F14: https://www.treasury.gov.za/divisions/ocpo/ostb/contracts/RT41-2020.zip | I14: =IF(G14="",VLOOKUP(IF(Inflation!$B$1-Ingredients!E14>0,Inflation!$B$1-Ingredients!E14,0),Inflation!$C$5:$D$20,2,FALSE)*C14,-PMT(0.08,G14,VLOOKUP(IF(Inflation!$B$1-Ingredients!E14>0,Inflation!$B$1-Ingredients!E14,0),Inflation!$C$5:$D$20,2,FALSE)*C14,0,1))/MAX(1,H14) -> 9.3 | J14: =IF(H14="",D14,"REDO") -> per test | K14: Average of supplier prices | L14: =IF(IFERROR(INDEX(InterventionCosts!$A$2:$A$2363,(MATCH(A14,InterventionCosts!$B$2:$B$2363,0))),1)=1,"","Yes") -> Yes
A15: Bond paper | B15: Box of 500x5 TYPEK A4 (for consent forms) | C15: =410/2500 -> 0.164 | D15: per page | E15: 2024 | F15: https://www.makro.co.za/stationery-office-furniture/paper-filing/paper/white-paper/copy-paper/typek-a4-office-paper-80-gsm/p/000000000000012434_BOX | I15: =IF(G15="",VLOOKUP(IF(Inflation!$B$1-Ingredients!E15>0,Inflation!$B$1-Ingredients!E15,0),Inflation!$C$5:$D$20,2,FALSE)*C15,-PMT(0.08,G15,VLOOKUP(IF(Inflation!$B$1-Ingredients!E15>0,Inflation!$B$1-Ingredients!E15,0),Inflation!$C$5:$D$20,2,FALSE)*C15,0,1))/MAX(1,H15) -> 0.164 | J15: =IF(H15="",D15,"REDO") -> per page | L15: =IF(IFERROR(INDEX(InterventionCosts!$A$2:$A$2363,(MATCH(A15,InterventionCosts!$B$2:$B$2363,0))),1)=1,"","Yes") -> Yes
A16: Paper A3 size (Typek) | C16: =229/500 -> 0.458 | D16: per page | E16: 2024 | F16: https://www.makro.co.za/stationery-office-furniture/paper-filing/paper/white-paper/a3-paper/typek-a3-office-paper-80-gsm/p/000000000000877929_EA | I16: =IF(G16="",VLOOKUP(IF(Inflation!$B$1-Ingredients!E16>0,Inflation!$B$1-Ingredients!E16,0),Inflation!$C$5:$D$20,2,FALSE)*C16,-PMT(0.08,G16,VLOOKUP(IF(Inflation!$B$1-Ingredients!E16>0,Inflation!$B$1-Ingredients!E16,0),Inflation!$C$5:$D$20,2,FALSE)*C16,0,1))/MAX(1,H16) -> 0.458 | J16: =IF(H16="",D16,"REDO") -> per page | L16: =IF(IFERROR(INDEX(InterventionCosts!$A$2:$A$2363,(MATCH(A16,InterventionCosts!$B$2:$B$2363,0))),1)=1,"","Yes") -> Yes
A17: Biosscrub | B17: Chlorhexidine 4% solution surgical scrub, 5L (sold in 500ml, price adjusted) | C17: =34.34*8 -> 274.72 | D17: per 5L | E17: 2024 | F17: https://www.health.gov.za/wp-content/uploads/2024/04/HP12-2023LQ-CPA-Add-4-12-Effective-1-May-2024.pdf | I17: =IF(G17="",VLOOKUP(IF(Inflation!$B$1-Ingredients!E17>0,Inflation!$B$1-Ingredients!E17,0),Inflation!$C$5:$D$20,2,FALSE)*C17,-PMT(0.08,G17,VLOOKUP(IF(Inflation!$B$1-Ingredients!E17>0,Inflation!$B$1-Ingredients!E17,0),Inflation!$C$5:$D$20,2,FALSE)*C17,0,1))/MAX(1,H17) -> 274.72 | J17: =IF(H17="",D17,"REDO") -> per 5L | L17: =IF(IFERROR(INDEX(InterventionCosts!$A$2:$A$2363,(MATCH(A17,InterventionCosts!$B$2:$B$2363,0))),1)=1,"","Yes") -> Yes
A18: Red biohazard bags | B18: per single | C18: =46*1.15/20 -> 2.645 | D18: per bag | E18: 2024 | F18: https://medqsupplies.co.za/product/bio-hazard-plastic-bags/ | I18: =IF(G18="",VLOOKUP(IF(Inflation!$B$1-Ingredients!E18>0,Inflation!$B$1-Ingredients!E18,0),Inflation!$C$5:$D$20,2,FALSE)*C18,-PMT(0.08,G18,VLOOKUP(IF(Inflation!$B$1-Ingredients!E18>0,Inflation!$B$1-Ingredients!E18,0),Inflation!$C$5:$D$20,2,FALSE)*C18,0,1))/MAX(1,H18) -> 2.645 | J18: =IF(H18="",D18,"REDO") -> per bag | L18: =IF(IFERROR(INDEX(InterventionCosts!$A$2:$A$2363,(MATCH(A18,InterventionCosts!$B$2:$B$2363,0))),1)=1,"","Yes") -> Yes
A19: Paper flip Files | B19: Pack of 20 | C19: 129 | D19: per 20 files | E19: 2024 | F19: https://www.makro.co.za/stationery-office-furniture/paper-filing/filing-folders/file-storage/tidy-files-medium-weight-files-/p/000000000000125629_PK | I19: =IF(G19="",VLOOKUP(IF(Inflation!$B$1-Ingredients!E19>0,Inflation!$B$1-Ingredients!E19,0),Inflation!$C$5:$D$20,2,FALSE)*C19,-PMT(0.08,G19,VLOOKUP(IF(Inflation!$B$1-Ingredients!E19>0,Inflation!$B$1-Ingredients!E19,0),Inflation!$C$5:$D$20,2,FALSE)*C19,0,1))/MAX(1,H19) -> 129 | J19: =IF(H19="",D19,"REDO") -> per 20 files | L19: =IF(IFERROR(INDEX(InterventionCosts!$A$2:$A$2363,(MATCH(A19,InterventionCosts!$B$2:$B$2363,0))),1)=1,"","Yes") -> Yes
A20: Results cards | B20: per one | C20: =0.05*13.5790416666667 -> 0.67895208 | D20: per 1 | E20: 2016 | F20: https://doi.org/10.1038/s41598-019-49109-w | I20: =IF(G20="",VLOOKUP(IF(Inflation!$B$1-Ingredients!E20>0,Inflation!$B$1-Ingredients!E20,0),Inflation!$C$5:$D$20,2,FALSE)*C20,-PMT(0.08,G20,VLOOKUP(IF(Inflation!$B$1-Ingredients!E20>0,Inflation!$B$1-Ingredients!E20,0),Inflation!$C$5:$D$20,2,FALSE)*C20,0,1))/MAX(1,H20) -> 1.0227714 | J20: =IF(H20="",D20,"REDO") -> per 1 | L20: =IF(IFERROR(INDEX(InterventionCosts!$A$2:$A$2363,(MATCH(A20,InterventionCosts!$B$2:$B$2363,0))),1)=1,"","Yes") -> Yes
A21: Hand sanitizer (500ml) | B21: Chlorhexidine 0.5% in Alcohol 70%, solution with emollient, 500ml Coloured red | C21: 17.92 | D21: per 500ml | E21: 2024 | F21: https://www.health.gov.za/wp-content/uploads/2024/04/HP12-2023LQ-CPA-Add-4-12-Effective-1-May-2024.pdf | I21: =IF(G21="",VLOOKUP(IF(Inflation!$B$1-Ingredients!E21>0,Inflation!$B$1-Ingredients!E21,0),Inflation!$C$5:$D$20,2,FALSE)*C21,-PMT(0.08,G21,VLOOKUP(IF(Inflation!$B$1-Ingredients!E21>0,Inflation!$B$1-Ingredients!E21,0),Inflation!$C$5:$D$20,2,FALSE)*C21,0,1))/MAX(1,H21) -> 17.92 | J21: =IF(H21="",D21,"REDO") -> per 500ml | L21: =IF(IFERROR(INDEX(InterventionCosts!$A$2:$A$2363,(MATCH(A21,InterventionCosts!$B$2:$B$2363,0))),1)=1,"","Yes") -> Yes
A22: IEC material (design, print, distribute) | C22: =2 -> 2 | D22: per material | E22: 2014 | F22: RSA GF proposal 2014 | I22: =IF(G22="",VLOOKUP(IF(Inflation!$B$1-Ingredients!E22>0,Inflation!$B$1-Ingredients!E22,0),Inflation!$C$5:$D$20,2,FALSE)*C22,-PMT(0.08,G22,VLOOKUP(IF(Inflation!$B$1-Ingredients!E22>0,Inflation!$B$1-Ingredients!E22,0),Inflation!$C$5:$D$20,2,FALSE)*C22,0,1))/MAX(1,H22) -> 3.3436168 | J22: =IF(H22="",D22,"REDO") -> per material | L22: =IF(IFERROR(INDEX(InterventionCosts!$A$2:$A$2363,(MATCH(A22,InterventionCosts!$B$2:$B$2363,0))),1)=1,"","Yes") -> Yes
A23: Pregnancy test (urine) | C23: =75.9/20 -> 3.795 | D23: per test | E23: 2019 | F23: Kendon Medical Supplies Pty Ltd, quote (19 Aug 2019) | I23: =IF(G23="",VLOOKUP(IF(Inflation!$B$1-Ingredients!E23>0,Inflation!$B$1-Ingredients!E23,0),Inflation!$C$5:$D$20,2,FALSE)*C23,-PMT(0.08,G23,VLOOKUP(IF(Inflation!$B$1-Ingredients!E23>0,Inflation!$B$1-Ingredients!E23,0),Inflation!$C$5:$D$20,2,FALSE)*C23,0,1))/MAX(1,H23) -> 4.8734278 | J23: =IF(H23="",D23,"REDO") -> per test | L23: =IF(IFERROR(INDEX(InterventionCosts!$A$2:$A$2363,(MATCH(A23,InterventionCosts!$B$2:$B$2363,0))),1)=1,"","Yes") -> Yes
A24: Rapid HIV test disposal | C24: 60 | D24: per 5l container | E24: 2024 | F24: https://www.medicalinnovations.co.za/product/sharps-container-5l/ | I24: =IF(G24="",VLOOKUP(IF(Inflation!$B$1-Ingredients!E24>0,Inflation!$B$1-Ingredients!E24,0),Inflation!$C$5:$D$20,2,FALSE)*C24,-PMT(0.08,G24,VLOOKUP(IF(Inflation!$B$1-Ingredients!E24>0,Inflation!$B$1-Ingredients!E24,0),Inflation!$C$5:$D$20,2,FALSE)*C24,0,1))/MAX(1,H24) -> 60 | J24: =IF(H24="",D24,"REDO") -> per 5l container | L24: =IF(IFERROR(INDEX(InterventionCosts!$A$2:$A$2363,(MATCH(A24,InterventionCosts!$B$2:$B$2363,0))),1)=1,"","Yes") -> Yes
A25: ART PPP Non-ARV drugs | C25: ='NonART drug data and costs'!$K$7 -> 29.735051 | D25: per visit | E25: 2023 | F25: Updated costs for Long L, Girdwood S, Govender K, Meyer-Rath G, Miot J: Cost and outcomes of routine HIV care and treatment: A comparison of public and private delivery models covering low-income earners in South Africa. Preprint available under DOI: https://doi.org/10.21203/rs.3.rs-960517/v1 | I25: =IF(G25="",VLOOKUP(IF(Inflation!$B$1-Ingredients!E25>0,Inflation!$B$1-Ingredients!E25,0),Inflation!$C$5:$D$20,2,FALSE)*C25,-PMT(0.08,G25,VLOOKUP(IF(Inflation!$B$1-Ingredients!E25>0,Inflation!$B$1-Ingredients!E25,0),Inflation!$C$5:$D$20,2,FALSE)*C25,0,1))/MAX(1,H25) -> 31.78677 | J25: =IF(H25="",D25,"REDO") -> per visit | L25: =IF(IFERROR(INDEX(InterventionCosts!$A$2:$A$2363,(MATCH(A25,InterventionCosts!$B$2:$B$2363,0))),1)=1,"","Yes") -> Yes
A26: HIVST kit | B26: Weighted avg from RT41-2020 amend6, oral and blood | C26: 74.558798 | D26: per test kit | E26: 2024 | F26: https://www.treasury.gov.za/divisions/ocpo/ostb/contracts/RT41-2020%20Addendum%202%20Price%20Adjustment.pdf | I26: =IF(G26="",VLOOKUP(IF(Inflation!$B$1-Ingredients!E26>0,Inflation!$B$1-Ingredients!E26,0),Inflation!$C$5:$D$20,2,FALSE)*C26,-PMT(0.08,G26,VLOOKUP(IF(Inflation!$B$1-Ingredients!E26>0,Inflation!$B$1-Ingredients!E26,0),Inflation!$C$5:$D$20,2,FALSE)*C26,0,1))/MAX(1,H26) -> 74.558798 | J26: =IF(H26="",D26,"REDO") -> per test kit | L26: =IF(IFERROR(INDEX(InterventionCosts!$A$2:$A$2363,(MATCH(A26,InterventionCosts!$B$2:$B$2363,0))),1)=1,"","Yes") -> Yes
A27: Rapid syphilis test | C27: 11.96 | D27: per test | E27: 2024 | F27: https://www.treasury.gov.za/divisions/ocpo/ostb/contracts/RT41-1-2020%20CPA%20Addendum%205.pdf | I27: =IF(G27="",VLOOKUP(IF(Inflation!$B$1-Ingredients!E27>0,Inflation!$B$1-Ingredients!E27,0),Inflation!$C$5:$D$20,2,FALSE)*C27,-PMT(0.08,G27,VLOOKUP(IF(Inflation!$B$1-Ingredients!E27>0,Inflation!$B$1-Ingredients!E27,0),Inflation!$C$5:$D$20,2,FALSE)*C27,0,1))/MAX(1,H27) -> 11.96 | J27: =IF(H27="",D27,"REDO") -> per test | L27: =IF(IFERROR(INDEX(InterventionCosts!$A$2:$A$2363,(MATCH(A27,InterventionCosts!$B$2:$B$2363,0))),1)=1,"","Yes") -> Yes
A28: Reagent (GX HIV Viral load) | C28: =149/10*1.15*exrate -> 319.75037 | D28: per test | E28: 2024 | F28: https://www.stoptb.org/sites/default/files/gdf_diagnostics_medical_devices_other_health_products_catalog_0.pdf | I28: =IF(G28="",VLOOKUP(IF(Inflation!$B$1-Ingredients!E28>0,Inflation!$B$1-Ingredients!E28,0),Inflation!$C$5:$D$20,2,FALSE)*C28,-PMT(0.08,G28,VLOOKUP(IF(Inflation!$B$1-Ingredients!E28>0,Inflation!$B$1-Ingredients!E28,0),Inflation!$C$5:$D$20,2,FALSE)*C28,0,1))/MAX(1,H28) -> 319.75037 | J28: =IF(H28="",D28,"REDO") -> per test | L28: =IF(IFERROR(INDEX(InterventionCosts!$A$2:$A$2363,(MATCH(A28,InterventionCosts!$B$2:$B$2363,0))),1)=1,"","Yes") -> Yes
A29: GX Consumables | C29: 2.81 | D29: per test | E29: 2019 | F29: Sarah Girdwood, https://www.ncbi.nlm.nih.gov/pmc/articles/PMC7700965/pdf/main.pdf | I29: =IF(G29="",VLOOKUP(IF(Inflation!$B$1-Ingredients!E29>0,Inflation!$B$1-Ingredients!E29,0),Inflation!$C$5:$D$20,2,FALSE)*C29,-PMT(0.08,G29,VLOOKUP(IF(Inflation!$B$1-Ingredients!E29>0,Inflation!$B$1-Ingredients!E29,0),Inflation!$C$5:$D$20,2,FALSE)*C29,0,1))/MAX(1,H29) -> 3.6085196 | J29: =IF(H29="",D29,"REDO") -> per test | L29: =IF(IFERROR(INDEX(InterventionCosts!$A$2:$A$2363,(MATCH(A29,InterventionCosts!$B$2:$B$2363,0))),1)=1,"","Yes") -> Yes
A30: PN printing/copying | C30: 75.144689 | D30: per client | E30: 2023 | F30: https://doi.org/10.1097/qai.0000000000003371 | I30: =IF(G30="",VLOOKUP(IF(Inflation!$B$1-Ingredients!E30>0,Inflation!$B$1-Ingredients!E30,0),Inflation!$C$5:$D$20,2,FALSE)*C30,-PMT(0.08,G30,VLOOKUP(IF(Inflation!$B$1-Ingredients!E30>0,Inflation!$B$1-Ingredients!E30,0),Inflation!$C$5:$D$20,2,FALSE)*C30,0,1))/MAX(1,H30) -> 80.329673 | J30: =IF(H30="",D30,"REDO") -> per client | L30: =IF(IFERROR(INDEX(InterventionCosts!$A$2:$A$2363,(MATCH(A30,InterventionCosts!$B$2:$B$2363,0))),1)=1,"","Yes") -> Yes
A31: PN office supplies | C31: 27 | D31: per client | E31: 2023 | F31: https://doi.org/10.1097/qai.0000000000003371 | I31: =IF(G31="",VLOOKUP(IF(Inflation!$B$1-Ingredients!E31>0,Inflation!$B$1-Ingredients!E31,0),Inflation!$C$5:$D$20,2,FALSE)*C31,-PMT(0.08,G31,VLOOKUP(IF(Inflation!$B$1-Ingredients!E31>0,Inflation!$B$1-Ingredients!E31,0),Inflation!$C$5:$D$20,2,FALSE)*C31,0,1))/MAX(1,H31) -> 28.863 | J31: =IF(H31="",D31,"REDO") -> per client | L31: =IF(IFERROR(INDEX(InterventionCosts!$A$2:$A$2363,(MATCH(A31,InterventionCosts!$B$2:$B$2363,0))),1)=1,"","Yes") -> Yes
A32: PN SMS service | C32: 1 | D32: per client | E32: 2023 | F32: https://doi.org/10.1097/qai.0000000000003371 | I32: =IF(G32="",VLOOKUP(IF(Inflation!$B$1-Ingredients!E32>0,Inflation!$B$1-Ingredients!E32,0),Inflation!$C$5:$D$20,2,FALSE)*C32,-PMT(0.08,G32,VLOOKUP(IF(Inflation!$B$1-Ingredients!E32>0,Inflation!$B$1-Ingredients!E32,0),Inflation!$C$5:$D$20,2,FALSE)*C32,0,1))/MAX(1,H32) -> 1.069 | J32: =IF(H32="",D32,"REDO") -> per client | L32: =IF(IFERROR(INDEX(InterventionCosts!$A$2:$A$2363,(MATCH(A32,InterventionCosts!$B$2:$B$2363,0))),1)=1,"","Yes") -> Yes
A33: Staff | L33: =IF(IFERROR(INDEX(InterventionCosts!$A$2:$A$2363,(MATCH(A33,InterventionCosts!$B$2:$B$2363,0))),1)=1,"","Yes")
A34: Area co-ordinator - BCC & outreach | C34: 408000 | D34: per annum | E34: 2022 | F34: GF Grant Portfolio Budget 2022 (Steve's Cohen personal communication) | H34: =workminutespa -> 107040 | I34: =IF(G34="",VLOOKUP(IF(Inflation!$B$1-Ingredients!E34>0,Inflation!$B$1-Ingredients!E34,0),Inflation!$C$5:$D$20,2,FALSE)*C34,-PMT(0.08,G34,VLOOKUP(IF(Inflation!$B$1-Ingredients!E34>0,Inflation!$B$1-Ingredients!E34,0),Inflation!$C$5:$D$20,2,FALSE)*C34,0,1))/MAX(1,H34) -> 4.3558155 | J34: per minute | L34: =IF(IFERROR(INDEX(InterventionCosts!$A$2:$A$2363,(MATCH(A34,InterventionCosts!$B$2:$B$2363,0))),1)=1,"","Yes") -> Yes
A35: Cleaner | B35: R22/hour | C35: =Staff_costs!$N$96 -> 4100.2267 | D35: per month | E35: 2024 | F35: =Staff_costs!D96 -> https://www.gov.za/news/media-statements/government-activities/minister-thulas-nxesi-announces-national-minimum-wage | I35: =IF(G35="",VLOOKUP(IF(Inflation!$B$1-Ingredients!E35>0,Inflation!$B$1-Ingredients!E35,0),Inflation!$C$5:$D$20,2,FALSE)*C35,-PMT(0.08,G35,VLOOKUP(IF(Inflation!$B$1-Ingredients!E35>0,Inflation!$B$1-Ingredients!E35,0),Inflation!$C$5:$D$20,2,FALSE)*C35,0,1))/MAX(1,H35) -> 4100.2267 | J35: =IF(H35="",D35,"REDO") -> per month | L35: =IF(IFERROR(INDEX(InterventionCosts!$A$2:$A$2363,(MATCH(A35,InterventionCosts!$B$2:$B$2363,0))),1)=1,"","Yes") -> Yes
A36: Queue marshall | B36: EWPW minimum wage | C36: =Staff_costs!$B$47 -> 2076.8733 | D36: per month | E36: 2024 | F36: https://www.gov.za/speeches/minister-thulas-nxesi-hikes-minimum-wage-farmworkers-and-domestic-workers-22-feb-2023-0000 | I36: =IF(G36="",VLOOKUP(IF(Inflation!$B$1-Ingredients!E36>0,Inflation!$B$1-Ingredients!E36,0),Inflation!$C$5:$D$20,2,FALSE)*C36,-PMT(0.08,G36,VLOOKUP(IF(Inflation!$B$1-Ingredients!E36>0,Inflation!$B$1-Ingredients!E36,0),Inflation!$C$5:$D$20,2,FALSE)*C36,0,1))/MAX(1,H36) -> 2076.8733 | J36: =IF(H36="",D36,"REDO") -> per month | L36: =IF(IFERROR(INDEX(InterventionCosts!$A$2:$A$2363,(MATCH(A36,InterventionCosts!$B$2:$B$2363,0))),1)=1,"","Yes") -> Yes
A37: Clerk | C37: =Staff_costs!$C$22 -> 1.8019482 | D37: per minute | E37: 2024 | F37: April 2024 Salary scale | I37: =IF(G37="",VLOOKUP(IF(Inflation!$B$1-Ingredients!E37>0,Inflation!$B$1-Ingredients!E37,0),Inflation!$C$5:$D$20,2,FALSE)*C37,-PMT(0.08,G37,VLOOKUP(IF(Inflation!$B$1-Ingredients!E37>0,Inflation!$B$1-Ingredients!E37,0),Inflation!$C$5:$D$20,2,FALSE)*C37,0,1))/MAX(1,H37) -> 1.8019482 | J37: =IF(H37="",D37,"REDO") -> per minute | L37: =IF(IFERROR(INDEX(InterventionCosts!$A$2:$A$2363,(MATCH(A37,InterventionCosts!$B$2:$B$2363,0))),1)=1,"","Yes") -> Yes
A38: Community health worker | C38: =Staff_costs!$B$44 -> 4100.2267 | D38: per month | E38: 2024 | F38: https://www.health.gov.za/wp-content/uploads/2022/07/Health-Department-welcomes-Bargaining-Council-resolution-to-improve-work-conditions-of-CHWs-27-July-2022.pdf | I38: =IF(G38="",VLOOKUP(IF(Inflation!$B$1-Ingredients!E38>0,Inflation!$B$1-Ingredients!E38,0),Inflation!$C$5:$D$20,2,FALSE)*C38,-PMT(0.08,G38,VLOOKUP(IF(Inflation!$B$1-Ingredients!E38>0,Inflation!$B$1-Ingredients!E38,0),Inflation!$C$5:$D$20,2,FALSE)*C38,0,1))/MAX(1,H38) -> 4100.2267 | J38: =IF(H38="",D38,"REDO") -> per month | L38: =IF(IFERROR(INDEX(InterventionCosts!$A$2:$A$2363,(MATCH(A38,InterventionCosts!$B$2:$B$2363,0))),1)=1,"","Yes") -> Yes
A39: Counsellor | C39: =Staff_costs!$C$23 -> 1.2444367 | D39: per minute | E39: 2024 | F39: April 2024 Salary scale | I39: =IF(G39="",VLOOKUP(IF(Inflation!$B$1-Ingredients!E39>0,Inflation!$B$1-Ingredients!E39,0),Inflation!$C$5:$D$20,2,FALSE)*C39,-PMT(0.08,G39,VLOOKUP(IF(Inflation!$B$1-Ingredients!E39>0,Inflation!$B$1-Ingredients!E39,0),Inflation!$C$5:$D$20,2,FALSE)*C39,0,1))/MAX(1,H39) -> 1.2444367 | J39: =IF(H39="",D39,"REDO") -> per minute | L39: =IF(IFERROR(INDEX(InterventionCosts!$A$2:$A$2363,(MATCH(A39,InterventionCosts!$B$2:$B$2363,0))),1)=1,"","Yes") -> Yes
A40: Data capturer | C40: =Staff_costs!$C$24 -> 1.8549351 | D40: per minute | E40: 2024 | F40: April 2024 Salary scale | I40: =IF(G40="",VLOOKUP(IF(Inflation!$B$1-Ingredients!E40>0,Inflation!$B$1-Ingredients!E40,0),Inflation!$C$5:$D$20,2,FALSE)*C40,-PMT(0.08,G40,VLOOKUP(IF(Inflation!$B$1-Ingredients!E40>0,Inflation!$B$1-Ingredients!E40,0),Inflation!$C$5:$D$20,2,FALSE)*C40,0,1))/MAX(1,H40) -> 1.8549351 | J40: =IF(H40="",D40,"REDO") -> per minute | L40: =IF(IFERROR(INDEX(InterventionCosts!$A$2:$A$2363,(MATCH(A40,InterventionCosts!$B$2:$B$2363,0))),1)=1,"","Yes") -> Yes
A41: Monitoring & Evaluation officer NGO | C41: 288000 | D41: per annum | E41: 2022 | F41: GF Grant Portfolio Budget 2022 (Steve Cohen personal communication) | H41: =workminutespa -> 107040 | I41: =IF(G41="",VLOOKUP(IF(Inflation!$B$1-Ingredients!E41>0,Inflation!$B$1-Ingredients!E41,0),Inflation!$C$5:$D$20,2,FALSE)*C41,-PMT(0.08,G41,VLOOKUP(IF(Inflation!$B$1-Ingredients!E41>0,Inflation!$B$1-Ingredients!E41,0),Inflation!$C$5:$D$20,2,FALSE)*C41,0,1))/MAX(1,H41) -> 3.0746933 | J41: per minute | L41: =IF(IFERROR(INDEX(InterventionCosts!$A$2:$A$2363,(MATCH(A41,InterventionCosts!$B$2:$B$2363,0))),1)=1,"","Yes") -> Yes
A42: Peer motivator stipend | C42: 20400 | D42: per annum | E42: 2022 | F42: GF Grant Portfolio Budget 2022 (Steve Cohen personal communication) | H42: =workminutespa -> 107040 | I42: =IF(G42="",VLOOKUP(IF(Inflation!$B$1-Ingredients!E42>0,Inflation!$B$1-Ingredients!E42,0),Inflation!$C$5:$D$20,2,FALSE)*C42,-PMT(0.08,G42,VLOOKUP(IF(Inflation!$B$1-Ingredients!E42>0,Inflation!$B$1-Ingredients!E42,0),Inflation!$C$5:$D$20,2,FALSE)*C42,0,1))/MAX(1,H42) -> 0.21779077 | J42: per minute | L42: =IF(IFERROR(INDEX(InterventionCosts!$A$2:$A$2363,(MATCH(A42,InterventionCosts!$B$2:$B$2363,0))),1)=1,"","Yes") -> Yes
A43: Programme Manager - Government | C43: =Staff_costs!$B$46*12 -> 1265311.9 | D43: per annum | E43: 2024 | F43: April 2024 Salary scale | H43: =workminutespa -> 107040 | I43: =IF(G43="",VLOOKUP(IF(Inflation!$B$1-Ingredients!E43>0,Inflation!$B$1-Ingredients!E43,0),Inflation!$C$5:$D$20,2,FALSE)*C43,-PMT(0.08,G43,VLOOKUP(IF(Inflation!$B$1-Ingredients!E43>0,Inflation!$B$1-Ingredients!E43,0),Inflation!$C$5:$D$20,2,FALSE)*C43,0,1))/MAX(1,H43) -> 11.820926 | J43: per minute | L43: =IF(IFERROR(INDEX(InterventionCosts!$A$2:$A$2363,(MATCH(A43,InterventionCosts!$B$2:$B$2363,0))),1)=1,"","Yes") -> Yes
A44: Security Guard | C44: =Staff_costs!B37*12 -> 140774 | D44: per annum | E44: 2024 | F44: =Staff_costs!D97 -> https://www.psira.co.za/dmdocuments/Illustrative%20Costing%20Guideline%202024-2025%20AREA%201%20and%202.pdf | H44: =workminutespa -> 107040 | I44: =IF(G44="",VLOOKUP(IF(Inflation!$B$1-Ingredients!E44>0,Inflation!$B$1-Ingredients!E44,0),Inflation!$C$5:$D$20,2,FALSE)*C44,-PMT(0.08,G44,VLOOKUP(IF(Inflation!$B$1-Ingredients!E44>0,Inflation!$B$1-Ingredients!E44,0),Inflation!$C$5:$D$20,2,FALSE)*C44,0,1))/MAX(1,H44) -> 1.3151532 | J44: per minute | L44: =IF(IFERROR(INDEX(InterventionCosts!$A$2:$A$2363,(MATCH(A44,InterventionCosts!$B$2:$B$2363,0))),1)=1,"","Yes") -> Yes
A45: Social Worker | C45: =Staff_costs!C32 -> 5.3971454 | D45: per minute | E45: 2024 | F45: April 2024 Salary scale | I45: =IF(G45="",VLOOKUP(IF(Inflation!$B$1-Ingredients!E45>0,Inflation!$B$1-Ingredients!E45,0),Inflation!$C$5:$D$20,2,FALSE)*C45,-PMT(0.08,G45,VLOOKUP(IF(Inflation!$B$1-Ingredients!E45>0,Inflation!$B$1-Ingredients!E45,0),Inflation!$C$5:$D$20,2,FALSE)*C45,0,1))/MAX(1,H45) -> 5.3971454 | J45: =IF(H45="",D45,"REDO") -> per minute | L45: =IF(IFERROR(INDEX(InterventionCosts!$A$2:$A$2363,(MATCH(A45,InterventionCosts!$B$2:$B$2363,0))),1)=1,"","Yes") -> Yes
A46: Staff Nurse | C46: =Staff_costs!C33 -> 3.239228 | D46: per minute | E46: 2024 | F46: April 2024 Salary scale | I46: =IF(G46="",VLOOKUP(IF(Inflation!$B$1-Ingredients!E46>0,Inflation!$B$1-Ingredients!E46,0),Inflation!$C$5:$D$20,2,FALSE)*C46,-PMT(0.08,G46,VLOOKUP(IF(Inflation!$B$1-Ingredients!E46>0,Inflation!$B$1-Ingredients!E46,0),Inflation!$C$5:$D$20,2,FALSE)*C46,0,1))/MAX(1,H46) -> 3.239228 | J46: =IF(H46="",D46,"REDO") -> per minute | L46: =IF(IFERROR(INDEX(InterventionCosts!$A$2:$A$2363,(MATCH(A46,InterventionCosts!$B$2:$B$2363,0))),1)=1,"","Yes") -> Yes
A47: Nursing assistant | C47: =Staff_costs!C34 -> 2.5530496 | D47: per minute | E47: 2024 | F47: April 2024 Salary scale | I47: =IF(G47="",VLOOKUP(IF(Inflation!$B$1-Ingredients!E47>0,Inflation!$B$1-Ingredients!E47,0),Inflation!$C$5:$D$20,2,FALSE)*C47,-PMT(0.08,G47,VLOOKUP(IF(Inflation!$B$1-Ingredients!E47>0,Inflation!$B$1-Ingredients!E47,0),Inflation!$C$5:$D$20,2,FALSE)*C47,0,1))/MAX(1,H47) -> 2.5530496 | J47: =IF(H47="",D47,"REDO") -> per minute | L47: =IF(IFERROR(INDEX(InterventionCosts!$A$2:$A$2363,(MATCH(A47,InterventionCosts!$B$2:$B$2363,0))),1)=1,"","Yes") -> Yes
A48: Senior nurse | C48: =Staff_costs!B35 -> 34361.648 | D48: per month | E48: 2024 | F48: April 2024 Salary scale | I48: =IF(G48="",VLOOKUP(IF(Inflation!$B$1-Ingredients!E48>0,Inflation!$B$1-Ingredients!E48,0),Inflation!$C$5:$D$20,2,FALSE)*C48,-PMT(0.08,G48,VLOOKUP(IF(Inflation!$B$1-Ingredients!E48>0,Inflation!$B$1-Ingredients!E48,0),Inflation!$C$5:$D$20,2,FALSE)*C48,0,1))/MAX(1,H48) -> 34361.648 | J48: =IF(H48="",D48,"REDO") -> per month | L48: =IF(IFERROR(INDEX(InterventionCosts!$A$2:$A$2363,(MATCH(A48,InterventionCosts!$B$2:$B$2363,0))),1)=1,"","Yes") -> Yes
A49: Professional nurse (Speciality) | C49: =Staff_costs!B31 -> 53200.165 | D49: per month | E49: 2024 | F49: April 2024 Salary scale | I49: =IF(G49="",VLOOKUP(IF(Inflation!$B$1-Ingredients!E49>0,Inflation!$B$1-Ingredients!E49,0),Inflation!$C$5:$D$20,2,FALSE)*C49,-PMT(0.08,G49,VLOOKUP(IF(Inflation!$B$1-Ingredients!E49>0,Inflation!$B$1-Ingredients!E49,0),Inflation!$C$5:$D$20,2,FALSE)*C49,0,1))/MAX(1,H49) -> 53200.165 | J49: =IF(H49="",D49,"REDO") -> per month | L49: =IF(IFERROR(INDEX(InterventionCosts!$A$2:$A$2363,(MATCH(A49,InterventionCosts!$B$2:$B$2363,0))),1)=1,"","Yes") -> Yes
A50: Professional nurse | C50: =Staff_costs!C30 -> 4.8996606 | D50: per minute | E50: 2024 | F50: April 2024 Salary scale | I50: =IF(G50="",VLOOKUP(IF(Inflation!$B$1-Ingredients!E50>0,Inflation!$B$1-Ingredients!E50,0),Inflation!$C$5:$D$20,2,FALSE)*C50,-PMT(0.08,G50,VLOOKUP(IF(Inflation!$B$1-Ingredients!E50>0,Inflation!$B$1-Ingredients!E50,0),Inflation!$C$5:$D$20,2,FALSE)*C50,0,1))/MAX(1,H50) -> 4.8996606 | J50: =IF(H50="",D50,"REDO") -> per minute | L50: =IF(IFERROR(INDEX(InterventionCosts!$A$2:$A$2363,(MATCH(A50,InterventionCosts!$B$2:$B$2363,0))),1)=1,"","Yes") -> Yes
A51: Pharmacist | C51: =Staff_costs!C26 -> 9.1192802 | D51: per minute | E51: 2024 | F51: April 2024 Salary scale | I51: =IF(G51="",VLOOKUP(IF(Inflation!$B$1-Ingredients!E51>0,Inflation!$B$1-Ingredients!E51,0),Inflation!$C$5:$D$20,2,FALSE)*C51,-PMT(0.08,G51,VLOOKUP(IF(Inflation!$B$1-Ingredients!E51>0,Inflation!$B$1-Ingredients!E51,0),Inflation!$C$5:$D$20,2,FALSE)*C51,0,1))/MAX(1,H51) -> 9.1192802 | J51: =IF(H51="",D51,"REDO") -> per minute | L51: =IF(IFERROR(INDEX(InterventionCosts!$A$2:$A$2363,(MATCH(A51,InterventionCosts!$B$2:$B$2363,0))),1)=1,"","Yes") -> Yes
A52: Pharmacist assistant | C52: =Staff_costs!C27 -> 2.1347304 | D52: per minute | E52: 2024 | F52: April 2024 Salary scale | I52: =IF(G52="",VLOOKUP(IF(Inflation!$B$1-Ingredients!E52>0,Inflation!$B$1-Ingredients!E52,0),Inflation!$C$5:$D$20,2,FALSE)*C52,-PMT(0.08,G52,VLOOKUP(IF(Inflation!$B$1-Ingredients!E52>0,Inflation!$B$1-Ingredients!E52,0),Inflation!$C$5:$D$20,2,FALSE)*C52,0,1))/MAX(1,H52) -> 2.1347304 | J52: =IF(H52="",D52,"REDO") -> per minute | L52: =IF(IFERROR(INDEX(InterventionCosts!$A$2:$A$2363,(MATCH(A52,InterventionCosts!$B$2:$B$2363,0))),1)=1,"","Yes") -> Yes
A53: Medical officer | C53: =Staff_costs!C28 -> 13.503224 | D53: per minute | E53: 2024 | F53: April 2024 Salary scale | I53: =IF(G53="",VLOOKUP(IF(Inflation!$B$1-Ingredients!E53>0,Inflation!$B$1-Ingredients!E53,0),Inflation!$C$5:$D$20,2,FALSE)*C53,-PMT(0.08,G53,VLOOKUP(IF(Inflation!$B$1-Ingredients!E53>0,Inflation!$B$1-Ingredients!E53,0),Inflation!$C$5:$D$20,2,FALSE)*C53,0,1))/MAX(1,H53) -> 13.503224 | J53: =IF(H53="",D53,"REDO") -> per minute | L53: =IF(IFERROR(INDEX(InterventionCosts!$A$2:$A$2363,(MATCH(A53,InterventionCosts!$B$2:$B$2363,0))),1)=1,"","Yes") -> Yes
A54: Administrative assistant | C54: =Staff_costs!B38 -> 21800.312 | D54: per month | E54: 2024 | F54: April 2024 Salary scale | I54: =IF(G54="",VLOOKUP(IF(Inflation!$B$1-Ingredients!E54>0,Inflation!$B$1-Ingredients!E54,0),Inflation!$C$5:$D$20,2,FALSE)*C54,-PMT(0.08,G54,VLOOKUP(IF(Inflation!$B$1-Ingredients!E54>0,Inflation!$B$1-Ingredients!E54,0),Inflation!$C$5:$D$20,2,FALSE)*C54,0,1))/MAX(1,H54) -> 21800.312 | J54: =IF(H54="",D54,"REDO") -> per month | L54: =IF(IFERROR(INDEX(InterventionCosts!$A$2:$A$2363,(MATCH(A54,InterventionCosts!$B$2:$B$2363,0))),1)=1,"","Yes") -> Yes
A55: Field coordinator | C55: =Staff_costs!B39 -> 62408.152 | D55: per month | E55: 2024 | F55: April 2024 Salary scale | I55: =IF(G55="",VLOOKUP(IF(Inflation!$B$1-Ingredients!E55>0,Inflation!$B$1-Ingredients!E55,0),Inflation!$C$5:$D$20,2,FALSE)*C55,-PMT(0.08,G55,VLOOKUP(IF(Inflation!$B$1-Ingredients!E55>0,Inflation!$B$1-Ingredients!E55,0),Inflation!$C$5:$D$20,2,FALSE)*C55,0,1))/MAX(1,H55) -> 62408.152 | J55: =IF(H55="",D55,"REDO") -> per month | L55: =IF(IFERROR(INDEX(InterventionCosts!$A$2:$A$2363,(MATCH(A55,InterventionCosts!$B$2:$B$2363,0))),1)=1,"","Yes") -> Yes
A56: Community mobilizer | C56: =Staff_costs!C42 -> 2.4439811 | D56: per minute | E56: 2024 | F56: April 2024 Salary scale | I56: =IF(G56="",VLOOKUP(IF(Inflation!$B$1-Ingredients!E56>0,Inflation!$B$1-Ingredients!E56,0),Inflation!$C$5:$D$20,2,FALSE)*C56,-PMT(0.08,G56,VLOOKUP(IF(Inflation!$B$1-Ingredients!E56>0,Inflation!$B$1-Ingredients!E56,0),Inflation!$C$5:$D$20,2,FALSE)*C56,0,1))/MAX(1,H56) -> 2.4439811 | J56: =IF(H56="",D56,"REDO") -> per minute | L56: =IF(IFERROR(INDEX(InterventionCosts!$A$2:$A$2363,(MATCH(A56,InterventionCosts!$B$2:$B$2363,0))),1)=1,"","Yes") -> Yes
A57: Data technician | C57: =Staff_costs!B40 -> 25449.108 | D57: per month | E57: 2024 | F57: April 2024 Salary scale | I57: =IF(G57="",VLOOKUP(IF(Inflation!$B$1-Ingredients!E57>0,Inflation!$B$1-Ingredients!E57,0),Inflation!$C$5:$D$20,2,FALSE)*C57,-PMT(0.08,G57,VLOOKUP(IF(Inflation!$B$1-Ingredients!E57>0,Inflation!$B$1-Ingredients!E57,0),Inflation!$C$5:$D$20,2,FALSE)*C57,0,1))/MAX(1,H57) -> 25449.108 | J57: =IF(H57="",D57,"REDO") -> per month | L57: =IF(IFERROR(INDEX(InterventionCosts!$A$2:$A$2363,(MATCH(A57,InterventionCosts!$B$2:$B$2363,0))),1)=1,"","Yes") -> Yes
A58: Driver | C58: =Staff_costs!B41 -> 23181.75 | D58: per month | E58: 2024 | F58: April 2024 Salary scale | I58: =IF(G58="",VLOOKUP(IF(Inflation!$B$1-Ingredients!E58>0,Inflation!$B$1-Ingredients!E58,0),Inflation!$C$5:$D$20,2,FALSE)*C58,-PMT(0.08,G58,VLOOKUP(IF(Inflation!$B$1-Ingredients!E58>0,Inflation!$B$1-Ingredients!E58,0),Inflation!$C$5:$D$20,2,FALSE)*C58,0,1))/MAX(1,H58) -> 23181.75 | J58: =IF(H58="",D58,"REDO") -> per month | L58: =IF(IFERROR(INDEX(InterventionCosts!$A$2:$A$2363,(MATCH(A58,InterventionCosts!$B$2:$B$2363,0))),1)=1,"","Yes") -> Yes
A59: Peer educator | B59: same as CHW | C59: =C38 -> 4100.2267 | D59: per month | E59: 2024 | F59: =F38 -> https://www.health.gov.za/wp-content/uploads/2022/07/Health-Department-welcomes-Bargaining-Council-resolution-to-improve-work-conditions-of-CHWs-27-July-2022.pdf | I59: =IF(G59="",VLOOKUP(IF(Inflation!$B$1-Ingredients!E59>0,Inflation!$B$1-Ingredients!E59,0),Inflation!$C$5:$D$20,2,FALSE)*C59,-PMT(0.08,G59,VLOOKUP(IF(Inflation!$B$1-Ingredients!E59>0,Inflation!$B$1-Ingredients!E59,0),Inflation!$C$5:$D$20,2,FALSE)*C59,0,1))/MAX(1,H59) -> 4100.2267 | J59: =IF(H59="",D59,"REDO") -> per month | L59: =IF(IFERROR(INDEX(InterventionCosts!$A$2:$A$2363,(MATCH(A59,InterventionCosts!$B$2:$B$2363,0))),1)=1,"","Yes") -> Yes
A60: Community navigator | B60: same as CHW | C60: =C38 -> 4100.2267 | D60: =D38 -> per month | E60: 2024 | F60: =F38 -> https://www.health.gov.za/wp-content/uploads/2022/07/Health-Department-welcomes-Bargaining-Council-resolution-to-improve-work-conditions-of-CHWs-27-July-2022.pdf | I60: =IF(G60="",VLOOKUP(IF(Inflation!$B$1-Ingredients!E60>0,Inflation!$B$1-Ingredients!E60,0),Inflation!$C$5:$D$20,2,FALSE)*C60,-PMT(0.08,G60,VLOOKUP(IF(Inflation!$B$1-Ingredients!E60>0,Inflation!$B$1-Ingredients!E60,0),Inflation!$C$5:$D$20,2,FALSE)*C60,0,1))/MAX(1,H60) -> 4100.2267 | J60: =IF(H60="",D60,"REDO") -> per month | L60: =IF(IFERROR(INDEX(InterventionCosts!$A$2:$A$2363,(MATCH(A60,InterventionCosts!$B$2:$B$2363,0))),1)=1,"","Yes") -> Yes
A61: Linkage Officer | B61: of similar calibre to linkage officers employed in NGO sector, Gr4 Non-OSD (AIDS healthcare foundation) | C61: =Staff_costs!$B$43*12 -> 261603.74 | D61: per year | E61: 2024 | F61: April 2024 Salary scale | I61: =IF(G61="",VLOOKUP(IF(Inflation!$B$1-Ingredients!E61>0,Inflation!$B$1-Ingredients!E61,0),Inflation!$C$5:$D$20,2,FALSE)*C61,-PMT(0.08,G61,VLOOKUP(IF(Inflation!$B$1-Ingredients!E61>0,Inflation!$B$1-Ingredients!E61,0),Inflation!$C$5:$D$20,2,FALSE)*C61,0,1))/MAX(1,H61) -> 261603.74 | J61: =IF(H61="",D61,"REDO") -> per year | L61: =IF(IFERROR(INDEX(InterventionCosts!$A$2:$A$2363,(MATCH(A61,InterventionCosts!$B$2:$B$2363,0))),1)=1,"","Yes") -> Yes
A62: Case Manager | C62: =Staff_costs!$B$48*12 -> 165035 | D62: per year | E62: 2024 | F62: April 2024 Salary scale | I62: =IF(G62="",VLOOKUP(IF(Inflation!$B$1-Ingredients!E62>0,Inflation!$B$1-Ingredients!E62,0),Inflation!$C$5:$D$20,2,FALSE)*C62,-PMT(0.08,G62,VLOOKUP(IF(Inflation!$B$1-Ingredients!E62>0,Inflation!$B$1-Ingredients!E62,0),Inflation!$C$5:$D$20,2,FALSE)*C62,0,1))/MAX(1,H62) -> 165035 | J62: =IF(H62="",D62,"REDO") -> per year | L62: =IF(IFERROR(INDEX(InterventionCosts!$A$2:$A$2363,(MATCH(A62,InterventionCosts!$B$2:$B$2363,0))),1)=1,"","Yes") -> Yes
A63: Social Work and related professionals | C63: =Staff_costs!$B$32*12 -> 577710.44 | D63: per year | E63: 2024 | F63: April 2024 Salary scale | I63: =IF(G63="",VLOOKUP(IF(Inflation!$B$1-Ingredients!E63>0,Inflation!$B$1-Ingredients!E63,0),Inflation!$C$5:$D$20,2,FALSE)*C63,-PMT(0.08,G63,VLOOKUP(IF(Inflation!$B$1-Ingredients!E63>0,Inflation!$B$1-Ingredients!E63,0),Inflation!$C$5:$D$20,2,FALSE)*C63,0,1))/MAX(1,H63) -> 577710.44 | J63: =IF(H63="",D63,"REDO") -> per year | L63: =IF(IFERROR(INDEX(InterventionCosts!$A$2:$A$2363,(MATCH(A63,InterventionCosts!$B$2:$B$2363,0))),1)=1,"","Yes") -> Yes
A64: WBOT OTL | C64: =Staff_costs!$B$42*12 -> 261603.74 | D64: per year | E64: 2024 | F64: April 2024 Salary scale | I64: =IF(G64="",VLOOKUP(IF(Inflation!$B$1-Ingredients!E64>0,Inflation!$B$1-Ingredients!E64,0),Inflation!$C$5:$D$20,2,FALSE)*C64,-PMT(0.08,G64,VLOOKUP(IF(Inflation!$B$1-Ingredients!E64>0,Inflation!$B$1-Ingredients!E64,0),Inflation!$C$5:$D$20,2,FALSE)*C64,0,1))/MAX(1,H64) -> 261603.74 | J64: =IF(H64="",D64,"REDO") -> per year | L64: =IF(IFERROR(INDEX(InterventionCosts!$A$2:$A$2363,(MATCH(A64,InterventionCosts!$B$2:$B$2363,0))),1)=1,"","Yes") -> Yes
A65: Youth workers | B65: same as CHW | C65: =C38 -> 4100.2267 | D65: =D38 -> per month | E65: =E38 -> 2024 | F65: =F38 -> https://www.health.gov.za/wp-content/uploads/2022/07/Health-Department-welcomes-Bargaining-Council-resolution-to-improve-work-conditions-of-CHWs-27-July-2022.pdf | I65: =IF(G65="",VLOOKUP(IF(Inflation!$B$1-Ingredients!E65>0,Inflation!$B$1-Ingredients!E65,0),Inflation!$C$5:$D$20,2,FALSE)*C65,-PMT(0.08,G65,VLOOKUP(IF(Inflation!$B$1-Ingredients!E65>0,Inflation!$B$1-Ingredients!E65,0),Inflation!$C$5:$D$20,2,FALSE)*C65,0,1))/MAX(1,H65) -> 4100.2267 | J65: =IF(H65="",D65,"REDO") -> per month | L65: =IF(IFERROR(INDEX(InterventionCosts!$A$2:$A$2363,(MATCH(A65,InterventionCosts!$B$2:$B$2363,0))),1)=1,"","Yes") -> Yes
A66: WBOT CHW | B66: same as CHW | C66: =C38 -> 4100.2267 | D66: =D38 -> per month | E66: =E38 -> 2024 | F66: =F38 -> https://www.health.gov.za/wp-content/uploads/2022/07/Health-Department-welcomes-Bargaining-Council-resolution-to-improve-work-conditions-of-CHWs-27-July-2022.pdf | I66: =IF(G66="",VLOOKUP(IF(Inflation!$B$1-Ingredients!E66>0,Inflation!$B$1-Ingredients!E66,0),Inflation!$C$5:$D$20,2,FALSE)*C66,-PMT(0.08,G66,VLOOKUP(IF(Inflation!$B$1-Ingredients!E66>0,Inflation!$B$1-Ingredients!E66,0),Inflation!$C$5:$D$20,2,FALSE)*C66,0,1))/MAX(1,H66) -> 4100.2267 | J66: =IF(H66="",D66,"REDO") -> per month | L66: =IF(IFERROR(INDEX(InterventionCosts!$A$2:$A$2363,(MATCH(A66,InterventionCosts!$B$2:$B$2363,0))),1)=1,"","Yes") -> Yes
A67: Psychologists and Vocational Counsellors | C67: =Staff_costs!$B$45*12 -> 1071765.8 | D67: per year | E67: =E39 -> 2024 | F67: April 2024 Salary scale | I67: =IF(G67="",VLOOKUP(IF(Inflation!$B$1-Ingredients!E67>0,Inflation!$B$1-Ingredients!E67,0),Inflation!$C$5:$D$20,2,FALSE)*C67,-PMT(0.08,G67,VLOOKUP(IF(Inflation!$B$1-Ingredients!E67>0,Inflation!$B$1-Ingredients!E67,0),Inflation!$C$5:$D$20,2,FALSE)*C67,0,1))/MAX(1,H67) -> 1071765.8 | J67: =IF(H67="",D67,"REDO") -> per year | L67: =IF(IFERROR(INDEX(InterventionCosts!$A$2:$A$2363,(MATCH(A67,InterventionCosts!$B$2:$B$2363,0))),1)=1,"","Yes") -> Yes
A68: Lab manager (GX, NHLS) | C68: 4376 | D68: per setup | E68: 2019 | F68: Sarah Girdwood, https://www.ncbi.nlm.nih.gov/pmc/articles/PMC7700965/pdf/main.pdf | I68: =IF(G68="",VLOOKUP(IF(Inflation!$B$1-Ingredients!E68>0,Inflation!$B$1-Ingredients!E68,0),Inflation!$C$5:$D$20,2,FALSE)*C68,-PMT(0.08,G68,VLOOKUP(IF(Inflation!$B$1-Ingredients!E68>0,Inflation!$B$1-Ingredients!E68,0),Inflation!$C$5:$D$20,2,FALSE)*C68,0,1))/MAX(1,H68) -> 5619.5309 | J68: =IF(H68="",D68,"REDO") -> per setup | L68: =IF(IFERROR(INDEX(InterventionCosts!$A$2:$A$2363,(MATCH(A68,InterventionCosts!$B$2:$B$2363,0))),1)=1,"","Yes") -> Yes
A69: POCT coordinator | C69: 4431 | D69: per setup | E69: 2019 | F69: Sarah Girdwood, https://www.ncbi.nlm.nih.gov/pmc/articles/PMC7700965/pdf/main.pdf | I69: =IF(G69="",VLOOKUP(IF(Inflation!$B$1-Ingredients!E69>0,Inflation!$B$1-Ingredients!E69,0),Inflation!$C$5:$D$20,2,FALSE)*C69,-PMT(0.08,G69,VLOOKUP(IF(Inflation!$B$1-Ingredients!E69>0,Inflation!$B$1-Ingredients!E69,0),Inflation!$C$5:$D$20,2,FALSE)*C69,0,1))/MAX(1,H69) -> 5690.1603 | J69: =IF(H69="",D69,"REDO") -> per setup | L69: =IF(IFERROR(INDEX(InterventionCosts!$A$2:$A$2363,(MATCH(A69,InterventionCosts!$B$2:$B$2363,0))),1)=1,"","Yes") -> Yes
A70: Peer navigator | C70: =Staff_costs!$B$49 -> 4100.2267 | D70: per month | E70: 2024 | F70: April 2024 Salary scale | I70: =IF(G70="",VLOOKUP(IF(Inflation!$B$1-Ingredients!E70>0,Inflation!$B$1-Ingredients!E70,0),Inflation!$C$5:$D$20,2,FALSE)*C70,-PMT(0.08,G70,VLOOKUP(IF(Inflation!$B$1-Ingredients!E70>0,Inflation!$B$1-Ingredients!E70,0),Inflation!$C$5:$D$20,2,FALSE)*C70,0,1))/MAX(1,H70) -> 4100.2267 | J70: =IF(H70="",D70,"REDO") -> per month | L70: =IF(IFERROR(INDEX(InterventionCosts!$A$2:$A$2363,(MATCH(A70,InterventionCosts!$B$2:$B$2363,0))),1)=1,"","Yes") -> Yes
A71: Equipment | L71: =IF(IFERROR(INDEX(InterventionCosts!$A$2:$A$2363,(MATCH(A71,InterventionCosts!$B$2:$B$2363,0))),1)=1,"","Yes")
A72: Phone | B72: Makro website QUALITEL Corded Business Phone | C72: 549 | D72: per phone | E72: 2024 | F72: https://www.makro.co.za/stationery-office-furniture/office-electronics/telephones-fax-machines/corded-phones/corded-telephones/qualitel-corded-phone/p/000000000000246452_EA | G72: 5 | H72: 12 | I72: =IF(G72="",VLOOKUP(IF(Inflation!$B$1-Ingredients!E72>0,Inflation!$B$1-Ingredients!E72,0),Inflation!$C$5:$D$20,2,FALSE)*C72,-PMT(0.08,G72,VLOOKUP(IF(Inflation!$B$1-Ingredients!E72>0,Inflation!$B$1-Ingredients!E72,0),Inflation!$C$5:$D$20,2,FALSE)*C72,0,1))/MAX(1,H72) -> 10.609614 | J72: per month | L72: =IF(IFERROR(INDEX(InterventionCosts!$A$2:$A$2363,(MATCH(A72,InterventionCosts!$B$2:$B$2363,0))),1)=1,"","Yes") -> Yes
A73: PN telephone | C73: 292 | D73: per client | E73: 2023 | F73: https://doi.org/10.1097/qai.0000000000003371 | I73: =IF(G73="",VLOOKUP(IF(Inflation!$B$1-Ingredients!E73>0,Inflation!$B$1-Ingredients!E73,0),Inflation!$C$5:$D$20,2,FALSE)*C73,-PMT(0.08,G73,VLOOKUP(IF(Inflation!$B$1-Ingredients!E73>0,Inflation!$B$1-Ingredients!E73,0),Inflation!$C$5:$D$20,2,FALSE)*C73,0,1))/MAX(1,H73) -> 312.148 | J73: =IF(H73="",D73,"REDO") -> per client | L73: =IF(IFERROR(INDEX(InterventionCosts!$A$2:$A$2363,(MATCH(A73,InterventionCosts!$B$2:$B$2363,0))),1)=1,"","Yes") -> Yes
A74: Mobile van | B74: Tabana Operational Vehicle | C74: =1711 -> 1711 | D74: per month | E74: 2016 | F74: https://doi.org/10.1038/s41598-019-49109-w; Tabana Operational Vehicle 2016 | G74: 1 | I74: =IF(G74="",VLOOKUP(IF(Inflation!$B$1-Ingredients!E74>0,Inflation!$B$1-Ingredients!E74,0),Inflation!$C$5:$D$20,2,FALSE)*C74,-PMT(0.08,G74,VLOOKUP(IF(Inflation!$B$1-Ingredients!E74>0,Inflation!$B$1-Ingredients!E74,0),Inflation!$C$5:$D$20,2,FALSE)*C74,0,1))/MAX(1,H74) -> 2577.4452 | J74: =IF(H74="",D74,"REDO") -> per month | L74: =IF(IFERROR(INDEX(InterventionCosts!$A$2:$A$2363,(MATCH(A74,InterventionCosts!$B$2:$B$2363,0))),1)=1,"","Yes") -> Yes
A75: GeneXpert CAPEX II | B75: Equipment cost for IV module with laptop | C75: =12530*1.15*exrate -> 268890.75 | D75: per machine | E75: 2024 | F75: https://www.stoptb.org/sites/default/files/gdf_diagnostics_medical_devices_other_health_products_catalog_0.pdf | G75: 3 | I75: =IF(G75="",VLOOKUP(IF(Inflation!$B$1-Ingredients!E75>0,Inflation!$B$1-Ingredients!E75,0),Inflation!$C$5:$D$20,2,FALSE)*C75,-PMT(0.08,G75,VLOOKUP(IF(Inflation!$B$1-Ingredients!E75>0,Inflation!$B$1-Ingredients!E75,0),Inflation!$C$5:$D$20,2,FALSE)*C75,0,1))/MAX(1,H75) -> 96609.836 | J75: =IF(H75="",D75,"REDO") -> per machine | L75: =IF(IFERROR(INDEX(InterventionCosts!$A$2:$A$2363,(MATCH(A75,InterventionCosts!$B$2:$B$2363,0))),1)=1,"","Yes") -> Yes
A76: Support equipment (GX, NHLS) | C76: 9280 | D76: per setup | E76: 2019 | F76: Sarah Girdwood, https://www.ncbi.nlm.nih.gov/pmc/articles/PMC7700965/pdf/main.pdf | I76: =IF(G76="",VLOOKUP(IF(Inflation!$B$1-Ingredients!E76>0,Inflation!$B$1-Ingredients!E76,0),Inflation!$C$5:$D$20,2,FALSE)*C76,-PMT(0.08,G76,VLOOKUP(IF(Inflation!$B$1-Ingredients!E76>0,Inflation!$B$1-Ingredients!E76,0),Inflation!$C$5:$D$20,2,FALSE)*C76,0,1))/MAX(1,H76) -> 11917.104 | J76: =IF(H76="",D76,"REDO") -> per setup | L76: =IF(IFERROR(INDEX(InterventionCosts!$A$2:$A$2363,(MATCH(A76,InterventionCosts!$B$2:$B$2363,0))),1)=1,"","Yes") -> Yes
A77: Lab tests | L77: =IF(IFERROR(INDEX(InterventionCosts!$A$2:$A$2363,(MATCH(A77,InterventionCosts!$B$2:$B$2363,0))),1)=1,"","Yes")
A78: ELISA | B78: HIV Serology (confirm) | C78: 60.2 | D78: per test | E78: 2021 | F78: NHLS 2021 price-list | I78: =IF(G78="",VLOOKUP(IF(Inflation!$B$1-Ingredients!E78>0,Inflation!$B$1-Ingredients!E78,0),Inflation!$C$5:$D$20,2,FALSE)*C78,-PMT(0.08,G78,VLOOKUP(IF(Inflation!$B$1-Ingredients!E78>0,Inflation!$B$1-Ingredients!E78,0),Inflation!$C$5:$D$20,2,FALSE)*C78,0,1))/MAX(1,H78) -> 71.889952 | J78: =IF(H78="",D78,"REDO") -> per test | L78: =IF(IFERROR(INDEX(InterventionCosts!$A$2:$A$2363,(MATCH(A78,InterventionCosts!$B$2:$B$2363,0))),1)=1,"","Yes") -> Yes
A79: HIV PCR | C79: 414.58 | D79: per test | E79: 2021 | F79: NHLS 2021 price-list | I79: =IF(G79="",VLOOKUP(IF(Inflation!$B$1-Ingredients!E79>0,Inflation!$B$1-Ingredients!E79,0),Inflation!$C$5:$D$20,2,FALSE)*C79,-PMT(0.08,G79,VLOOKUP(IF(Inflation!$B$1-Ingredients!E79>0,Inflation!$B$1-Ingredients!E79,0),Inflation!$C$5:$D$20,2,FALSE)*C79,0,1))/MAX(1,H79) -> 495.08532 | J79: =IF(H79="",D79,"REDO") -> per test | L79: =IF(IFERROR(INDEX(InterventionCosts!$A$2:$A$2363,(MATCH(A79,InterventionCosts!$B$2:$B$2363,0))),1)=1,"","Yes") -> Yes
A80: Viral load | C80: 414.58 | D80: per test | E80: 2021 | F80: NHLS 2021 price-list | I80: =IF(G80="",VLOOKUP(IF(Inflation!$B$1-Ingredients!E80>0,Inflation!$B$1-Ingredients!E80,0),Inflation!$C$5:$D$20,2,FALSE)*C80,-PMT(0.08,G80,VLOOKUP(IF(Inflation!$B$1-Ingredients!E80>0,Inflation!$B$1-Ingredients!E80,0),Inflation!$C$5:$D$20,2,FALSE)*C80,0,1))/MAX(1,H80) -> 495.08532 | J80: =IF(H80="",D80,"REDO") -> per test | L80: =IF(IFERROR(INDEX(InterventionCosts!$A$2:$A$2363,(MATCH(A80,InterventionCosts!$B$2:$B$2363,0))),1)=1,"","Yes") -> Yes
A81: HBsAg | C81: 137.34 | D81: per test | E81: 2021 | F81: NHLS 2021 price-list | I81: =IF(G81="",VLOOKUP(IF(Inflation!$B$1-Ingredients!E81>0,Inflation!$B$1-Ingredients!E81,0),Inflation!$C$5:$D$20,2,FALSE)*C81,-PMT(0.08,G81,VLOOKUP(IF(Inflation!$B$1-Ingredients!E81>0,Inflation!$B$1-Ingredients!E81,0),Inflation!$C$5:$D$20,2,FALSE)*C81,0,1))/MAX(1,H81) -> 164.0094 | J81: =IF(H81="",D81,"REDO") -> per test | L81: =IF(IFERROR(INDEX(InterventionCosts!$A$2:$A$2363,(MATCH(A81,InterventionCosts!$B$2:$B$2363,0))),1)=1,"","Yes") -> Yes
A82: ALT | C82: 49.56 | D82: per test | E82: 2021 | F82: NHLS 2021 price-list | I82: =IF(G82="",VLOOKUP(IF(Inflation!$B$1-Ingredients!E82>0,Inflation!$B$1-Ingredients!E82,0),Inflation!$C$5:$D$20,2,FALSE)*C82,-PMT(0.08,G82,VLOOKUP(IF(Inflation!$B$1-Ingredients!E82>0,Inflation!$B$1-Ingredients!E82,0),Inflation!$C$5:$D$20,2,FALSE)*C82,0,1))/MAX(1,H82) -> 59.183821 | J82: =IF(H82="",D82,"REDO") -> per test | L82: =IF(IFERROR(INDEX(InterventionCosts!$A$2:$A$2363,(MATCH(A82,InterventionCosts!$B$2:$B$2363,0))),1)=1,"","Yes") -> Yes
A83: CD4 | C83: 72.51 | D83: per test | E83: 2021 | F83: NHLS 2021 price-list | I83: =IF(G83="",VLOOKUP(IF(Inflation!$B$1-Ingredients!E83>0,Inflation!$B$1-Ingredients!E83,0),Inflation!$C$5:$D$20,2,FALSE)*C83,-PMT(0.08,G83,VLOOKUP(IF(Inflation!$B$1-Ingredients!E83>0,Inflation!$B$1-Ingredients!E83,0),Inflation!$C$5:$D$20,2,FALSE)*C83,0,1))/MAX(1,H83) -> 86.590372 | J83: =IF(H83="",D83,"REDO") -> per test | L83: =IF(IFERROR(INDEX(InterventionCosts!$A$2:$A$2363,(MATCH(A83,InterventionCosts!$B$2:$B$2363,0))),1)=1,"","Yes") -> Yes
A84: Syphilis RPR | C84: 34.27 | D84: per test | E84: 2021 | F84: NHLS 2021 price-list | I84: =IF(G84="",VLOOKUP(IF(Inflation!$B$1-Ingredients!E84>0,Inflation!$B$1-Ingredients!E84,0),Inflation!$C$5:$D$20,2,FALSE)*C84,-PMT(0.08,G84,VLOOKUP(IF(Inflation!$B$1-Ingredients!E84>0,Inflation!$B$1-Ingredients!E84,0),Inflation!$C$5:$D$20,2,FALSE)*C84,0,1))/MAX(1,H84) -> 40.924728 | J84: =IF(H84="",D84,"REDO") -> per test | L84: =IF(IFERROR(INDEX(InterventionCosts!$A$2:$A$2363,(MATCH(A84,InterventionCosts!$B$2:$B$2363,0))),1)=1,"","Yes") -> Yes
A85: Creatinine | C85: 33.11 | D85: per test | E85: 2021 | F85: NHLS 2021 price-list | I85: =IF(G85="",VLOOKUP(IF(Inflation!$B$1-Ingredients!E85>0,Inflation!$B$1-Ingredients!E85,0),Inflation!$C$5:$D$20,2,FALSE)*C85,-PMT(0.08,G85,VLOOKUP(IF(Inflation!$B$1-Ingredients!E85>0,Inflation!$B$1-Ingredients!E85,0),Inflation!$C$5:$D$20,2,FALSE)*C85,0,1))/MAX(1,H85) -> 39.539473 | J85: =IF(H85="",D85,"REDO") -> per test | L85: =IF(IFERROR(INDEX(InterventionCosts!$A$2:$A$2363,(MATCH(A85,InterventionCosts!$B$2:$B$2363,0))),1)=1,"","Yes") -> Yes
A86: Overheads | L86: =IF(IFERROR(INDEX(InterventionCosts!$A$2:$A$2363,(MATCH(A86,InterventionCosts!$B$2:$B$2363,0))),1)=1,"","Yes")
A87: Distribution costs for non-traditional outlets (Female Condom) | B87: 40% Markup | C87: =40%*C6 -> 3.9265436 | D87: per condom distributed | E87: 2023 | F87: Provincial strategic implementation plans (Steve Cohen, personal communication) | I87: =IF(G87="",VLOOKUP(IF(Inflation!$B$1-Ingredients!E87>0,Inflation!$B$1-Ingredients!E87,0),Inflation!$C$5:$D$20,2,FALSE)*C87,-PMT(0.08,G87,VLOOKUP(IF(Inflation!$B$1-Ingredients!E87>0,Inflation!$B$1-Ingredients!E87,0),Inflation!$C$5:$D$20,2,FALSE)*C87,0,1))/MAX(1,H87) -> 4.1974751 | J87: =IF(H87="",D87,"REDO") -> per condom distributed | L87: =IF(IFERROR(INDEX(InterventionCosts!$A$2:$A$2363,(MATCH(A87,InterventionCosts!$B$2:$B$2363,0))),1)=1,"","Yes") -> Yes
A88: Distribution costs for non-traditional outlets (Male Condom) | B88: 40% Markup | C88: =40%*C7 -> 0.24775784 | D88: per condom distributed | E88: 2023 | F88: Provincial strategic implementation plans (Steve Cohen, personal communication) | I88: =IF(G88="",VLOOKUP(IF(Inflation!$B$1-Ingredients!E88>0,Inflation!$B$1-Ingredients!E88,0),Inflation!$C$5:$D$20,2,FALSE)*C88,-PMT(0.08,G88,VLOOKUP(IF(Inflation!$B$1-Ingredients!E88>0,Inflation!$B$1-Ingredients!E88,0),Inflation!$C$5:$D$20,2,FALSE)*C88,0,1))/MAX(1,H88) -> 0.26485313 | J88: =IF(H88="",D88,"REDO") -> per condom distributed | L88: =IF(IFERROR(INDEX(InterventionCosts!$A$2:$A$2363,(MATCH(A88,InterventionCosts!$B$2:$B$2363,0))),1)=1,"","Yes") -> Yes
A89: Distribution Costs (Female Condom) | B89: 20% Markup | C89: =20%*C6 -> 1.9632718 | D89: per condom distributed | E89: 2023 | F89: Provincial strategic implementation plans (Steve Cohen, personal communication) | I89: =IF(G89="",VLOOKUP(IF(Inflation!$B$1-Ingredients!E89>0,Inflation!$B$1-Ingredients!E89,0),Inflation!$C$5:$D$20,2,FALSE)*C89,-PMT(0.08,G89,VLOOKUP(IF(Inflation!$B$1-Ingredients!E89>0,Inflation!$B$1-Ingredients!E89,0),Inflation!$C$5:$D$20,2,FALSE)*C89,0,1))/MAX(1,H89) -> 2.0987375 | J89: =IF(H89="",D89,"REDO") -> per condom distributed | L89: =IF(IFERROR(INDEX(InterventionCosts!$A$2:$A$2363,(MATCH(A89,InterventionCosts!$B$2:$B$2363,0))),1)=1,"","Yes") -> Yes
A90: Distribution Costs (Male Condom) | B90: 20% Markup | C90: =20%*C7 -> 0.12387892 | D90: per condom distributed | E90: 2023 | F90: Provincial strategic implementation plans (Steve Cohen, personal communication) | I90: =IF(G90="",VLOOKUP(IF(Inflation!$B$1-Ingredients!E90>0,Inflation!$B$1-Ingredients!E90,0),Inflation!$C$5:$D$20,2,FALSE)*C90,-PMT(0.08,G90,VLOOKUP(IF(Inflation!$B$1-Ingredients!E90>0,Inflation!$B$1-Ingredients!E90,0),Inflation!$C$5:$D$20,2,FALSE)*C90,0,1))/MAX(1,H90) -> 0.13242656 | J90: =IF(H90="",D90,"REDO") -> per condom distributed | L90: =IF(IFERROR(INDEX(InterventionCosts!$A$2:$A$2363,(MATCH(A90,InterventionCosts!$B$2:$B$2363,0))),1)=1,"","Yes") -> Yes
A91: Electricity | B91: Average electricity in June-July 2016, -August-September 2016, Septemeber-October 2016 | C91: =(((8121.11-498.14)+(6925.66-416.02)+(7553-537.88))/3)/388 -> 18.168153 | D91: per square meter | E91: 2016 | F91: Estimate - HERO's Bills | I91: =IF(G91="",VLOOKUP(IF(Inflation!$B$1-Ingredients!E91>0,Inflation!$B$1-Ingredients!E91,0),Inflation!$C$5:$D$20,2,FALSE)*C91,-PMT(0.08,G91,VLOOKUP(IF(Inflation!$B$1-Ingredients!E91>0,Inflation!$B$1-Ingredients!E91,0),Inflation!$C$5:$D$20,2,FALSE)*C91,0,1))/MAX(1,H91) -> 27.36845 | J91: =IF(H91="",D91,"REDO") -> per square meter | L91: =IF(IFERROR(INDEX(InterventionCosts!$A$2:$A$2363,(MATCH(A91,InterventionCosts!$B$2:$B$2363,0))),1)=1,"","Yes") -> Yes
A92: Ground travel | B92: Motor vehicle | C92: 4.84 | D92: per km | E92: 2024 | F92: https://www.sars.gov.za/wp-content/uploads/Ops/Guides/PAYE-GEN-01-G03-Guide-for-Employers-in-respect-of-Allowances-External-Guide.pdf | I92: =IF(G92="",VLOOKUP(IF(Inflation!$B$1-Ingredients!E92>0,Inflation!$B$1-Ingredients!E92,0),Inflation!$C$5:$D$20,2,FALSE)*C92,-PMT(0.08,G92,VLOOKUP(IF(Inflation!$B$1-Ingredients!E92>0,Inflation!$B$1-Ingredients!E92,0),Inflation!$C$5:$D$20,2,FALSE)*C92,0,1))/MAX(1,H92) -> 4.84 | J92: =IF(H92="",D92,"REDO") -> per km | L92: =IF(IFERROR(INDEX(InterventionCosts!$A$2:$A$2363,(MATCH(A92,InterventionCosts!$B$2:$B$2363,0))),1)=1,"","Yes") -> Yes
A93: Patient forms - printing | B93: Data collection | C93: =0.08 -> 0.08 | D93: per form | E93: 2013 | F93: RSA GF proposal | I93: =IF(G93="",VLOOKUP(IF(Inflation!$B$1-Ingredients!E93>0,Inflation!$B$1-Ingredients!E93,0),Inflation!$C$5:$D$20,2,FALSE)*C93,-PMT(0.08,G93,VLOOKUP(IF(Inflation!$B$1-Ingredients!E93>0,Inflation!$B$1-Ingredients!E93,0),Inflation!$C$5:$D$20,2,FALSE)*C93,0,1))/MAX(1,H93) -> 0.14136812 | J93: =IF(H93="",D93,"REDO") -> per form | L93: =IF(IFERROR(INDEX(InterventionCosts!$A$2:$A$2363,(MATCH(A93,InterventionCosts!$B$2:$B$2363,0))),1)=1,"","Yes") -> Yes
A94: Space | B94: Rental Cost | C94: 150 | D94: per square meter | E94: 2024 | F94: Average retail price for B & C grade commercial property (property24.com) | I94: =IF(G94="",VLOOKUP(IF(Inflation!$B$1-Ingredients!E94>0,Inflation!$B$1-Ingredients!E94,0),Inflation!$C$5:$D$20,2,FALSE)*C94,-PMT(0.08,G94,VLOOKUP(IF(Inflation!$B$1-Ingredients!E94>0,Inflation!$B$1-Ingredients!E94,0),Inflation!$C$5:$D$20,2,FALSE)*C94,0,1))/MAX(1,H94) -> 150 | J94: =IF(H94="",D94,"REDO") -> per square meter | L94: =IF(IFERROR(INDEX(InterventionCosts!$A$2:$A$2363,(MATCH(A94,InterventionCosts!$B$2:$B$2363,0))),1)=1,"","Yes") -> Yes
A95: Transportation allowance - per month | B95: for peer educators/ peer motivators, CHWs | C95: =75*8 -> 600 | D95: pp per month | E95: 2022 | F95: GF Grant Portfolio Budget 2022 (Steve's Cohen personal communication) | I95: =IF(G95="",VLOOKUP(IF(Inflation!$B$1-Ingredients!E95>0,Inflation!$B$1-Ingredients!E95,0),Inflation!$C$5:$D$20,2,FALSE)*C95,-PMT(0.08,G95,VLOOKUP(IF(Inflation!$B$1-Ingredients!E95>0,Inflation!$B$1-Ingredients!E95,0),Inflation!$C$5:$D$20,2,FALSE)*C95,0,1))/MAX(1,H95) -> 685.6566 | J95: =IF(H95="",D95,"REDO") -> pp per month | L95: =IF(IFERROR(INDEX(InterventionCosts!$A$2:$A$2363,(MATCH(A95,InterventionCosts!$B$2:$B$2363,0))),1)=1,"","Yes") -> Yes
A96: Smith room | C96: =877 -> 877 | D96: per room | E96: 2016 | F96: https://doi.org/10.1038/s41598-019-49109-w | I96: =IF(G96="",VLOOKUP(IF(Inflation!$B$1-Ingredients!E96>0,Inflation!$B$1-Ingredients!E96,0),Inflation!$C$5:$D$20,2,FALSE)*C96,-PMT(0.08,G96,VLOOKUP(IF(Inflation!$B$1-Ingredients!E96>0,Inflation!$B$1-Ingredients!E96,0),Inflation!$C$5:$D$20,2,FALSE)*C96,0,1))/MAX(1,H96) -> 1321.1101 | J96: =IF(H96="",D96,"REDO") -> per room | L96: =IF(IFERROR(INDEX(InterventionCosts!$A$2:$A$2363,(MATCH(A96,InterventionCosts!$B$2:$B$2363,0))),1)=1,"","Yes") -> Yes
A97: Smith room furniture | C97: =167.27 -> 167.27 | D97: per room | E97: 2016 | F97: https://doi.org/10.1038/s41598-019-49109-w | I97: =IF(G97="",VLOOKUP(IF(Inflation!$B$1-Ingredients!E97>0,Inflation!$B$1-Ingredients!E97,0),Inflation!$C$5:$D$20,2,FALSE)*C97,-PMT(0.08,G97,VLOOKUP(IF(Inflation!$B$1-Ingredients!E97>0,Inflation!$B$1-Ingredients!E97,0),Inflation!$C$5:$D$20,2,FALSE)*C97,0,1))/MAX(1,H97) -> 251.97502 | J97: =IF(H97="",D97,"REDO") -> per room | L97: =IF(IFERROR(INDEX(InterventionCosts!$A$2:$A$2363,(MATCH(A97,InterventionCosts!$B$2:$B$2363,0))),1)=1,"","Yes") -> Yes
A98: Tabana Room | C98: =348 -> 348 | D98: per room | E98: 2016 | F98: https://doi.org/10.1038/s41598-019-49109-w | I98: =IF(G98="",VLOOKUP(IF(Inflation!$B$1-Ingredients!E98>0,Inflation!$B$1-Ingredients!E98,0),Inflation!$C$5:$D$20,2,FALSE)*C98,-PMT(0.08,G98,VLOOKUP(IF(Inflation!$B$1-Ingredients!E98>0,Inflation!$B$1-Ingredients!E98,0),Inflation!$C$5:$D$20,2,FALSE)*C98,0,1))/MAX(1,H98) -> 524.22614 | J98: =IF(H98="",D98,"REDO") -> per room | L98: =IF(IFERROR(INDEX(InterventionCosts!$A$2:$A$2363,(MATCH(A98,InterventionCosts!$B$2:$B$2363,0))),1)=1,"","Yes") -> Yes
A99: Tabana Room equipment | C99: =109.15 -> 109.15 | D99: per room | E99: 2016 | F99: https://doi.org/10.1038/s41598-019-49109-w | I99: =IF(G99="",VLOOKUP(IF(Inflation!$B$1-Ingredients!E99>0,Inflation!$B$1-Ingredients!E99,0),Inflation!$C$5:$D$20,2,FALSE)*C99,-PMT(0.08,G99,VLOOKUP(IF(Inflation!$B$1-Ingredients!E99>0,Inflation!$B$1-Ingredients!E99,0),Inflation!$C$5:$D$20,2,FALSE)*C99,0,1))/MAX(1,H99) -> 164.42323 | J99: =IF(H99="",D99,"REDO") -> per room | L99: =IF(IFERROR(INDEX(InterventionCosts!$A$2:$A$2363,(MATCH(A99,InterventionCosts!$B$2:$B$2363,0))),1)=1,"","Yes") -> Yes
A100: Reception (large) | C100: =1791.1179 -> 1791.1179 | D100: monthly cost | E100: 2016 | F100: https://doi.org/10.1038/s41598-019-49109-w | I100: =IF(G100="",VLOOKUP(IF(Inflation!$B$1-Ingredients!E100>0,Inflation!$B$1-Ingredients!E100,0),Inflation!$C$5:$D$20,2,FALSE)*C100,-PMT(0.08,G100,VLOOKUP(IF(Inflation!$B$1-Ingredients!E100>0,Inflation!$B$1-Ingredients!E100,0),Inflation!$C$5:$D$20,2,FALSE)*C100,0,1))/MAX(1,H100) -> 2698.1346 | J100: =IF(H100="",D100,"REDO") -> monthly cost | L100: =IF(IFERROR(INDEX(InterventionCosts!$A$2:$A$2363,(MATCH(A100,InterventionCosts!$B$2:$B$2363,0))),1)=1,"","Yes") -> Yes
...

Sheet InterventionCosts
A1: Intervention | B1: Ingredient | C1: Source for inclusion in intervention | D1: Cost Category | E1: ="Unit Cost (ZAR "&CostYear&")" -> Unit Cost (ZAR 2024) | F1: Unit | G1: Cost year (original source) | H1: Source of unit cost | I1: Quantity | J1: Source of quantity | K1: Total Cost | L1: Notes
A2: Condom distribution in clinics | B2: Female condom | C2: Assumption | D2: Consumables | E2: =IF(B2="","",INDEX(Ingredients!$I$1:$I$5013,(MATCH(InterventionCosts!B2,Ingredients!$A$1:$A$5013,0)))) -> 9.816359 | F2: =INDEX(Ingredients!J$1:J$265,(MATCH(InterventionCosts!B2,Ingredients!A$1:A$265,0))) -> per condom | G2: =IF(B2="","",INDEX(Ingredients!$E$1:$E$238,(MATCH(InterventionCosts!B2,Ingredients!A$1:A$238,0)))) -> 2024 | H2: =INDEX(Ingredients!$F$1:$F$120,(MATCH(InterventionCosts!B2,Ingredients!A$1:A$120,0))) -> http://www.treasury.gov.za/divisions/ocpo/ostb/contracts/RT75-2021.zip | I2: 0.017681726 | J2: https://www.treasury.gov.za/divisions/ocpo/ostb/contracts/RT75-2021.zip | K2: =E2*I2 -> 0.17357017
A3: Condom distribution in clinics | B3: Male condom | C3: Assumption | D3: Consumables | E3: =IF(B3="","",INDEX(Ingredients!$I$1:$I$5013,(MATCH(InterventionCosts!B3,Ingredients!$A$1:$A$5013,0)))) -> 0.6193946 | F3: =INDEX(Ingredients!J$1:J$265,(MATCH(InterventionCosts!B3,Ingredients!A$1:A$265,0))) -> per condom | G3: =IF(B3="","",INDEX(Ingredients!$E$1:$E$238,(MATCH(InterventionCosts!B3,Ingredients!A$1:A$238,0)))) -> 2024 | H3: =INDEX(Ingredients!$F$1:$F$120,(MATCH(InterventionCosts!B3,Ingredients!A$1:A$120,0))) -> https://www.treasury.gov.za/divisions/ocpo/ostb/contracts/RT75-2021.zip | I3: 0.98231827 | J3: https://www.treasury.gov.za/divisions/ocpo/ostb/contracts/RT75-2021.zip | K3: =E3*I3 -> 0.60844263
A4: Condom distribution in clinics | B4: Distribution Costs (Female Condom) | C4: Provincial strategic implementation plans (Steve Cohen, personal communication) | D4: Overheads | E4: =IF(B4="","",INDEX(Ingredients!$I$1:$I$5013,(MATCH(InterventionCosts!B4,Ingredients!$A$1:$A$5013,0)))) -> 2.0987375 | F4: =INDEX(Ingredients!J$1:J$265,(MATCH(InterventionCosts!B4,Ingredients!A$1:A$265,0))) -> per condom distributed | G4: =IF(B4="","",INDEX(Ingredients!$E$1:$E$238,(MATCH(InterventionCosts!B4,Ingredients!A$1:A$238,0)))) -> 2023 | H4: =INDEX(Ingredients!$F$1:$F$120,(MATCH(InterventionCosts!B4,Ingredients!A$1:A$120,0))) -> Provincial strategic implementation plans (Steve Cohen, personal communication) | I4: 0.017681726 | J4: Provincial strategic implementation plans (Steve Cohen, personal communication) | K4: =E4*I4 -> 0.037109302
A5: Condom distribution in clinics | B5: Distribution Costs (Male Condom) | C5: Provincial strategic implementation plans (Steve Cohen, personal communication) | D5: Overheads | E5: =IF(B5="","",INDEX(Ingredients!$I$1:$I$5013,(MATCH(InterventionCosts!B5,Ingredients!$A$1:$A$5013,0)))) -> 0.13242656 | F5: =INDEX(Ingredients!J$1:J$265,(MATCH(InterventionCosts!B5,Ingredients!A$1:A$265,0))) -> per condom distributed | G5: =IF(B5="","",INDEX(Ingredients!$E$1:$E$238,(MATCH(InterventionCosts!B5,Ingredients!A$1:A$238,0)))) -> 2023 | H5: =INDEX(Ingredients!$F$1:$F$120,(MATCH(InterventionCosts!B5,Ingredients!A$1:A$120,0))) -> Provincial strategic implementation plans (Steve Cohen, personal communication) | I5: 0.98231827 | J5: Provincial strategic implementation plans (Steve Cohen, personal communication) | K5: =E5*I5 -> 0.13008503
A6: Condom distribution in clinics | F6: Cost per intervention | G6: =IF(B6="","",INDEX(Ingredients!$E$1:$E$120,(MATCH(InterventionCosts!B6,Ingredients!A$1:A$120,0)))) | H6: =IF(B6="","",INDEX(Ingredients!$F$3:$F$119,(MATCH(InterventionCosts!B6,Ingredients!A$1:A$265,0)))) | L6: =SUM(K2:K5) -> 0.94920714
A7: Condom distribution in clinics | F7: Unit | G7: =IF(B7="","",INDEX(Ingredients!$E$1:$E$120,(MATCH(InterventionCosts!B7,Ingredients!A$1:A$120,0)))) | H7: =IF(B7="","",INDEX(Ingredients!$F$3:$F$119,(MATCH(InterventionCosts!B7,Ingredients!A$1:A$265,0)))) | L7: per condom distributed
G8: =IF(B8="","",INDEX(Ingredients!$E$1:$E$120,(MATCH(InterventionCosts!B8,Ingredients!A$1:A$120,0)))) | H8: =IF(B8="","",INDEX(Ingredients!$F$3:$F$119,(MATCH(InterventionCosts!B8,Ingredients!A$1:A$265,0))))
A9: Condom distribution in non-traditional outlets (hotels; shops; malls) | B9: Male condom | C9: Assumption | D9: Consumables | E9: =IF(B9="","",INDEX(Ingredients!$I$1:$I$5013,(MATCH(InterventionCosts!B9,Ingredients!$A$1:$A$5013,0)))) -> 0.6193946 | F9: =INDEX(Ingredients!J$1:J$265,(MATCH(InterventionCosts!B9,Ingredients!A$1:A$265,0))) -> per condom | G9: =IF(B9="","",INDEX(Ingredients!$E$1:$E$238,(MATCH(InterventionCosts!B9,Ingredients!A$1:A$238,0)))) -> 2024 | H9: =INDEX(Ingredients!$F$1:$F$120,(MATCH(InterventionCosts!B9,Ingredients!A$1:A$120,0))) -> https://www.treasury.gov.za/divisions/ocpo/ostb/contracts/RT75-2021.zip | I9: 0.98231827 | J9: https://www.treasury.gov.za/divisions/ocpo/ostb/contracts/RT75-2021.zip | K9: =E9*I9 -> 0.60844263
A10: Condom distribution in non-traditional outlets (hotels; shops; malls) | B10: Female condom | C10: Assumption | D10: Consumables | E10: =IF(B10="","",INDEX(Ingredients!$I$1:$I$5013,(MATCH(InterventionCosts!B10,Ingredients!$A$1:$A$5013,0)))) -> 9.816359 | F10: =INDEX(Ingredients!J$1:J$265,(MATCH(InterventionCosts!B10,Ingredients!A$1:A$265,0))) -> per condom | G10: =IF(B10="","",INDEX(Ingredients!$E$1:$E$238,(MATCH(InterventionCosts!B10,Ingredients!A$1:A$238,0)))) -> 2024 | H10: =INDEX(Ingredients!$F$1:$F$120,(MATCH(InterventionCosts!B10,Ingredients!A$1:A$120,0))) -> http://www.treasury.gov.za/divisions/ocpo/ostb/contracts/RT75-2021.zip | I10: 0.017681726 | J10: https://www.treasury.gov.za/divisions/ocpo/ostb/contracts/RT75-2021.zip | K10: =E10*I10 -> 0.17357017
A11: Condom distribution in non-traditional outlets (hotels; shops; malls) | B11: Distribution costs for non-traditional outlets (Male Condom) | C11: Provincial strategic implementation plans (Steve Cohen, personal communication) | D11: Overheads | E11: =IF(B11="","",INDEX(Ingredients!$I$1:$I$5013,(MATCH(InterventionCosts!B11,Ingredients!$A$1:$A$5013,0)))) -> 0.26485313 | F11: =INDEX(Ingredients!J$1:J$265,(MATCH(InterventionCosts!B11,Ingredients!A$1:A$265,0))) -> per condom distributed | G11: =IF(B11="","",INDEX(Ingredients!$E$1:$E$238,(MATCH(InterventionCosts!B11,Ingredients!A$1:A$238,0)))) -> 2023 | H11: =INDEX(Ingredients!$F$1:$F$120,(MATCH(InterventionCosts!B11,Ingredients!A$1:A$120,0))) -> Provincial strategic implementation plans (Steve Cohen, personal communication) | I11: 0.98231827 | J11: Provincial strategic implementation plans (Steve Cohen, personal communication) | K11: =E11*I11 -> 0.26017007
A12: Condom distribution in non-traditional outlets (hotels; shops; malls) | B12: Distribution costs for non-traditional outlets (Female Condom) | C12: Provincial strategic implementation plans (Steve Cohen, personal communication) | D12: Overheads | E12: =IF(B12="","",INDEX(Ingredients!$I$1:$I$5013,(MATCH(InterventionCosts!B12,Ingredients!$A$1:$A$5013,0)))) -> 4.1974751 | F12: =INDEX(Ingredients!J$1:J$265,(MATCH(InterventionCosts!B12,Ingredients!A$1:A$265,0))) -> per condom distributed | G12: =IF(B12="","",INDEX(Ingredients!$E$1:$E$238,(MATCH(InterventionCosts!B12,Ingredients!A$1:A$238,0)))) -> 2023 | H12: =INDEX(Ingredients!$F$1:$F$120,(MATCH(InterventionCosts!B12,Ingredients!A$1:A$120,0))) -> Provincial strategic implementation plans (Steve Cohen, personal communication) | I12: 0.017681726 | J12: Provincial strategic implementation plans (Steve Cohen, personal communication) | K12: =E12*I12 -> 0.074218603
A13: Condom distribution in non-traditional outlets (hotels; shops; malls) | F13: Cost per intervention | G13: =IF(B13="","",INDEX(Ingredients!$E$1:$E$120,(MATCH(InterventionCosts!B13,Ingredients!A$1:A$120,0)))) | H13: =IF(B13="","",INDEX(Ingredients!$F$3:$F$119,(MATCH(InterventionCosts!B13,Ingredients!A$1:A$265,0)))) | L13: =SUM(K9:K12) -> 1.1164015
A14: Condom distribution in non-traditional outlets (hotels; shops; malls) | F14: Unit | G14: =IF(B14="","",INDEX(Ingredients!$E$1:$E$120,(MATCH(InterventionCosts!B14,Ingredients!A$1:A$120,0)))) | H14: =IF(B14="","",INDEX(Ingredients!$F$3:$F$119,(MATCH(InterventionCosts!B14,Ingredients!A$1:A$265,0)))) | L14: per condom distributed
G15: =IF(B15="","",INDEX(Ingredients!$E$1:$E$120,(MATCH(InterventionCosts!B15,Ingredients!A$1:A$120,0)))) | H15: =IF(B15="","",INDEX(Ingredients!$F$3:$F$119,(MATCH(InterventionCosts!B15,Ingredients!A$1:A$265,0))))
A16: Medical male circumcision | B16: Medical male circumcision | C16: Assumption | D16: Other | E16: =IF(B16="","",INDEX(Ingredients!$I$1:$I$5013,(MATCH(InterventionCosts!B16,Ingredients!$A$1:$A$5013,0)))) -> 1481.154 | F16: =INDEX(Ingredients!J$1:J$265,(MATCH(InterventionCosts!B16,Ingredients!A$1:A$265,0))) -> per circumcision (Average) | G16: =IF(B16="","",INDEX(Ingredients!$E$1:$E$238,(MATCH(InterventionCosts!B16,Ingredients!A$1:A$238,0)))) -> 2024 | H16: =IF(B16="","",INDEX(Ingredients!$F$3:$F$238,(MATCH(InterventionCosts!B16,Ingredients!A$3:A$238,0)))) -> Contract Circular RT35-2019, weighted average based on target volume | I16: 1 | J16: Assumed 1 per person circumcised | K16: =E16*I16 -> 1481.154
A17: Medical male circumcision | E17: =IF(B17="","",INDEX(Ingredients!$I$1:$I$5013,(MATCH(InterventionCosts!B17,Ingredients!$A$1:$A$5013,0)))) | F17: Cost per intervention | G17: =IF(B17="","",INDEX(Ingredients!$E$1:$E$238,(MATCH(InterventionCosts!B17,Ingredients!A$1:A$238,0)))) | H17: =IF(B17="","",INDEX(Ingredients!$F$3:$F$119,(MATCH(InterventionCosts!B17,Ingredients!A$1:A$265,0)))) | L17: =K16 -> 1481.154
A18: Medical male circumcision | E18: =IF(B18="","",INDEX(Ingredients!$I$1:$I$5013,(MATCH(InterventionCosts!B18,Ingredients!$A$1:$A$5013,0)))) | F18: Unit | G18: =IF(B18="","",INDEX(Ingredients!$E$1:$E$238,(MATCH(InterventionCosts!B18,Ingredients!A$1:A$238,0)))) | H18: =IF(B18="","",INDEX(Ingredients!$F$3:$F$119,(MATCH(InterventionCosts!B18,Ingredients!A$1:A$265,0)))) | L18: per circumcision
A19: Early infant male circumcision | F19: Cost per intervention | L19: =L17/2 -> 740.577
A20: Early infant male circumcision | F20: Unit | L20: per circumcision
G21: =IF(B21="","",INDEX(Ingredients!$E$1:$E$238,(MATCH(InterventionCosts!B21,Ingredients!A$1:A$238,0)))) | H21: =IF(B21="","",INDEX(Ingredients!$F$3:$F$119,(MATCH(InterventionCosts!B21,Ingredients!A$1:A$265,0))))
A22: PMTCT (mother not on any ART; presentation in labour) | B22: NVP suspension first 3 months | C22: National ART cost model (Meyer Rath) | D22: Drugs | E22: =IF(B22="","",INDEX(Ingredients!$I$1:$I$5013,(MATCH(InterventionCosts!B22,Ingredients!$A$1:$A$5013,0)))) -> 65.86875 | F22: =INDEX(Ingredients!J$1:J$265,(MATCH(InterventionCosts!B22,Ingredients!A$1:A$265,0))) -> per child | G22: =IF(B22="","",INDEX(Ingredients!$E$1:$E$238,(MATCH(InterventionCosts!B22,Ingredients!A$1:A$238,0)))) -> 2024 | H22: =INDEX(Ingredients!$F$1:$F$318,(MATCH(InterventionCosts!B22,Ingredients!A$1:A$318,0))) -> Master Procurement Circular May 2024 | I22: 0.25 | J22: Assumed - 3 months | K22: =E22*I22 -> 16.467188
A23: PMTCT (mother not on any ART; presentation in labour) | B23: NVP suspension last 9 months | C23: National ART cost model (Meyer Rath) | D23: Drugs | E23: =IF(B23="","",INDEX(Ingredients!$I$1:$I$5013,(MATCH(InterventionCosts!B23,Ingredients!$A$1:$A$5013,0)))) -> 316.17 | F23: =INDEX(Ingredients!J$1:J$265,(MATCH(InterventionCosts!B23,Ingredients!A$1:A$265,0))) -> per child | G23: =IF(B23="","",INDEX(Ingredients!$E$1:$E$238,(MATCH(InterventionCosts!B23,Ingredients!A$1:A$238,0)))) -> 2024 | H23: =INDEX(Ingredients!$F$1:$F$318,(MATCH(InterventionCosts!B23,Ingredients!A$1:A$318,0))) -> Master Procurement Circular May 2024 | I23: 0.75 | J23: Assumed - 9 months | K23: =E23*I23 -> 237.1275
A24: PMTCT (mother not on any ART; presentation in labour) | B24: AZT 300mg | C24: National ART cost model (Meyer Rath) | D24: Drugs | E24: =IF(B24="","",INDEX(Ingredients!$I$1:$I$5013,(MATCH(InterventionCosts!B24,Ingredients!$A$1:$A$5013,0)))) -> 6.28 | F24: =INDEX(Ingredients!J$1:J$265,(MATCH(InterventionCosts!B24,Ingredients!A$1:A$265,0))) -> per dose | G24: =IF(B24="","",INDEX(Ingredients!$E$1:$E$238,(MATCH(InterventionCosts!B24,Ingredients!A$1:A$238,0)))) -> 2024 | H24: =INDEX(Ingredients!$F$1:$F$318,(MATCH(InterventionCosts!B24,Ingredients!A$1:A$318,0))) -> Master Procurement Circular May 2024 | I24: 1 | J24: PMTCT guidelines | K24: =E24*I24 -> 6.28
